Workbook

Sheet AutoimmuneDiseases
A1: AutoimmuneDiseaseId | B1: DiseaseLabel | C1: IsComplexDisease | D1: Name | E1: RelativePath | F1: CountOfDiseaseStages | G1: CountOfInterventionTargets | H1: DiseaseStages | I1: Treatments | J1: ClinicalPhenotypes | K1: IndividualPredictions | L1: CounterfactualTrajectories | M1: InterventionTargets
A2: sle | B2: Systemic Lupus Erythematosus | C2: TRUE | D2: =B2 -> Systemic Lupus Erythematosus | E2: ="/diseases/" & A2 -> /diseases/sle | F2: =COUNTIFS(DiseaseStages!D2:D999, A2) -> 3 | G2: =COUNTIFS(InterventionTargets!D2:D999, A2) -> 7
A3: ra | B3: Rheumatoid Arthritis | C3: TRUE | D3: =B3 -> Rheumatoid Arthritis | E3: ="/diseases/" & A3 -> /diseases/ra | F3: =COUNTIFS(DiseaseStages!D2:D999, A3) -> 2 | G3: =COUNTIFS(InterventionTargets!D2:D999, A3) -> 0
A4: psa | B4: Psoriatic Arthritis | C4: TRUE | D4: =B4 -> Psoriatic Arthritis | E4: ="/diseases/" & A4 -> /diseases/psa | F4: =COUNTIFS(DiseaseStages!D2:D999, A4) -> 1 | G4: =COUNTIFS(InterventionTargets!D2:D999, A4) -> 4

Sheet DiseaseStages
A1: DiseaseStageId | B1: StageLabel | C1: SortOrder | D1: AutoimmuneDisease | E1: Name | F1: ParentPath | G1: RelativePath | H1: AutoimmuneDiseaseDiseaseLabel | I1: IsPresymptomatic
A2: sle-presymptomatic | B2: Presymptomatic | C2: 1 | D2: sle | E2: =H2 & " — " & B2 -> Systemic Lupus Erythematosus — Presymptomatic | F2: =INDEX(AutoimmuneDiseases!E2:E999, MATCH(D2,AutoimmuneDiseases!A2:A999, 0)) -> /diseases/sle | G2: =F2 & "/stages/" & A2 -> /diseases/sle/stages/sle-presymptomatic | H2: =INDEX(AutoimmuneDiseases!B2:B999, MATCH(D2,AutoimmuneDiseases!A2:A999, 0)) -> Systemic Lupus Erythematosus | I2: =IF(B2 = "Presymptomatic", TRUE(), FALSE()) -> TRUE
A3: sle-active | B3: Active | C3: 2 | D3: sle | E3: =H3 & " — " & B3 -> Systemic Lupus Erythematosus — Active | F3: =INDEX(AutoimmuneDiseases!E2:E999, MATCH(D3,AutoimmuneDiseases!A2:A999, 0)) -> /diseases/sle | G3: =F3 & "/stages/" & A3 -> /diseases/sle/stages/sle-active | H3: =INDEX(AutoimmuneDiseases!B2:B999, MATCH(D3,AutoimmuneDiseases!A2:A999, 0)) -> Systemic Lupus Erythematosus | I3: =IF(B3 = "Presymptomatic", TRUE(), FALSE()) -> FALSE
A4: sle-remission | B4: Remission | C4: 3 | D4: sle | E4: =H4 & " — " & B4 -> Systemic Lupus Erythematosus — Remission | F4: =INDEX(AutoimmuneDiseases!E2:E999, MATCH(D4,AutoimmuneDiseases!A2:A999, 0)) -> /diseases/sle | G4: =F4 & "/stages/" & A4 -> /diseases/sle/stages/sle-remission | H4: =INDEX(AutoimmuneDiseases!B2:B999, MATCH(D4,AutoimmuneDiseases!A2:A999, 0)) -> Systemic Lupus Erythematosus | I4: =IF(B4 = "Presymptomatic", TRUE(), FALSE()) -> FALSE
A5: ra-active | B5: Active | C5: 1 | D5: ra | E5: =H5 & " — " & B5 -> Rheumatoid Arthritis — Active | F5: =INDEX(AutoimmuneDiseases!E2:E999, MATCH(D5,AutoimmuneDiseases!A2:A999, 0)) -> /diseases/ra | G5: =F5 & "/stages/" & A5 -> /diseases/ra/stages/ra-active | H5: =INDEX(AutoimmuneDiseases!B2:B999, MATCH(D5,AutoimmuneDiseases!A2:A999, 0)) -> Rheumatoid Arthritis | I5: =IF(B5 = "Presymptomatic", TRUE(), FALSE()) -> FALSE
A6: ra-remission | B6: Remission | C6: 2 | D6: ra | E6: =H6 & " — " & B6 -> Rheumatoid Arthritis — Remission | F6: =INDEX(AutoimmuneDiseases!E2:E999, MATCH(D6,AutoimmuneDiseases!A2:A999, 0)) -> /diseases/ra | G6: =F6 & "/stages/" & A6 -> /diseases/ra/stages/ra-remission | H6: =INDEX(AutoimmuneDiseases!B2:B999, MATCH(D6,AutoimmuneDiseases!A2:A999, 0)) -> Rheumatoid Arthritis | I6: =IF(B6 = "Presymptomatic", TRUE(), FALSE()) -> FALSE
A7: psa-active | B7: Active | C7: 1 | D7: psa | E7: =H7 & " — " & B7 -> Psoriatic Arthritis — Active | F7: =INDEX(AutoimmuneDiseases!E2:E999, MATCH(D7,AutoimmuneDiseases!A2:A999, 0)) -> /diseases/psa | G7: =F7 & "/stages/" & A7 -> /diseases/psa/stages/psa-active | H7: =INDEX(AutoimmuneDiseases!B2:B999, MATCH(D7,AutoimmuneDiseases!A2:A999, 0)) -> Psoriatic Arthritis | I7: =IF(B7 = "Presymptomatic", TRUE(), FALSE()) -> FALSE

Sheet Tissues
A1: TissueId | B1: TissueLabel | C1: Name | D1: RelativePath | E1: CountOfOmicsAssays | F1: OmicsAssays
A2: blood | B2: Blood | C2: =B2 -> Blood | D2: ="/tissues/" & A2 -> /tissues/blood | E2: =COUNTIFS(OmicsAssays!E2:E999, A2) -> 36
A3: gut | B3: Gut | C3: =B3 -> Gut | D3: ="/tissues/" & A3 -> /tissues/gut | E3: =COUNTIFS(OmicsAssays!E2:E999, A3) -> 0
A4: synovium | B4: Synovium | C4: =B4 -> Synovium | D4: ="/tissues/" & A4 -> /tissues/synovium | E4: =COUNTIFS(OmicsAssays!E2:E999, A4) -> 0
A5: skin | B5: Skin | C5: =B5 -> Skin | D5: ="/tissues/" & A5 -> /tissues/skin | E5: =COUNTIFS(OmicsAssays!E2:E999, A5) -> 0
A6: kidney | B6: Kidney | C6: =B6 -> Kidney | D6: ="/tissues/" & A6 -> /tissues/kidney | E6: =COUNTIFS(OmicsAssays!E2:E999, A6) -> 0

Sheet OmicsModalities
A1: OmicsModalityId | B1: ModalityLabel | C1: IsSingleCell | D1: Name | E1: RelativePath | F1: CountOfOmicsAssays | G1: OmicsAssays
A2: long-read-genomes | B2: Phased Telomere-to-Telomere Long-Read Genomes | C2: FALSE | D2: =B2 -> Phased Telomere-to-Telomere Long-Read Genomes | E2: ="/omics-modalities/" & A2 -> /omics-modalities/long-read-genomes | F2: =COUNTIFS(OmicsAssays!D2:D999, A2) -> 0
A3: rna-seq | B3: RNA-seq | C3: FALSE | D3: =B3 -> RNA-seq | E3: ="/omics-modalities/" & A3 -> /omics-modalities/rna-seq | F3: =COUNTIFS(OmicsAssays!D2:D999, A3) -> 12
A4: single-cell-rna | B4: Single-Cell RNA-seq | C4: TRUE | D4: =B4 -> Single-Cell RNA-seq | E4: ="/omics-modalities/" & A4 -> /omics-modalities/single-cell-rna | F4: =COUNTIFS(OmicsAssays!D2:D999, A4) -> 0
A5: atac-seq | B5: ATAC-seq | C5: FALSE | D5: =B5 -> ATAC-seq | E5: ="/omics-modalities/" & A5 -> /omics-modalities/atac-seq | F5: =COUNTIFS(OmicsAssays!D2:D999, A5) -> 12
A6: proteomics | B6: Proteomics | C6: FALSE | D6: =B6 -> Proteomics | E6: ="/omics-modalities/" & A6 -> /omics-modalities/proteomics | F6: =COUNTIFS(OmicsAssays!D2:D999, A6) -> 12
A7: microbiome | B7: Microbiome | C7: FALSE | D7: =B7 -> Microbiome | E7: ="/omics-modalities/" & A7 -> /omics-modalities/microbiome | F7: =COUNTIFS(OmicsAssays!D2:D999, A7) -> 0
A8: methylome | B8: Methylome (sparse context) | C8: FALSE | D8: =B8 -> Methylome (sparse context) | E8: ="/omics-modalities/" & A8 -> /omics-modalities/methylome | F8: =COUNTIFS(OmicsAssays!D2:D999, A8) -> 0
A9: hi-c | B9: Chromatin Conformation Hi-C (sparse context) | C9: FALSE | D9: =B9 -> Chromatin Conformation Hi-C (sparse context) | E9: ="/omics-modalities/" & A9 -> /omics-modalities/hi-c | F9: =COUNTIFS(OmicsAssays!D2:D999, A9) -> 0

Sheet FederatedDatasets
A1: FederatedDatasetId | B1: NodeLabel | C1: Region | D1: IsPrivacyPreserving | E1: Name | F1: RelativePath | G1: CountOfIndividuals | H1: Individuals | I1: OmicsAssays | J1: CohortReplications
A2: fed-europe | B2: European Reference Node | C2: Europe | D2: TRUE | E2: =B2 -> European Reference Node | F2: ="/datasets/" & A2 -> /datasets/fed-europe | G2: =COUNTIFS(Individuals!G2:G999, A2) -> 4
A3: fed-east-asia | B3: East Asia Federated Node | C3: East Asia | D3: TRUE | E3: =B3 -> East Asia Federated Node | F3: ="/datasets/" & A3 -> /datasets/fed-east-asia | G3: =COUNTIFS(Individuals!G2:G999, A3) -> 1
A4: fed-west-africa | B4: West Africa Federated Node | C4: West Africa | D4: TRUE | E4: =B4 -> West Africa Federated Node | F4: ="/datasets/" & A4 -> /datasets/fed-west-africa | G4: =COUNTIFS(Individuals!G2:G999, A4) -> 1
A5: fed-amazon | B5: Amazon Indigenous Cohort | C5: Amazon Basin | D5: TRUE | E5: =B5 -> Amazon Indigenous Cohort | F5: ="/datasets/" & A5 -> /datasets/fed-amazon | G5: =COUNTIFS(Individuals!G2:G999, A5) -> 4

Sheet VariantTypes
A1: VariantTypeId | B1: TypeLabel | C1: IsRareVariantClass | D1: Name | E1: RelativePath | F1: CountOfGenomicVariants | G1: GenomicVariants
A2: regulatory | B2: Regulatory Variant | C2: TRUE | D2: =B2 -> Regulatory Variant | E2: ="/variant-types/" & A2 -> /variant-types/regulatory | F2: =COUNTIFS(GenomicVariants!D2:D999, A2) -> 12
A3: coding | B3: Coding Variant | C3: FALSE | D3: =B3 -> Coding Variant | E3: ="/variant-types/" & A3 -> /variant-types/coding | F3: =COUNTIFS(GenomicVariants!D2:D999, A3) -> 0
A4: hla-haplotype | B4: HLA Haplotype | C4: FALSE | D4: =B4 -> HLA Haplotype | E4: ="/variant-types/" & A4 -> /variant-types/hla-haplotype | F4: =COUNTIFS(GenomicVariants!D2:D999, A4) -> 0
A5: structural | B5: Structural Variant | C5: TRUE | D5: =B5 -> Structural Variant | E5: ="/variant-types/" & A5 -> /variant-types/structural | F5: =COUNTIFS(GenomicVariants!D2:D999, A5) -> 0
A6: de-novo | B6: De Novo Mutation | C6: TRUE | D6: =B6 -> De Novo Mutation | E6: ="/variant-types/" & A6 -> /variant-types/de-novo | F6: =COUNTIFS(GenomicVariants!D2:D999, A6) -> 0

Sheet Individuals
A1: IndividualId | B1: GivenName | C1: FamilyName | D1: AncestryLabel | E1: AgeYears | F1: IsAncestryAbsentFromTraining | G1: FederatedDataset | H1: EnrollmentDate | I1: HasCrypticRelatednessFlag | J1: Name | K1: Slug | L1: RelativePath | M1: FederatedDatasetNodeLabel | N1: CountOfGenomicVariants | O1: CountOfCausalMechanisms | P1: CountOfEpistaticInteractions | Q1: RareVariantBurdenScore | R1: CausalArchitectureScore | S1: IsDevelopmentWindow | T1: IsAgingWindow | U1: CountConfirmedCausalNodes | V1: SumConfirmedCausalConfidence | W1: CountCrossAncestryConfirmedNodes | X1: MaxSeverityScore | Y1: CountHighSeverityPhenotypes | Z1: HasHighSeverityPhenotype | AA1: CountPredictedTreatmentResponses | AB1: HasPredictedTreatmentResponse | AC1: GenomicVariants | AD1: OmicsAssays | AE1: EnvironmentalExposures | AF1: Treatments | AG1: ClinicalPhenotypes | AH1: CausalMechanisms | AI1: EpistaticInteractions | AJ1: CounterfactualTrajectories | AK1: IndividualPredictions | AL1: CaseNarrative | AM1: CountSerologyPanels | AN1: CountPreNephriticSignaturePanels | AO1: IsInPreNephriticSignatureCluster | AP1: SignatureStrength | AQ1: MaxProgressionStateOrder | AR1: LatestSledaiScore | AS1: NephritisProgressionStateKey | AT1: ActivityTier | AU1: IsHighDiseaseActivity | AV1: IsDiseaseProgressing | AW1: TargetPathwayCode | AX1: TargetPathway | AY1: CurrentProgressionStateId | AZ1: ReachableStatesAhead
A2: ind-a-reyes | B2: Ana | C2: Reyes | D2: European | E2: 34 | F2: FALSE | G2: fed-europe | H2: 45026 | I2: FALSE | J2: =B2 & " " & C2 -> Ana Reyes | K2: =SUBSTITUTE(LOWER(C2 & "-" & B2), " ", "-") -> reyes-ana | L2: ="/intake/new-patient/" & K2 -> /intake/new-patient/reyes-ana | M2: =IF(G2 = "", "", INDEX(FederatedDatasets!B2:B999, MATCH(G2,FederatedDatasets!A2:A999, 0))) -> European Reference Node | N2: =COUNTIFS(GenomicVariants!C2:C999, A2) -> 1 | O2: =COUNTIFS(CausalMechanisms!C2:C999, A2) -> 1 | P2: =COUNTIFS(EpistaticInteractions!C2:C999, A2) -> 1 | Q2: =IF(E2 > 0, N2 / E2, 0) -> 0.029411765 | R2: =O2 * 10 + P2 * 5 + Q2 -> 15.029412 | S2: =IF(E2 <= 25, TRUE(), FALSE()) -> FALSE | T2: =IF(E2 >= 60, TRUE(), FALSE()) -> FALSE | U2: =COUNTIFS(CausalMechanisms!C2:C999, A2,CausalMechanisms!AC2:AC999, TRUE()) -> 1 | V2: =SUMIFS(CausalMechanisms!AA2:AA999,CausalMechanisms!C2:C999, A2,CausalMechanisms!AC2:AC999, TRUE()) -> 0.75833333 | W2: =COUNTIFS(CausalMechanisms!C2:C999, A2,CausalMechanisms!AD2:AD999, TRUE()) -> 1 | X2: =_xlfn.MAXIFS(ClinicalPhenotypes!G2:G999,ClinicalPhenotypes!C2:C999, A2) -> 9 | Y2: =COUNTIFS(ClinicalPhenotypes!C2:C999, A2,ClinicalPhenotypes!N2:N999, TRUE()) -> 1 | Z2: =IF(Y2 >= 1, TRUE(), FALSE()) -> TRUE | AA2: =COUNTIFS(Treatments!C2:C999, A2,Treatments!P2:P999, TRUE()) -> 1 | AB2: =IF(AA2 >= 1, TRUE(), FALSE()) -> TRUE | AL2: Ana Reyes, a 34-year-old woman of European ancestry (cohort is in the training set), presents with photosensitive malar rash, arthralgia, and a positive ANA, raising concern for SLE onset. Family history is notable for lupus in a maternal aunt. Genotyping finds the IRF5 regulatory variant rs2004640 at an allele frequency of 0.006 (rare), and allele-specific expression is present at the locus. Functional workup of the IRF5 -> type-I interferon -> SLE-risk edge returns a cis-eQTL in blood RNA-seq with effect 0.91 (SE 0.20), a caQTL in blood ATAC-seq with effect 0.73 (SE 0.19), and a pQTL in blood proteomics with effect 0.66 (SE 0.20) — three assays across two omics modalities, all ancestry-PC and batch adjusted. The edge replicates with a positive effect sign in an East Asian cohort (p=0.004) and in an African cohort (p=0.013), while a European replication is directionally consistent but not significant (p=0.18). Two ancestry-permutation negative controls collapse to the null (permutation effect 0.012 and 0.028, well inside the +/-0.1 null band). The IL-interferon target is druggable (anifrolumab, anti-IFNAR1), giving a perturbable intervention target. For SLE-onset risk, the model's reliability bins each carry coverage of 29-34 held-out individuals, with observed event rates tracking predicted bands closely (e.g. 0.09 observed at the 0.1 band, 0.88 at the 0.9 band). No cryptic-relatedness or assortative-mating leakage was flagged. | AM2: =COUNTIFS(SerologyObservations!B2:B999, A2) -> 2 | AN2: =COUNTIFS(SerologyObservations!B2:B999, A2,SerologyObservations!Q2:Q999, TRUE()) -> 0 | AO2: =IF(AN2>=1,TRUE(),FALSE()) -> FALSE | AP2: =IF(AN2>=2,2,IF(AN2>=1,1,0)) -> 0 | AQ2: =_xlfn.MAXIFS(SerologyObservations!X2:X999,SerologyObservations!B2:B999, A2) -> 0 | AR2: =_xlfn.MAXIFS(SerologyObservations!V2:V999,SerologyObservations!B2:B999, A2) -> 0 | AS2: =IF(AQ2>=5,"BiopsyIndicated",IF(AQ2>=4,"RenalFlareRisk",IF(AQ2>=3,"EarlyNephritis",IF(AQ2>=2,"SerologicActive","PresymptomaticAutoimmunity")))) -> PresymptomaticAutoimmunity | AT2: =IF(AR2>=12,"High / flare",IF(AR2>=6,"Moderate",IF(AR2>=1,"Mild","Quiescent"))) -> Quiescent | AU2: =IF(AR2>=12,TRUE(),FALSE()) -> FALSE | AV2: =IF(OR(AS2="EarlyNephritis",AS2="RenalFlareRisk",AS2="BiopsyIndicated"),TRUE(),FALSE()) -> FALSE | AW2: =_xlfn.MAXIFS(CausalMechanisms!H2:H999,CausalMechanisms!C2:C999, A2) -> 1 | AX2: =IF(AW2=1,"type-I-IFN",IF(AW2=2,"B-cell/autoantibody",IF(AW2=3,"T-cell-costim",IF(AW2=4,"IL-17/23","")))) -> type-I-IFN | AY2: ="lupus-nephritis-progression--" & LOWER(AS2) -> lupus-nephritis-progression--presymptomaticautoimmunity | AZ2: =INDEX(MachineStates!Q2:Q999, MATCH(AY2,MachineStates!A2:A999, 0)) -> #VALUE!
A3: ind-b-okafor | B3: Bili | C3: Okafor | D3: European | E3: 41 | F3: FALSE | G3: fed-europe | H3: 45058 | I3: FALSE | J3: =B3 & " " & C3 -> Bili Okafor | K3: =SUBSTITUTE(LOWER(C3 & "-" & B3), " ", "-") -> okafor-bili | L3: ="/intake/new-patient/" & K3 -> /intake/new-patient/okafor-bili | M3: =IF(G3 = "", "", INDEX(FederatedDatasets!B2:B999, MATCH(G3,FederatedDatasets!A2:A999, 0))) -> European Reference Node | N3: =COUNTIFS(GenomicVariants!C2:C999, A3) -> 1 | O3: =COUNTIFS(CausalMechanisms!C2:C999, A3) -> 1 | P3: =COUNTIFS(EpistaticInteractions!C2:C999, A3) -> 0 | Q3: =IF(E3 > 0, N3 / E3, 0) -> 0.024390244 | R3: =O3 * 10 + P3 * 5 + Q3 -> 10.02439 | S3: =IF(E3 <= 25, TRUE(), FALSE()) -> FALSE | T3: =IF(E3 >= 60, TRUE(), FALSE()) -> FALSE | U3: =COUNTIFS(CausalMechanisms!C2:C999, A3,CausalMechanisms!AC2:AC999, TRUE()) -> 1 | V3: =SUMIFS(CausalMechanisms!AA2:AA999,CausalMechanisms!C2:C999, A3,CausalMechanisms!AC2:AC999, TRUE()) -> 0.75833333 | W3: =COUNTIFS(CausalMechanisms!C2:C999, A3,CausalMechanisms!AD2:AD999, TRUE()) -> 1 | X3: =_xlfn.MAXIFS(ClinicalPhenotypes!G2:G999,ClinicalPhenotypes!C2:C999, A3) -> 8 | Y3: =COUNTIFS(ClinicalPhenotypes!C2:C999, A3,ClinicalPhenotypes!N2:N999, TRUE()) -> 1 | Z3: =IF(Y3 >= 1, TRUE(), FALSE()) -> TRUE | AA3: =COUNTIFS(Treatments!C2:C999, A3,Treatments!P2:P999, TRUE()) -> 1 | AB3: =IF(AA3 >= 1, TRUE(), FALSE()) -> TRUE | AL3: Bili Okafor, a 41-year-old man of European ancestry (in the training set), presents with serositis, fatigue, and a high-titre ANA suggestive of SLE onset. Genotyping finds the IRF5 regulatory variant rs2004640 at an allele frequency of 0.006 (rare), with allele-specific expression present. The IRF5 -> type-I interferon -> SLE-risk edge is supported by a cis-eQTL in blood RNA-seq with effect 0.84 (SE 0.21), a caQTL in blood ATAC-seq with effect 0.79 (SE 0.20), and a pQTL in blood proteomics with effect 0.58 (SE 0.20), spanning two omics modalities and adjusted for ancestry PCs and batch. It replicates positive in an East Asian cohort (p=0.006) and an African cohort (p=0.017), with a non-significant European replication (p=0.22). Two ancestry-permutation controls collapse to the null (permutation effect 0.015 and 0.024 inside +/-0.1). The interferon target is druggable. The mechanism is as solid as Ana's — but the calibration substrate is thin: this site only accrued coverage of 7-14 held-out individuals per reliability bin, far below the 20-count floor needed to trust the predicted-vs-observed match. No cryptic-relatedness leakage was flagged. | AM3: =COUNTIFS(SerologyObservations!B2:B999, A3) -> 2 | AN3: =COUNTIFS(SerologyObservations!B2:B999, A3,SerologyObservations!Q2:Q999, TRUE()) -> 0 | AO3: =IF(AN3>=1,TRUE(),FALSE()) -> FALSE | AP3: =IF(AN3>=2,2,IF(AN3>=1,1,0)) -> 0 | AQ3: =_xlfn.MAXIFS(SerologyObservations!X2:X999,SerologyObservations!B2:B999, A3) -> 0 | AR3: =_xlfn.MAXIFS(SerologyObservations!V2:V999,SerologyObservations!B2:B999, A3) -> 0 | AS3: =IF(AQ3>=5,"BiopsyIndicated",IF(AQ3>=4,"RenalFlareRisk",IF(AQ3>=3,"EarlyNephritis",IF(AQ3>=2,"SerologicActive","PresymptomaticAutoimmunity")))) -> PresymptomaticAutoimmunity | AT3: =IF(AR3>=12,"High / flare",IF(AR3>=6,"Moderate",IF(AR3>=1,"Mild","Quiescent"))) -> Quiescent | AU3: =IF(AR3>=12,TRUE(),FALSE()) -> FALSE | AV3: =IF(OR(AS3="EarlyNephritis",AS3="RenalFlareRisk",AS3="BiopsyIndicated"),TRUE(),FALSE()) -> FALSE | AW3: =_xlfn.MAXIFS(CausalMechanisms!H2:H999,CausalMechanisms!C2:C999, A3) -> 1 | AX3: =IF(AW3=1,"type-I-IFN",IF(AW3=2,"B-cell/autoantibody",IF(AW3=3,"T-cell-costim",IF(AW3=4,"IL-17/23","")))) -> type-I-IFN | AY3: ="lupus-nephritis-progression--" & LOWER(AS3) -> lupus-nephritis-progression--presymptomaticautoimmunity | AZ3: =INDEX(MachineStates!Q2:Q999, MATCH(AY3,MachineStates!A2:A999, 0)) -> #VALUE!
A4: ind-c-chen | B4: Chen | C4: Wei | D4: East Asian | E4: 47 | F4: FALSE | G4: fed-east-asia | H4: 44805 | I4: FALSE | J4: =B4 & " " & C4 -> Chen Wei | K4: =SUBSTITUTE(LOWER(C4 & "-" & B4), " ", "-") -> wei-chen | L4: ="/intake/new-patient/" & K4 -> /intake/new-patient/wei-chen | M4: =IF(G4 = "", "", INDEX(FederatedDatasets!B2:B999, MATCH(G4,FederatedDatasets!A2:A999, 0))) -> East Asia Federated Node | N4: =COUNTIFS(GenomicVariants!C2:C999, A4) -> 1 | O4: =COUNTIFS(CausalMechanisms!C2:C999, A4) -> 1 | P4: =COUNTIFS(EpistaticInteractions!C2:C999, A4) -> 0 | Q4: =IF(E4 > 0, N4 / E4, 0) -> 0.021276596 | R4: =O4 * 10 + P4 * 5 + Q4 -> 10.021277 | S4: =IF(E4 <= 25, TRUE(), FALSE()) -> FALSE | T4: =IF(E4 >= 60, TRUE(), FALSE()) -> FALSE | U4: =COUNTIFS(CausalMechanisms!C2:C999, A4,CausalMechanisms!AC2:AC999, TRUE()) -> 0 | V4: =SUMIFS(CausalMechanisms!AA2:AA999,CausalMechanisms!C2:C999, A4,CausalMechanisms!AC2:AC999, TRUE()) -> 0 | W4: =COUNTIFS(CausalMechanisms!C2:C999, A4,CausalMechanisms!AD2:AD999, TRUE()) -> 0 | X4: =_xlfn.MAXIFS(ClinicalPhenotypes!G2:G999,ClinicalPhenotypes!C2:C999, A4) -> 9 | Y4: =COUNTIFS(ClinicalPhenotypes!C2:C999, A4,ClinicalPhenotypes!N2:N999, TRUE()) -> 1 | Z4: =IF(Y4 >= 1, TRUE(), FALSE()) -> TRUE | AA4: =COUNTIFS(Treatments!C2:C999, A4,Treatments!P2:P999, TRUE()) -> 0 | AB4: =IF(AA4 >= 1, TRUE(), FALSE()) -> FALSE | AL4: Chen Wei, a 47-year-old woman of East Asian ancestry (in the training set), presents with arthritis, oral ulcers, and anti-dsDNA positivity concerning for SLE onset. Genotyping finds the STAT4 regulatory variant rs7574865 at an allele frequency of 0.008 (rare), with allele-specific expression present. The STAT4 -> Th1/IFN -> SLE-risk edge shows a cis-eQTL in blood RNA-seq with effect 1.02 (SE 0.23), a caQTL in blood ATAC-seq with effect 0.61 (SE 0.20), and a pQTL in blood proteomics with effect 0.55 (SE 0.21), across two modalities, ancestry-PC and batch adjusted. Replication is troubling: the effect is positive in an East Asian cohort (p=0.009) but the SIGN FLIPS to negative in an African cohort (p=0.024), and the European replication is non-significant (p=0.27) — only one concordant cohort. Worse, while one ancestry-permutation control collapses (permutation effect 0.013), a second negative control does NOT collapse: its permutation effect is 0.46, far outside the +/-0.1 null band, so the signal is not separable from permuted noise. Reliability bins carry coverage of 28-32 per bin. No cryptic-relatedness leakage was flagged. | AM4: =COUNTIFS(SerologyObservations!B2:B999, A4) -> 2 | AN4: =COUNTIFS(SerologyObservations!B2:B999, A4,SerologyObservations!Q2:Q999, TRUE()) -> 0 | AO4: =IF(AN4>=1,TRUE(),FALSE()) -> FALSE | AP4: =IF(AN4>=2,2,IF(AN4>=1,1,0)) -> 0 | AQ4: =_xlfn.MAXIFS(SerologyObservations!X2:X999,SerologyObservations!B2:B999, A4) -> 0 | AR4: =_xlfn.MAXIFS(SerologyObservations!V2:V999,SerologyObservations!B2:B999, A4) -> 0 | AS4: =IF(AQ4>=5,"BiopsyIndicated",IF(AQ4>=4,"RenalFlareRisk",IF(AQ4>=3,"EarlyNephritis",IF(AQ4>=2,"SerologicActive","PresymptomaticAutoimmunity")))) -> PresymptomaticAutoimmunity | AT4: =IF(AR4>=12,"High / flare",IF(AR4>=6,"Moderate",IF(AR4>=1,"Mild","Quiescent"))) -> Quiescent | AU4: =IF(AR4>=12,TRUE(),FALSE()) -> FALSE | AV4: =IF(OR(AS4="EarlyNephritis",AS4="RenalFlareRisk",AS4="BiopsyIndicated"),TRUE(),FALSE()) -> FALSE | AW4: =_xlfn.MAXIFS(CausalMechanisms!H2:H999,CausalMechanisms!C2:C999, A4) -> 2 | AX4: =IF(AW4=1,"type-I-IFN",IF(AW4=2,"B-cell/autoantibody",IF(AW4=3,"T-cell-costim",IF(AW4=4,"IL-17/23","")))) -> B-cell/autoantibody | AY4: ="lupus-nephritis-progression--" & LOWER(AS4) -> lupus-nephritis-progression--presymptomaticautoimmunity | AZ4: =INDEX(MachineStates!Q2:Q999, MATCH(AY4,MachineStates!A2:A999, 0)) -> #VALUE!
A5: ind-d-santos | B5: Diego | C5: Santos | D5: European | E5: 29 | F5: FALSE | G5: fed-europe | H5: 45311 | I5: TRUE | J5: =B5 & " " & C5 -> Diego Santos | K5: =SUBSTITUTE(LOWER(C5 & "-" & B5), " ", "-") -> santos-diego | L5: ="/intake/new-patient/" & K5 -> /intake/new-patient/santos-diego | M5: =IF(G5 = "", "", INDEX(FederatedDatasets!B2:B999, MATCH(G5,FederatedDatasets!A2:A999, 0))) -> European Reference Node | N5: =COUNTIFS(GenomicVariants!C2:C999, A5) -> 1 | O5: =COUNTIFS(CausalMechanisms!C2:C999, A5) -> 1 | P5: =COUNTIFS(EpistaticInteractions!C2:C999, A5) -> 0 | Q5: =IF(E5 > 0, N5 / E5, 0) -> 0.034482759 | R5: =O5 * 10 + P5 * 5 + Q5 -> 10.034483 | S5: =IF(E5 <= 25, TRUE(), FALSE()) -> FALSE | T5: =IF(E5 >= 60, TRUE(), FALSE()) -> FALSE | U5: =COUNTIFS(CausalMechanisms!C2:C999, A5,CausalMechanisms!AC2:AC999, TRUE()) -> 1 | V5: =SUMIFS(CausalMechanisms!AA2:AA999,CausalMechanisms!C2:C999, A5,CausalMechanisms!AC2:AC999, TRUE()) -> 0.75833333 | W5: =COUNTIFS(CausalMechanisms!C2:C999, A5,CausalMechanisms!AD2:AD999, TRUE()) -> 1 | X5: =_xlfn.MAXIFS(ClinicalPhenotypes!G2:G999,ClinicalPhenotypes!C2:C999, A5) -> 8 | Y5: =COUNTIFS(ClinicalPhenotypes!C2:C999, A5,ClinicalPhenotypes!N2:N999, TRUE()) -> 1 | Z5: =IF(Y5 >= 1, TRUE(), FALSE()) -> TRUE | AA5: =COUNTIFS(Treatments!C2:C999, A5,Treatments!P2:P999, TRUE()) -> 0 | AB5: =IF(AA5 >= 1, TRUE(), FALSE()) -> FALSE | AL5: Diego Santos, a 29-year-old man of European ancestry (in the training set), presents with nephritis and a malar rash concerning for SLE onset. Genotyping finds the IRF5 regulatory variant rs2004640 at an allele frequency of 0.006 (rare), with allele-specific expression present. The IRF5 -> type-I interferon -> SLE-risk edge is fully supported: a cis-eQTL in blood RNA-seq with effect 0.88 (SE 0.20), a caQTL in blood ATAC-seq with effect 0.95 (SE 0.21), and a pQTL in blood proteomics with effect 0.62 (SE 0.20), across two modalities and adjusted for ancestry PCs and batch. It replicates positive in an East Asian cohort (p=0.003) and an African cohort (p=0.019), with a non-significant European replication (p=0.16). Two ancestry-permutation controls collapse to the null (permutation effect 0.009 and 0.031 inside +/-0.1). The interferon target is druggable, and reliability bins carry coverage of 30-36 per bin. However, sample QC raised a cryptic-relatedness / assortative-mating flag for this participant: kinship estimates indicate undeclared relatives inside the cohort, so the prediction may be confounded by leakage rather than the mechanism alone. | AM5: =COUNTIFS(SerologyObservations!B2:B999, A5) -> 3 | AN5: =COUNTIFS(SerologyObservations!B2:B999, A5,SerologyObservations!Q2:Q999, TRUE()) -> 0 | AO5: =IF(AN5>=1,TRUE(),FALSE()) -> FALSE | AP5: =IF(AN5>=2,2,IF(AN5>=1,1,0)) -> 0 | AQ5: =_xlfn.MAXIFS(SerologyObservations!X2:X999,SerologyObservations!B2:B999, A5) -> 5 | AR5: =_xlfn.MAXIFS(SerologyObservations!V2:V999,SerologyObservations!B2:B999, A5) -> 0 | AS5: =IF(AQ5>=5,"BiopsyIndicated",IF(AQ5>=4,"RenalFlareRisk",IF(AQ5>=3,"EarlyNephritis",IF(AQ5>=2,"SerologicActive","PresymptomaticAutoimmunity")))) -> BiopsyIndicated | AT5: =IF(AR5>=12,"High / flare",IF(AR5>=6,"Moderate",IF(AR5>=1,"Mild","Quiescent"))) -> Quiescent | AU5: =IF(AR5>=12,TRUE(),FALSE()) -> FALSE | AV5: =IF(OR(AS5="EarlyNephritis",AS5="RenalFlareRisk",AS5="BiopsyIndicated"),TRUE(),FALSE()) -> TRUE | AW5: =_xlfn.MAXIFS(CausalMechanisms!H2:H999,CausalMechanisms!C2:C999, A5) -> 2 | AX5: =IF(AW5=1,"type-I-IFN",IF(AW5=2,"B-cell/autoantibody",IF(AW5=3,"T-cell-costim",IF(AW5=4,"IL-17/23","")))) -> B-cell/autoantibody | AY5: ="lupus-nephritis-progression--" & LOWER(AS5) -> lupus-nephritis-progression--biopsyindicated | AZ5: =INDEX(MachineStates!Q2:Q999, MATCH(AY5,MachineStates!A2:A999, 0)) -> #VALUE!
A6: ind-e-mensah | B6: Esi | C6: Mensah | D6: African | E6: 38 | F6: FALSE | G6: fed-west-africa | H6: 45122 | I6: FALSE | J6: =B6 & " " & C6 -> Esi Mensah | K6: =SUBSTITUTE(LOWER(C6 & "-" & B6), " ", "-") -> mensah-esi | L6: ="/intake/new-patient/" & K6 -> /intake/new-patient/mensah-esi | M6: =IF(G6 = "", "", INDEX(FederatedDatasets!B2:B999, MATCH(G6,FederatedDatasets!A2:A999, 0))) -> West Africa Federated Node | N6: =COUNTIFS(GenomicVariants!C2:C999, A6) -> 1 | O6: =COUNTIFS(CausalMechanisms!C2:C999, A6) -> 1 | P6: =COUNTIFS(EpistaticInteractions!C2:C999, A6) -> 0 | Q6: =IF(E6 > 0, N6 / E6, 0) -> 0.026315789 | R6: =O6 * 10 + P6 * 5 + Q6 -> 10.026316 | S6: =IF(E6 <= 25, TRUE(), FALSE()) -> FALSE | T6: =IF(E6 >= 60, TRUE(), FALSE()) -> FALSE | U6: =COUNTIFS(CausalMechanisms!C2:C999, A6,CausalMechanisms!AC2:AC999, TRUE()) -> 0 | V6: =SUMIFS(CausalMechanisms!AA2:AA999,CausalMechanisms!C2:C999, A6,CausalMechanisms!AC2:AC999, TRUE()) -> 0 | W6: =COUNTIFS(CausalMechanisms!C2:C999, A6,CausalMechanisms!AD2:AD999, TRUE()) -> 0 | X6: =_xlfn.MAXIFS(ClinicalPhenotypes!G2:G999,ClinicalPhenotypes!C2:C999, A6) -> 3 | Y6: =COUNTIFS(ClinicalPhenotypes!C2:C999, A6,ClinicalPhenotypes!N2:N999, TRUE()) -> 0 | Z6: =IF(Y6 >= 1, TRUE(), FALSE()) -> FALSE | AA6: =COUNTIFS(Treatments!C2:C999, A6,Treatments!P2:P999, TRUE()) -> 0 | AB6: =IF(AA6 >= 1, TRUE(), FALSE()) -> FALSE | AL6: Esi Mensah, a 38-year-old woman of African ancestry (in the training set), presents with arthralgia and cytopenias concerning for SLE onset. Genotyping finds the CTLA4 enhancer variant rs3087243 at an allele frequency of 0.007 (rare), with allele-specific expression present. The CTLA4 -> T-cell costimulation -> SLE-risk edge is well supported: a cis-eQTL in blood RNA-seq with effect 0.79 (SE 0.21), a caQTL in blood ATAC-seq with effect 0.71 (SE 0.20), and a pQTL in blood proteomics with effect 0.41 (SE 0.20), across two modalities, ancestry-PC and batch adjusted. It replicates positive in an East Asian cohort (p=0.007) and a European cohort (p=0.021), with a non-significant African replication (p=0.19). Two ancestry-permutation controls collapse to the null (permutation effect 0.011 and 0.026 inside +/-0.1), and reliability bins carry coverage of 27-33 per bin. The gap is experimental: no perturbable intervention target has been mapped for this edge — there is no agent or assay that could knock the costimulation node down to test it, so the mechanism is not experimentally falsifiable as stated. | AM6: =COUNTIFS(SerologyObservations!B2:B999, A6) -> 2 | AN6: =COUNTIFS(SerologyObservations!B2:B999, A6,SerologyObservations!Q2:Q999, TRUE()) -> 0 | AO6: =IF(AN6>=1,TRUE(),FALSE()) -> FALSE | AP6: =IF(AN6>=2,2,IF(AN6>=1,1,0)) -> 0 | AQ6: =_xlfn.MAXIFS(SerologyObservations!X2:X999,SerologyObservations!B2:B999, A6) -> 0 | AR6: =_xlfn.MAXIFS(SerologyObservations!V2:V999,SerologyObservations!B2:B999, A6) -> 0 | AS6: =IF(AQ6>=5,"BiopsyIndicated",IF(AQ6>=4,"RenalFlareRisk",IF(AQ6>=3,"EarlyNephritis",IF(AQ6>=2,"SerologicActive","PresymptomaticAutoimmunity")))) -> PresymptomaticAutoimmunity | AT6: =IF(AR6>=12,"High / flare",IF(AR6>=6,"Moderate",IF(AR6>=1,"Mild","Quiescent"))) -> Quiescent | AU6: =IF(AR6>=12,TRUE(),FALSE()) -> FALSE | AV6: =IF(OR(AS6="EarlyNephritis",AS6="RenalFlareRisk",AS6="BiopsyIndicated"),TRUE(),FALSE()) -> FALSE | AW6: =_xlfn.MAXIFS(CausalMechanisms!H2:H999,CausalMechanisms!C2:C999, A6) -> 3 | AX6: =IF(AW6=1,"type-I-IFN",IF(AW6=2,"B-cell/autoantibody",IF(AW6=3,"T-cell-costim",IF(AW6=4,"IL-17/23","")))) -> T-cell-costim | AY6: ="lupus-nephritis-progression--" & LOWER(AS6) -> lupus-nephritis-progression--presymptomaticautoimmunity | AZ6: =INDEX(MachineStates!Q2:Q999, MATCH(AY6,MachineStates!A2:A999, 0)) -> #VALUE!
A7: ind-f-haidar | B7: Faisal | C7: Haidar | D7: Indigenous American | E7: 31 | F7: TRUE | G7: fed-amazon | H7: 45689 | I7: FALSE | J7: =B7 & " " & C7 -> Faisal Haidar | K7: =SUBSTITUTE(LOWER(C7 & "-" & B7), " ", "-") -> haidar-faisal | L7: ="/intake/new-patient/" & K7 -> /intake/new-patient/haidar-faisal | M7: =IF(G7 = "", "", INDEX(FederatedDatasets!B2:B999, MATCH(G7,FederatedDatasets!A2:A999, 0))) -> Amazon Indigenous Cohort | N7: =COUNTIFS(GenomicVariants!C2:C999, A7) -> 1 | O7: =COUNTIFS(CausalMechanisms!C2:C999, A7) -> 1 | P7: =COUNTIFS(EpistaticInteractions!C2:C999, A7) -> 0 | Q7: =IF(E7 > 0, N7 / E7, 0) -> 0.032258065 | R7: =O7 * 10 + P7 * 5 + Q7 -> 10.032258 | S7: =IF(E7 <= 25, TRUE(), FALSE()) -> FALSE | T7: =IF(E7 >= 60, TRUE(), FALSE()) -> FALSE | U7: =COUNTIFS(CausalMechanisms!C2:C999, A7,CausalMechanisms!AC2:AC999, TRUE()) -> 1 | V7: =SUMIFS(CausalMechanisms!AA2:AA999,CausalMechanisms!C2:C999, A7,CausalMechanisms!AC2:AC999, TRUE()) -> 0.85833333 | W7: =COUNTIFS(CausalMechanisms!C2:C999, A7,CausalMechanisms!AD2:AD999, TRUE()) -> 0 | X7: =_xlfn.MAXIFS(ClinicalPhenotypes!G2:G999,ClinicalPhenotypes!C2:C999, A7) -> 2 | Y7: =COUNTIFS(ClinicalPhenotypes!C2:C999, A7,ClinicalPhenotypes!N2:N999, TRUE()) -> 0 | Z7: =IF(Y7 >= 1, TRUE(), FALSE()) -> FALSE | AA7: =COUNTIFS(Treatments!C2:C999, A7,Treatments!P2:P999, TRUE()) -> 0 | AB7: =IF(AA7 >= 1, TRUE(), FALSE()) -> FALSE | AL7: Faisal Haidar, a 31-year-old man of Indigenous American ancestry — an ancestry deliberately HELD OUT of the training set — presents with dactylitis, enthesitis, and nail pitting concerning for psoriatic-arthritis (PsA) onset. Genotyping finds the IL23R regulatory variant rs11209026 at an allele frequency of 0.009 (rare), with allele-specific expression present. The IL23R -> IL-17 axis -> PsA-risk edge is well supported: a cis-eQTL in blood RNA-seq with effect 1.07 (SE 0.20), a caQTL in blood ATAC-seq with effect 0.83 (SE 0.21), and a pQTL in blood proteomics with effect 0.74 (SE 0.20), across two modalities and adjusted for ancestry PCs and batch. The IL-17 target is druggable (secukinumab). Two ancestry-permutation controls collapse to the null (permutation effect 0.008 and 0.022 inside +/-0.1), and reliability bins carry coverage of 30-35 per bin. But every replication of this edge was run in an Indigenous American cohort: p=0.005, p=0.015, and p=0.034, all positive, all in the SAME ancestry. There is no cohort in a DIFFERENT ancestry confirming the effect — so for a patient whose ancestry is absent from training, nothing demonstrates the mechanism transports. No cryptic-relatedness leakage was flagged. | AM7: =COUNTIFS(SerologyObservations!B2:B999, A7) -> 2 | AN7: =COUNTIFS(SerologyObservations!B2:B999, A7,SerologyObservations!Q2:Q999, TRUE()) -> 0 | AO7: =IF(AN7>=1,TRUE(),FALSE()) -> FALSE | AP7: =IF(AN7>=2,2,IF(AN7>=1,1,0)) -> 0 | AQ7: =_xlfn.MAXIFS(SerologyObservations!X2:X999,SerologyObservations!B2:B999, A7) -> 0 | AR7: =_xlfn.MAXIFS(SerologyObservations!V2:V999,SerologyObservations!B2:B999, A7) -> 0 | AS7: =IF(AQ7>=5,"BiopsyIndicated",IF(AQ7>=4,"RenalFlareRisk",IF(AQ7>=3,"EarlyNephritis",IF(AQ7>=2,"SerologicActive","PresymptomaticAutoimmunity")))) -> PresymptomaticAutoimmunity | AT7: =IF(AR7>=12,"High / flare",IF(AR7>=6,"Moderate",IF(AR7>=1,"Mild","Quiescent"))) -> Quiescent | AU7: =IF(AR7>=12,TRUE(),FALSE()) -> FALSE | AV7: =IF(OR(AS7="EarlyNephritis",AS7="RenalFlareRisk",AS7="BiopsyIndicated"),TRUE(),FALSE()) -> FALSE | AW7: =_xlfn.MAXIFS(CausalMechanisms!H2:H999,CausalMechanisms!C2:C999, A7) -> 4 | AX7: =IF(AW7=1,"type-I-IFN",IF(AW7=2,"B-cell/autoantibody",IF(AW7=3,"T-cell-costim",IF(AW7=4,"IL-17/23","")))) -> IL-17/23 | AY7: ="lupus-nephritis-progression--" & LOWER(AS7) -> lupus-nephritis-progression--presymptomaticautoimmunity | AZ7: =INDEX(MachineStates!Q2:Q999, MATCH(AY7,MachineStates!A2:A999, 0)) -> #VALUE!
A8: ind-g-lin | B8: Grace | C8: Lin | D8: Indigenous American | E8: 36 | F8: TRUE | G8: fed-amazon | H8: 45691 | I8: FALSE | J8: =B8 & " " & C8 -> Grace Lin | K8: =SUBSTITUTE(LOWER(C8 & "-" & B8), " ", "-") -> lin-grace | L8: ="/intake/new-patient/" & K8 -> /intake/new-patient/lin-grace | M8: =IF(G8 = "", "", INDEX(FederatedDatasets!B2:B999, MATCH(G8,FederatedDatasets!A2:A999, 0))) -> Amazon Indigenous Cohort | N8: =COUNTIFS(GenomicVariants!C2:C999, A8) -> 1 | O8: =COUNTIFS(CausalMechanisms!C2:C999, A8) -> 1 | P8: =COUNTIFS(EpistaticInteractions!C2:C999, A8) -> 0 | Q8: =IF(E8 > 0, N8 / E8, 0) -> 0.027777778 | R8: =O8 * 10 + P8 * 5 + Q8 -> 10.027778 | S8: =IF(E8 <= 25, TRUE(), FALSE()) -> FALSE | T8: =IF(E8 >= 60, TRUE(), FALSE()) -> FALSE | U8: =COUNTIFS(CausalMechanisms!C2:C999, A8,CausalMechanisms!AC2:AC999, TRUE()) -> 1 | V8: =SUMIFS(CausalMechanisms!AA2:AA999,CausalMechanisms!C2:C999, A8,CausalMechanisms!AC2:AC999, TRUE()) -> 0.85833333 | W8: =COUNTIFS(CausalMechanisms!C2:C999, A8,CausalMechanisms!AD2:AD999, TRUE()) -> 1 | X8: =_xlfn.MAXIFS(ClinicalPhenotypes!G2:G999,ClinicalPhenotypes!C2:C999, A8) -> 6 | Y8: =COUNTIFS(ClinicalPhenotypes!C2:C999, A8,ClinicalPhenotypes!N2:N999, TRUE()) -> 0 | Z8: =IF(Y8 >= 1, TRUE(), FALSE()) -> FALSE | AA8: =COUNTIFS(Treatments!C2:C999, A8,Treatments!P2:P999, TRUE()) -> 1 | AB8: =IF(AA8 >= 1, TRUE(), FALSE()) -> TRUE | AL8: Grace Lin, a 36-year-old woman of Indigenous American ancestry — again an ancestry HELD OUT of the training set — presents with plaque psoriasis and asymmetric oligoarthritis concerning for psoriatic-arthritis (PsA) onset. Genotyping finds the IL23R regulatory variant rs11209026 at an allele frequency of 0.009 (rare), with allele-specific expression present. The IL23R -> IL-17 axis -> PsA-risk edge is well supported: a cis-eQTL in blood RNA-seq with effect 0.96 (SE 0.20), a caQTL in blood ATAC-seq with effect 0.88 (SE 0.21), and a pQTL in blood proteomics with effect 0.69 (SE 0.20), across two modalities and adjusted for ancestry PCs and batch. The IL-17 target is druggable (secukinumab). Two ancestry-permutation controls collapse to the null (permutation effect 0.007 and 0.019 inside +/-0.1), and reliability bins carry coverage of 30-36 per bin. Crucially — and unlike Faisal — this edge was MEASURED to replicate ACROSS ancestries: positive in a European cohort (p=0.004), positive in an East Asian cohort (p=0.012), and positive in an Indigenous American cohort (p=0.029). Because the mechanism demonstrably holds in ancestries other than the held-out one, the prediction transports. No cryptic-relatedness leakage was flagged. | AM8: =COUNTIFS(SerologyObservations!B2:B999, A8) -> 2 | AN8: =COUNTIFS(SerologyObservations!B2:B999, A8,SerologyObservations!Q2:Q999, TRUE()) -> 0 | AO8: =IF(AN8>=1,TRUE(),FALSE()) -> FALSE | AP8: =IF(AN8>=2,2,IF(AN8>=1,1,0)) -> 0 | AQ8: =_xlfn.MAXIFS(SerologyObservations!X2:X999,SerologyObservations!B2:B999, A8) -> 0 | AR8: =_xlfn.MAXIFS(SerologyObservations!V2:V999,SerologyObservations!B2:B999, A8) -> 0 | AS8: =IF(AQ8>=5,"BiopsyIndicated",IF(AQ8>=4,"RenalFlareRisk",IF(AQ8>=3,"EarlyNephritis",IF(AQ8>=2,"SerologicActive","PresymptomaticAutoimmunity")))) -> PresymptomaticAutoimmunity | AT8: =IF(AR8>=12,"High / flare",IF(AR8>=6,"Moderate",IF(AR8>=1,"Mild","Quiescent"))) -> Quiescent | AU8: =IF(AR8>=12,TRUE(),FALSE()) -> FALSE | AV8: =IF(OR(AS8="EarlyNephritis",AS8="RenalFlareRisk",AS8="BiopsyIndicated"),TRUE(),FALSE()) -> FALSE | AW8: =_xlfn.MAXIFS(CausalMechanisms!H2:H999,CausalMechanisms!C2:C999, A8) -> 4 | AX8: =IF(AW8=1,"type-I-IFN",IF(AW8=2,"B-cell/autoantibody",IF(AW8=3,"T-cell-costim",IF(AW8=4,"IL-17/23","")))) -> IL-17/23 | AY8: ="lupus-nephritis-progression--" & LOWER(AS8) -> lupus-nephritis-progression--presymptomaticautoimmunity | AZ8: =INDEX(MachineStates!Q2:Q999, MATCH(AY8,MachineStates!A2:A999, 0)) -> #VALUE!
A9: ind-h-yamamoto | B9: Hana | C9: Yamamoto | D9: East Asian | E9: 33 | F9: FALSE | H9: 45839 | I9: FALSE | J9: =B9 & " " & C9 -> Hana Yamamoto | K9: =SUBSTITUTE(LOWER(C9 & "-" & B9), " ", "-") -> yamamoto-hana | L9: ="/intake/new-patient/" & K9 -> /intake/new-patient/yamamoto-hana | M9: =IF(G9 = "", "", INDEX(FederatedDatasets!B2:B999, MATCH(G9,FederatedDatasets!A2:A999, 0))) | N9: =COUNTIFS(GenomicVariants!C2:C999, A9) -> 1 | O9: =COUNTIFS(CausalMechanisms!C2:C999, A9) -> 1 | P9: =COUNTIFS(EpistaticInteractions!C2:C999, A9) -> 0 | Q9: =IF(E9 > 0, N9 / E9, 0) -> 0.03030303 | R9: =O9 * 10 + P9 * 5 + Q9 -> 10.030303 | S9: =IF(E9 <= 25, TRUE(), FALSE()) -> FALSE | T9: =IF(E9 >= 60, TRUE(), FALSE()) -> FALSE | U9: =COUNTIFS(CausalMechanisms!C2:C999, A9,CausalMechanisms!AC2:AC999, TRUE()) -> 1 | V9: =SUMIFS(CausalMechanisms!AA2:AA999,CausalMechanisms!C2:C999, A9,CausalMechanisms!AC2:AC999, TRUE()) -> 0.75833333 | W9: =COUNTIFS(CausalMechanisms!C2:C999, A9,CausalMechanisms!AD2:AD999, TRUE()) -> 1 | X9: =_xlfn.MAXIFS(ClinicalPhenotypes!G2:G999,ClinicalPhenotypes!C2:C999, A9) -> 9 | Y9: =COUNTIFS(ClinicalPhenotypes!C2:C999, A9,ClinicalPhenotypes!N2:N999, TRUE()) -> 1 | Z9: =IF(Y9 >= 1, TRUE(), FALSE()) -> TRUE | AA9: =COUNTIFS(Treatments!C2:C999, A9,Treatments!P2:P999, TRUE()) -> 1 | AB9: =IF(AA9 >= 1, TRUE(), FALSE()) -> TRUE | AL9: 33yo East Asian woman; rising anti-dsDNA with falling complement and new significant proteinuria (0.7 g/day) over one quarter — early lupus nephritis. Progression-demo case (no v1 keystone mechanism attached). | AM9: =COUNTIFS(SerologyObservations!B2:B999, A9) -> 2 | AN9: =COUNTIFS(SerologyObservations!B2:B999, A9,SerologyObservations!Q2:Q999, TRUE()) -> 0 | AO9: =IF(AN9>=1,TRUE(),FALSE()) -> FALSE | AP9: =IF(AN9>=2,2,IF(AN9>=1,1,0)) -> 0 | AQ9: =_xlfn.MAXIFS(SerologyObservations!X2:X999,SerologyObservations!B2:B999, A9) -> 3 | AR9: =_xlfn.MAXIFS(SerologyObservations!V2:V999,SerologyObservations!B2:B999, A9) -> 0 | AS9: =IF(AQ9>=5,"BiopsyIndicated",IF(AQ9>=4,"RenalFlareRisk",IF(AQ9>=3,"EarlyNephritis",IF(AQ9>=2,"SerologicActive","PresymptomaticAutoimmunity")))) -> EarlyNephritis | AT9: =IF(AR9>=12,"High / flare",IF(AR9>=6,"Moderate",IF(AR9>=1,"Mild","Quiescent"))) -> Quiescent | AU9: =IF(AR9>=12,TRUE(),FALSE()) -> FALSE | AV9: =IF(OR(AS9="EarlyNephritis",AS9="RenalFlareRisk",AS9="BiopsyIndicated"),TRUE(),FALSE()) -> TRUE | AW9: =_xlfn.MAXIFS(CausalMechanisms!H2:H999,CausalMechanisms!C2:C999, A9) -> 1 | AX9: =IF(AW9=1,"type-I-IFN",IF(AW9=2,"B-cell/autoantibody",IF(AW9=3,"T-cell-costim",IF(AW9=4,"IL-17/23","")))) -> type-I-IFN | AY9: ="lupus-nephritis-progression--" & LOWER(AS9) -> lupus-nephritis-progression--earlynephritis | AZ9: =INDEX(MachineStates!Q2:Q999, MATCH(AY9,MachineStates!A2:A999, 0)) -> #VALUE!
A10: ind-i-conteh | B10: Ibrahim | C10: Conteh | D10: African | E10: 45 | F10: FALSE | H10: 45809 | I10: TRUE | J10: =B10 & " " & C10 -> Ibrahim Conteh | K10: =SUBSTITUTE(LOWER(C10 & "-" & B10), " ", "-") -> conteh-ibrahim | L10: ="/intake/new-patient/" & K10 -> /intake/new-patient/conteh-ibrahim | M10: =IF(G10 = "", "", INDEX(FederatedDatasets!B2:B999, MATCH(G10,FederatedDatasets!A2:A999, 0))) | N10: =COUNTIFS(GenomicVariants!C2:C999, A10) -> 1 | O10: =COUNTIFS(CausalMechanisms!C2:C999, A10) -> 1 | P10: =COUNTIFS(EpistaticInteractions!C2:C999, A10) -> 0 | Q10: =IF(E10 > 0, N10 / E10, 0) -> 0.022222222 | R10: =O10 * 10 + P10 * 5 + Q10 -> 10.022222 | S10: =IF(E10 <= 25, TRUE(), FALSE()) -> FALSE | T10: =IF(E10 >= 60, TRUE(), FALSE()) -> FALSE | U10: =COUNTIFS(CausalMechanisms!C2:C999, A10,CausalMechanisms!AC2:AC999, TRUE()) -> 1 | V10: =SUMIFS(CausalMechanisms!AA2:AA999,CausalMechanisms!C2:C999, A10,CausalMechanisms!AC2:AC999, TRUE()) -> 0.75833333 | W10: =COUNTIFS(CausalMechanisms!C2:C999, A10,CausalMechanisms!AD2:AD999, TRUE()) -> 1 | X10: =_xlfn.MAXIFS(ClinicalPhenotypes!G2:G999,ClinicalPhenotypes!C2:C999, A10) -> 8 | Y10: =COUNTIFS(ClinicalPhenotypes!C2:C999, A10,ClinicalPhenotypes!N2:N999, TRUE()) -> 1 | Z10: =IF(Y10 >= 1, TRUE(), FALSE()) -> TRUE | AA10: =COUNTIFS(Treatments!C2:C999, A10,Treatments!P2:P999, TRUE()) -> 0 | AB10: =IF(AA10 >= 1, TRUE(), FALSE()) -> FALSE | AL10: 45yo African man; brisk serologic activity and proteinuria climbing to 1.5 g/day — at risk of renal flare. Progression-demo case (no v1 keystone mechanism attached). | AM10: =COUNTIFS(SerologyObservations!B2:B999, A10) -> 2 | AN10: =COUNTIFS(SerologyObservations!B2:B999, A10,SerologyObservations!Q2:Q999, TRUE()) -> 0 | AO10: =IF(AN10>=1,TRUE(),FALSE()) -> FALSE | AP10: =IF(AN10>=2,2,IF(AN10>=1,1,0)) -> 0 | AQ10: =_xlfn.MAXIFS(SerologyObservations!X2:X999,SerologyObservations!B2:B999, A10) -> 4 | AR10: =_xlfn.MAXIFS(SerologyObservations!V2:V999,SerologyObservations!B2:B999, A10) -> 0 | AS10: =IF(AQ10>=5,"BiopsyIndicated",IF(AQ10>=4,"RenalFlareRisk",IF(AQ10>=3,"EarlyNephritis",IF(AQ10>=2,"SerologicActive","PresymptomaticAutoimmunity")))) -> RenalFlareRisk | AT10: =IF(AR10>=12,"High / flare",IF(AR10>=6,"Moderate",IF(AR10>=1,"Mild","Quiescent"))) -> Quiescent | AU10: =IF(AR10>=12,TRUE(),FALSE()) -> FALSE | AV10: =IF(OR(AS10="EarlyNephritis",AS10="RenalFlareRisk",AS10="BiopsyIndicated"),TRUE(),FALSE()) -> TRUE | AW10: =_xlfn.MAXIFS(CausalMechanisms!H2:H999,CausalMechanisms!C2:C999, A10) -> 2 | AX10: =IF(AW10=1,"type-I-IFN",IF(AW10=2,"B-cell/autoantibody",IF(AW10=3,"T-cell-costim",IF(AW10=4,"IL-17/23","")))) -> B-cell/autoantibody | AY10: ="lupus-nephritis-progression--" & LOWER(AS10) -> lupus-nephritis-progression--renalflarerisk | AZ10: =INDEX(MachineStates!Q2:Q999, MATCH(AY10,MachineStates!A2:A999, 0)) -> #VALUE!
A11: ind-j-brooks | B11: Jamal | C11: Brooks | D11: Hispanic/Latino | E11: 52 | F11: FALSE | G11: fed-europe | H11: 45058 | I11: FALSE | J11: =B11 & " " & C11 -> Jamal Brooks | K11: =SUBSTITUTE(LOWER(C11 & "-" & B11), " ", "-") -> brooks-jamal | L11: ="/intake/new-patient/" & K11 -> /intake/new-patient/brooks-jamal | M11: =IF(G11 = "", "", INDEX(FederatedDatasets!B2:B999, MATCH(G11,FederatedDatasets!A2:A999, 0))) -> European Reference Node | N11: =COUNTIFS(GenomicVariants!C2:C999, A11) -> 1 | O11: =COUNTIFS(CausalMechanisms!C2:C999, A11) -> 1 | P11: =COUNTIFS(EpistaticInteractions!C2:C999, A11) -> 0 | Q11: =IF(E11 > 0, N11 / E11, 0) -> 0.019230769 | R11: =O11 * 10 + P11 * 5 + Q11 -> 10.019231 | S11: =IF(E11 <= 25, TRUE(), FALSE()) -> FALSE | T11: =IF(E11 >= 60, TRUE(), FALSE()) -> FALSE | U11: =COUNTIFS(CausalMechanisms!C2:C999, A11,CausalMechanisms!AC2:AC999, TRUE()) -> 1 | V11: =SUMIFS(CausalMechanisms!AA2:AA999,CausalMechanisms!C2:C999, A11,CausalMechanisms!AC2:AC999, TRUE()) -> 0.75833333 | W11: =COUNTIFS(CausalMechanisms!C2:C999, A11,CausalMechanisms!AD2:AD999, TRUE()) -> 1 | X11: =_xlfn.MAXIFS(ClinicalPhenotypes!G2:G999,ClinicalPhenotypes!C2:C999, A11) -> 8 | Y11: =COUNTIFS(ClinicalPhenotypes!C2:C999, A11,ClinicalPhenotypes!N2:N999, TRUE()) -> 1 | Z11: =IF(Y11 >= 1, TRUE(), FALSE()) -> TRUE | AA11: =COUNTIFS(Treatments!C2:C999, A11,Treatments!P2:P999, TRUE()) -> 1 | AB11: =IF(AA11 >= 1, TRUE(), FALSE()) -> TRUE | AL11: 52yo Hispanic/Latino man; the targeted mechanism is confirmed but the calibration bins are under-covered — uncertainty collapses, so NOT actionable on the calibration gate. | AM11: =COUNTIFS(SerologyObservations!B2:B999, A11) -> 2 | AN11: =COUNTIFS(SerologyObservations!B2:B999, A11,SerologyObservations!Q2:Q999, TRUE()) -> 0 | AO11: =IF(AN11>=1,TRUE(),FALSE()) -> FALSE | AP11: =IF(AN11>=2,2,IF(AN11>=1,1,0)) -> 0 | AQ11: =_xlfn.MAXIFS(SerologyObservations!X2:X999,SerologyObservations!B2:B999, A11) -> 0 | AR11: =_xlfn.MAXIFS(SerologyObservations!V2:V999,SerologyObservations!B2:B999, A11) -> 0 | AS11: =IF(AQ11>=5,"BiopsyIndicated",IF(AQ11>=4,"RenalFlareRisk",IF(AQ11>=3,"EarlyNephritis",IF(AQ11>=2,"SerologicActive","PresymptomaticAutoimmunity")))) -> PresymptomaticAutoimmunity | AT11: =IF(AR11>=12,"High / flare",IF(AR11>=6,"Moderate",IF(AR11>=1,"Mild","Quiescent"))) -> Quiescent | AU11: =IF(AR11>=12,TRUE(),FALSE()) -> FALSE | AV11: =IF(OR(AS11="EarlyNephritis",AS11="RenalFlareRisk",AS11="BiopsyIndicated"),TRUE(),FALSE()) -> FALSE | AW11: =_xlfn.MAXIFS(CausalMechanisms!H2:H999,CausalMechanisms!C2:C999, A11) -> 1 | AX11: =IF(AW11=1,"type-I-IFN",IF(AW11=2,"B-cell/autoantibody",IF(AW11=3,"T-cell-costim",IF(AW11=4,"IL-17/23","")))) -> type-I-IFN | AY11: ="lupus-nephritis-progression--" & LOWER(AS11) -> lupus-nephritis-progression--presymptomaticautoimmunity | AZ11: =INDEX(MachineStates!Q2:Q999, MATCH(AY11,MachineStates!A2:A999, 0)) -> #VALUE!
A12: ind-k-nair | B12: Kavya | C12: Nair | D12: South Asian | E12: 39 | F12: TRUE | G12: fed-amazon | H12: 45689 | I12: FALSE | J12: =B12 & " " & C12 -> Kavya Nair | K12: =SUBSTITUTE(LOWER(C12 & "-" & B12), " ", "-") -> nair-kavya | L12: ="/intake/new-patient/" & K12 -> /intake/new-patient/nair-kavya | M12: =IF(G12 = "", "", INDEX(FederatedDatasets!B2:B999, MATCH(G12,FederatedDatasets!A2:A999, 0))) -> Amazon Indigenous Cohort | N12: =COUNTIFS(GenomicVariants!C2:C999, A12) -> 1 | O12: =COUNTIFS(CausalMechanisms!C2:C999, A12) -> 1 | P12: =COUNTIFS(EpistaticInteractions!C2:C999, A12) -> 0 | Q12: =IF(E12 > 0, N12 / E12, 0) -> 0.025641026 | R12: =O12 * 10 + P12 * 5 + Q12 -> 10.025641 | S12: =IF(E12 <= 25, TRUE(), FALSE()) -> FALSE | T12: =IF(E12 >= 60, TRUE(), FALSE()) -> FALSE | U12: =COUNTIFS(CausalMechanisms!C2:C999, A12,CausalMechanisms!AC2:AC999, TRUE()) -> 1 | V12: =SUMIFS(CausalMechanisms!AA2:AA999,CausalMechanisms!C2:C999, A12,CausalMechanisms!AC2:AC999, TRUE()) -> 0.85833333 | W12: =COUNTIFS(CausalMechanisms!C2:C999, A12,CausalMechanisms!AD2:AD999, TRUE()) -> 0 | X12: =_xlfn.MAXIFS(ClinicalPhenotypes!G2:G999,ClinicalPhenotypes!C2:C999, A12) -> 2 | Y12: =COUNTIFS(ClinicalPhenotypes!C2:C999, A12,ClinicalPhenotypes!N2:N999, TRUE()) -> 0 | Z12: =IF(Y12 >= 1, TRUE(), FALSE()) -> FALSE | AA12: =COUNTIFS(Treatments!C2:C999, A12,Treatments!P2:P999, TRUE()) -> 0 | AB12: =IF(AA12 >= 1, TRUE(), FALSE()) -> FALSE | AL12: 39yo South Asian woman, ancestry absent from training; confirmed mechanism but all replications ran in one ancestry — fails ancestry transport, NOT actionable. | AM12: =COUNTIFS(SerologyObservations!B2:B999, A12) -> 2 | AN12: =COUNTIFS(SerologyObservations!B2:B999, A12,SerologyObservations!Q2:Q999, TRUE()) -> 0 | AO12: =IF(AN12>=1,TRUE(),FALSE()) -> FALSE | AP12: =IF(AN12>=2,2,IF(AN12>=1,1,0)) -> 0 | AQ12: =_xlfn.MAXIFS(SerologyObservations!X2:X999,SerologyObservations!B2:B999, A12) -> 0 | AR12: =_xlfn.MAXIFS(SerologyObservations!V2:V999,SerologyObservations!B2:B999, A12) -> 0 | AS12: =IF(AQ12>=5,"BiopsyIndicated",IF(AQ12>=4,"RenalFlareRisk",IF(AQ12>=3,"EarlyNephritis",IF(AQ12>=2,"SerologicActive","PresymptomaticAutoimmunity")))) -> PresymptomaticAutoimmunity | AT12: =IF(AR12>=12,"High / flare",IF(AR12>=6,"Moderate",IF(AR12>=1,"Mild","Quiescent"))) -> Quiescent | AU12: =IF(AR12>=12,TRUE(),FALSE()) -> FALSE | AV12: =IF(OR(AS12="EarlyNephritis",AS12="RenalFlareRisk",AS12="BiopsyIndicated"),TRUE(),FALSE()) -> FALSE | AW12: =_xlfn.MAXIFS(CausalMechanisms!H2:H999,CausalMechanisms!C2:C999, A12) -> 4 | AX12: =IF(AW12=1,"type-I-IFN",IF(AW12=2,"B-cell/autoantibody",IF(AW12=3,"T-cell-costim",IF(AW12=4,"IL-17/23","")))) -> IL-17/23 | AY12: ="lupus-nephritis-progression--" & LOWER(AS12) -> lupus-nephritis-progression--presymptomaticautoimmunity | AZ12: =INDEX(MachineStates!Q2:Q999, MATCH(AY12,MachineStates!A2:A999, 0)) -> #VALUE!
A13: ind-l-brandt | B13: Lena | C13: Brandt | D13: Indigenous American | E13: 28 | F13: TRUE | G13: fed-amazon | H13: 45691 | I13: FALSE | J13: =B13 & " " & C13 -> Lena Brandt | K13: =SUBSTITUTE(LOWER(C13 & "-" & B13), " ", "-") -> brandt-lena | L13: ="/intake/new-patient/" & K13 -> /intake/new-patient/brandt-lena | M13: =IF(G13 = "", "", INDEX(FederatedDatasets!B2:B999, MATCH(G13,FederatedDatasets!A2:A999, 0))) -> Amazon Indigenous Cohort | N13: =COUNTIFS(GenomicVariants!C2:C999, A13) -> 1 | O13: =COUNTIFS(CausalMechanisms!C2:C999, A13) -> 1 | P13: =COUNTIFS(EpistaticInteractions!C2:C999, A13) -> 0 | Q13: =IF(E13 > 0, N13 / E13, 0) -> 0.035714286 | R13: =O13 * 10 + P13 * 5 + Q13 -> 10.035714 | S13: =IF(E13 <= 25, TRUE(), FALSE()) -> FALSE | T13: =IF(E13 >= 60, TRUE(), FALSE()) -> FALSE | U13: =COUNTIFS(CausalMechanisms!C2:C999, A13,CausalMechanisms!AC2:AC999, TRUE()) -> 1 | V13: =SUMIFS(CausalMechanisms!AA2:AA999,CausalMechanisms!C2:C999, A13,CausalMechanisms!AC2:AC999, TRUE()) -> 0.85833333 | W13: =COUNTIFS(CausalMechanisms!C2:C999, A13,CausalMechanisms!AD2:AD999, TRUE()) -> 1 | X13: =_xlfn.MAXIFS(ClinicalPhenotypes!G2:G999,ClinicalPhenotypes!C2:C999, A13) -> 6 | Y13: =COUNTIFS(ClinicalPhenotypes!C2:C999, A13,ClinicalPhenotypes!N2:N999, TRUE()) -> 0 | Z13: =IF(Y13 >= 1, TRUE(), FALSE()) -> FALSE | AA13: =COUNTIFS(Treatments!C2:C999, A13,Treatments!P2:P999, TRUE()) -> 1 | AB13: =IF(AA13 >= 1, TRUE(), FALSE()) -> TRUE | AL13: 28yo Indigenous-American woman, holdout ancestry; the positive twin — the IL23R node replicated cross-ancestry, so transport passes and she is actionable. | AM13: =COUNTIFS(SerologyObservations!B2:B999, A13) -> 2 | AN13: =COUNTIFS(SerologyObservations!B2:B999, A13,SerologyObservations!Q2:Q999, TRUE()) -> 0 | AO13: =IF(AN13>=1,TRUE(),FALSE()) -> FALSE | AP13: =IF(AN13>=2,2,IF(AN13>=1,1,0)) -> 0 | AQ13: =_xlfn.MAXIFS(SerologyObservations!X2:X999,SerologyObservations!B2:B999, A13) -> 0 | AR13: =_xlfn.MAXIFS(SerologyObservations!V2:V999,SerologyObservations!B2:B999, A13) -> 0 | AS13: =IF(AQ13>=5,"BiopsyIndicated",IF(AQ13>=4,"RenalFlareRisk",IF(AQ13>=3,"EarlyNephritis",IF(AQ13>=2,"SerologicActive","PresymptomaticAutoimmunity")))) -> PresymptomaticAutoimmunity | AT13: =IF(AR13>=12,"High / flare",IF(AR13>=6,"Moderate",IF(AR13>=1,"Mild","Quiescent"))) -> Quiescent | AU13: =IF(AR13>=12,TRUE(),FALSE()) -> FALSE | AV13: =IF(OR(AS13="EarlyNephritis",AS13="RenalFlareRisk",AS13="BiopsyIndicated"),TRUE(),FALSE()) -> FALSE | AW13: =_xlfn.MAXIFS(CausalMechanisms!H2:H999,CausalMechanisms!C2:C999, A13) -> 4 | AX13: =IF(AW13=1,"type-I-IFN",IF(AW13=2,"B-cell/autoantibody",IF(AW13=3,"T-cell-costim",IF(AW13=4,"IL-17/23","")))) -> IL-17/23 | AY13: ="lupus-nephritis-progression--" & LOWER(AS13) -> lupus-nephritis-progression--presymptomaticautoimmunity | AZ13: =INDEX(MachineStates!Q2:Q999, MATCH(AY13,MachineStates!A2:A999, 0)) -> #VALUE!

Sheet GenomicVariants
A1: GenomicVariantId | B1: VariantLabel | C1: Individual | D1: VariantType | E1: AlleleFrequency | F1: HasAlleleSpecificExpression | G1: Name | H1: ParentPath | I1: RelativePath | J1: VariantTypeLabel | K1: VariantClassIsRare | L1: IndividualAncestryLabel | M1: IsRareVariant | N1: IsCausalCandidate | O1: SourceQuote
A2: var-a-irf5 | B2: IRF5 regulatory (rs2004640) | C2: ind-a-reyes | D2: regulatory | E2: 0.006 | F2: TRUE | G2: =B2 -> IRF5 regulatory (rs2004640) | H2: =INDEX(Individuals!L2:L999, MATCH(C2,Individuals!A2:A999, 0)) -> /intake/new-patient/reyes-ana | I2: =H2 & "/variants/" & A2 -> /intake/new-patient/reyes-ana/variants/var-a-irf5 | J2: =INDEX(VariantTypes!B2:B999, MATCH(D2,VariantTypes!A2:A999, 0)) -> Regulatory Variant | K2: =INDEX(VariantTypes!C2:C999, MATCH(D2,VariantTypes!A2:A999, 0)) -> TRUE | L2: =INDEX(Individuals!D2:D999, MATCH(C2,Individuals!A2:A999, 0)) -> European | M2: =IF(E2 < 0.01, TRUE(), FALSE()) -> TRUE | N2: =IF(AND(OR(M2, K2), F2), TRUE(), FALSE()) -> TRUE | O2: IRF5 regulatory variant rs2004640 at an allele frequency of 0.006 (rare), and allele-specific expression is present
A3: var-b-irf5 | B3: IRF5 regulatory (rs2004640) | C3: ind-b-okafor | D3: regulatory | E3: 0.006 | F3: TRUE | G3: =B3 -> IRF5 regulatory (rs2004640) | H3: =INDEX(Individuals!L2:L999, MATCH(C3,Individuals!A2:A999, 0)) -> /intake/new-patient/okafor-bili | I3: =H3 & "/variants/" & A3 -> /intake/new-patient/okafor-bili/variants/var-b-irf5 | J3: =INDEX(VariantTypes!B2:B999, MATCH(D3,VariantTypes!A2:A999, 0)) -> Regulatory Variant | K3: =INDEX(VariantTypes!C2:C999, MATCH(D3,VariantTypes!A2:A999, 0)) -> TRUE | L3: =INDEX(Individuals!D2:D999, MATCH(C3,Individuals!A2:A999, 0)) -> European | M3: =IF(E3 < 0.01, TRUE(), FALSE()) -> TRUE | N3: =IF(AND(OR(M3, K3), F3), TRUE(), FALSE()) -> TRUE | O3: IRF5 regulatory variant rs2004640 at an allele frequency of 0.006 (rare), with allele-specific expression present
A4: var-c-stat4 | B4: STAT4 regulatory (rs7574865) | C4: ind-c-chen | D4: regulatory | E4: 0.008 | F4: TRUE | G4: =B4 -> STAT4 regulatory (rs7574865) | H4: =INDEX(Individuals!L2:L999, MATCH(C4,Individuals!A2:A999, 0)) -> /intake/new-patient/wei-chen | I4: =H4 & "/variants/" & A4 -> /intake/new-patient/wei-chen/variants/var-c-stat4 | J4: =INDEX(VariantTypes!B2:B999, MATCH(D4,VariantTypes!A2:A999, 0)) -> Regulatory Variant | K4: =INDEX(VariantTypes!C2:C999, MATCH(D4,VariantTypes!A2:A999, 0)) -> TRUE | L4: =INDEX(Individuals!D2:D999, MATCH(C4,Individuals!A2:A999, 0)) -> East Asian | M4: =IF(E4 < 0.01, TRUE(), FALSE()) -> TRUE | N4: =IF(AND(OR(M4, K4), F4), TRUE(), FALSE()) -> TRUE | O4: STAT4 regulatory variant rs7574865 at an allele frequency of 0.008 (rare), with allele-specific expression present
A5: var-d-irf5 | B5: IRF5 regulatory (rs2004640) | C5: ind-d-santos | D5: regulatory | E5: 0.006 | F5: TRUE | G5: =B5 -> IRF5 regulatory (rs2004640) | H5: =INDEX(Individuals!L2:L999, MATCH(C5,Individuals!A2:A999, 0)) -> /intake/new-patient/santos-diego | I5: =H5 & "/variants/" & A5 -> /intake/new-patient/santos-diego/variants/var-d-irf5 | J5: =INDEX(VariantTypes!B2:B999, MATCH(D5,VariantTypes!A2:A999, 0)) -> Regulatory Variant | K5: =INDEX(VariantTypes!C2:C999, MATCH(D5,VariantTypes!A2:A999, 0)) -> TRUE | L5: =INDEX(Individuals!D2:D999, MATCH(C5,Individuals!A2:A999, 0)) -> European | M5: =IF(E5 < 0.01, TRUE(), FALSE()) -> TRUE | N5: =IF(AND(OR(M5, K5), F5), TRUE(), FALSE()) -> TRUE | O5: IRF5 regulatory variant rs2004640 at an allele frequency of 0.006 (rare), with allele-specific expression present
A6: var-e-ctla4 | B6: CTLA4 enhancer (rs3087243) | C6: ind-e-mensah | D6: regulatory | E6: 0.007 | F6: TRUE | G6: =B6 -> CTLA4 enhancer (rs3087243) | H6: =INDEX(Individuals!L2:L999, MATCH(C6,Individuals!A2:A999, 0)) -> /intake/new-patient/mensah-esi | I6: =H6 & "/variants/" & A6 -> /intake/new-patient/mensah-esi/variants/var-e-ctla4 | J6: =INDEX(VariantTypes!B2:B999, MATCH(D6,VariantTypes!A2:A999, 0)) -> Regulatory Variant | K6: =INDEX(VariantTypes!C2:C999, MATCH(D6,VariantTypes!A2:A999, 0)) -> TRUE | L6: =INDEX(Individuals!D2:D999, MATCH(C6,Individuals!A2:A999, 0)) -> African | M6: =IF(E6 < 0.01, TRUE(), FALSE()) -> TRUE | N6: =IF(AND(OR(M6, K6), F6), TRUE(), FALSE()) -> TRUE | O6: CTLA4 enhancer variant rs3087243 at an allele frequency of 0.007 (rare), with allele-specific expression present
A7: var-f-il23r | B7: IL23R regulatory (rs11209026) | C7: ind-f-haidar | D7: regulatory | E7: 0.009 | F7: TRUE | G7: =B7 -> IL23R regulatory (rs11209026) | H7: =INDEX(Individuals!L2:L999, MATCH(C7,Individuals!A2:A999, 0)) -> /intake/new-patient/haidar-faisal | I7: =H7 & "/variants/" & A7 -> /intake/new-patient/haidar-faisal/variants/var-f-il23r | J7: =INDEX(VariantTypes!B2:B999, MATCH(D7,VariantTypes!A2:A999, 0)) -> Regulatory Variant | K7: =INDEX(VariantTypes!C2:C999, MATCH(D7,VariantTypes!A2:A999, 0)) -> TRUE | L7: =INDEX(Individuals!D2:D999, MATCH(C7,Individuals!A2:A999, 0)) -> Indigenous American | M7: =IF(E7 < 0.01, TRUE(), FALSE()) -> TRUE | N7: =IF(AND(OR(M7, K7), F7), TRUE(), FALSE()) -> TRUE | O7: IL23R regulatory variant rs11209026 at an allele frequency of 0.009 (rare), with allele-specific expression present
A8: var-g-il23r | B8: IL23R regulatory (rs11209026) | C8: ind-g-lin | D8: regulatory | E8: 0.009 | F8: TRUE | G8: =B8 -> IL23R regulatory (rs11209026) | H8: =INDEX(Individuals!L2:L999, MATCH(C8,Individuals!A2:A999, 0)) -> /intake/new-patient/lin-grace | I8: =H8 & "/variants/" & A8 -> /intake/new-patient/lin-grace/variants/var-g-il23r | J8: =INDEX(VariantTypes!B2:B999, MATCH(D8,VariantTypes!A2:A999, 0)) -> Regulatory Variant | K8: =INDEX(VariantTypes!C2:C999, MATCH(D8,VariantTypes!A2:A999, 0)) -> TRUE | L8: =INDEX(Individuals!D2:D999, MATCH(C8,Individuals!A2:A999, 0)) -> Indigenous American | M8: =IF(E8 < 0.01, TRUE(), FALSE()) -> TRUE | N8: =IF(AND(OR(M8, K8), F8), TRUE(), FALSE()) -> TRUE | O8: IL23R regulatory variant rs11209026 at an allele frequency of 0.009 (rare), with allele-specific expression present
A9: var-h-irf5 | B9: IRF5 regulatory (rs2004640) | C9: ind-h-yamamoto | D9: regulatory | E9: 0.006 | F9: TRUE | G9: =B9 -> IRF5 regulatory (rs2004640) | H9: =INDEX(Individuals!L2:L999, MATCH(C9,Individuals!A2:A999, 0)) -> /intake/new-patient/yamamoto-hana | I9: =H9 & "/variants/" & A9 -> /intake/new-patient/yamamoto-hana/variants/var-h-irf5 | J9: =INDEX(VariantTypes!B2:B999, MATCH(D9,VariantTypes!A2:A999, 0)) -> Regulatory Variant | K9: =INDEX(VariantTypes!C2:C999, MATCH(D9,VariantTypes!A2:A999, 0)) -> TRUE | L9: =INDEX(Individuals!D2:D999, MATCH(C9,Individuals!A2:A999, 0)) -> East Asian | M9: =IF(E9 < 0.01, TRUE(), FALSE()) -> TRUE | N9: =IF(AND(OR(M9, K9), F9), TRUE(), FALSE()) -> TRUE | O9: IRF5 regulatory variant rs2004640 at an allele frequency of 0.006 (rare), and allele-specific expression is present
A10: var-i-irf5 | B10: IRF5 regulatory (rs2004640) | C10: ind-i-conteh | D10: regulatory | E10: 0.006 | F10: TRUE | G10: =B10 -> IRF5 regulatory (rs2004640) | H10: =INDEX(Individuals!L2:L999, MATCH(C10,Individuals!A2:A999, 0)) -> /intake/new-patient/conteh-ibrahim | I10: =H10 & "/variants/" & A10 -> /intake/new-patient/conteh-ibrahim/variants/var-i-irf5 | J10: =INDEX(VariantTypes!B2:B999, MATCH(D10,VariantTypes!A2:A999, 0)) -> Regulatory Variant | K10: =INDEX(VariantTypes!C2:C999, MATCH(D10,VariantTypes!A2:A999, 0)) -> TRUE | L10: =INDEX(Individuals!D2:D999, MATCH(C10,Individuals!A2:A999, 0)) -> African | M10: =IF(E10 < 0.01, TRUE(), FALSE()) -> TRUE | N10: =IF(AND(OR(M10, K10), F10), TRUE(), FALSE()) -> TRUE | O10: IRF5 regulatory variant rs2004640 at an allele frequency of 0.006 (rare), with allele-specific expression present
A11: var-j-irf5 | B11: IRF5 regulatory (rs2004640) | C11: ind-j-brooks | D11: regulatory | E11: 0.006 | F11: TRUE | G11: =B11 -> IRF5 regulatory (rs2004640) | H11: =INDEX(Individuals!L2:L999, MATCH(C11,Individuals!A2:A999, 0)) -> /intake/new-patient/brooks-jamal | I11: =H11 & "/variants/" & A11 -> /intake/new-patient/brooks-jamal/variants/var-j-irf5 | J11: =INDEX(VariantTypes!B2:B999, MATCH(D11,VariantTypes!A2:A999, 0)) -> Regulatory Variant | K11: =INDEX(VariantTypes!C2:C999, MATCH(D11,VariantTypes!A2:A999, 0)) -> TRUE | L11: =INDEX(Individuals!D2:D999, MATCH(C11,Individuals!A2:A999, 0)) -> Hispanic/Latino | M11: =IF(E11 < 0.01, TRUE(), FALSE()) -> TRUE | N11: =IF(AND(OR(M11, K11), F11), TRUE(), FALSE()) -> TRUE | O11: IRF5 regulatory variant rs2004640 at an allele frequency of 0.006 (rare), with allele-specific expression present
A12: var-k-il23r | B12: IL23R regulatory (rs11209026) | C12: ind-k-nair | D12: regulatory | E12: 0.009 | F12: TRUE | G12: =B12 -> IL23R regulatory (rs11209026) | H12: =INDEX(Individuals!L2:L999, MATCH(C12,Individuals!A2:A999, 0)) -> /intake/new-patient/nair-kavya | I12: =H12 & "/variants/" & A12 -> /intake/new-patient/nair-kavya/variants/var-k-il23r | J12: =INDEX(VariantTypes!B2:B999, MATCH(D12,VariantTypes!A2:A999, 0)) -> Regulatory Variant | K12: =INDEX(VariantTypes!C2:C999, MATCH(D12,VariantTypes!A2:A999, 0)) -> TRUE | L12: =INDEX(Individuals!D2:D999, MATCH(C12,Individuals!A2:A999, 0)) -> South Asian | M12: =IF(E12 < 0.01, TRUE(), FALSE()) -> TRUE | N12: =IF(AND(OR(M12, K12), F12), TRUE(), FALSE()) -> TRUE | O12: IL23R regulatory variant rs11209026 at an allele frequency of 0.009 (rare), with allele-specific expression present
A13: var-l-il23r | B13: IL23R regulatory (rs11209026) | C13: ind-l-brandt | D13: regulatory | E13: 0.009 | F13: TRUE | G13: =B13 -> IL23R regulatory (rs11209026) | H13: =INDEX(Individuals!L2:L999, MATCH(C13,Individuals!A2:A999, 0)) -> /intake/new-patient/brandt-lena | I13: =H13 & "/variants/" & A13 -> /intake/new-patient/brandt-lena/variants/var-l-il23r | J13: =INDEX(VariantTypes!B2:B999, MATCH(D13,VariantTypes!A2:A999, 0)) -> Regulatory Variant | K13: =INDEX(VariantTypes!C2:C999, MATCH(D13,VariantTypes!A2:A999, 0)) -> TRUE | L13: =INDEX(Individuals!D2:D999, MATCH(C13,Individuals!A2:A999, 0)) -> Indigenous American | M13: =IF(E13 < 0.01, TRUE(), FALSE()) -> TRUE | N13: =IF(AND(OR(M13, K13), F13), TRUE(), FALSE()) -> TRUE | O13: IL23R regulatory variant rs11209026 at an allele frequency of 0.009 (rare), with allele-specific expression present

Sheet OmicsAssays
A1: OmicsAssayId | B1: AssayLabel | C1: Individual | D1: OmicsModality | E1: Tissue | F1: FederatedDataset | G1: BatchId | H1: MeasurementErrorScore | I1: HasCellStateSpecificEffect | J1: Name | K1: ParentPath | L1: RelativePath | M1: ModalityLabel | N1: TissueLabel | O1: HasBatchEffectRisk | P1: IsHighQualityAssay | Q1: EvidenceItems
A2: assay-a-rna | B2: assay-a-rna | C2: ind-a-reyes | D2: rna-seq | E2: blood | G2: b1 | H2: 0.05 | I2: TRUE | J2: =B2 -> assay-a-rna | K2: =INDEX(Individuals!L2:L999, MATCH(C2,Individuals!A2:A999, 0)) -> /intake/new-patient/reyes-ana | L2: =K2 & "/assays/" & A2 -> /intake/new-patient/reyes-ana/assays/assay-a-rna | M2: =INDEX(OmicsModalities!B2:B999, MATCH(D2,OmicsModalities!A2:A999, 0)) -> RNA-seq | N2: =IF(E2 = "", "Missing Tissue", INDEX(Tissues!B2:B999, MATCH(E2,Tissues!A2:A999, 0))) -> Blood | O2: =IF(H2 > 0.3, TRUE(), FALSE()) -> FALSE | P2: =IF(AND(NOT(O2), H2 < 0.15), TRUE(), FALSE()) -> TRUE
A3: assay-a-atac | B3: assay-a-atac | C3: ind-a-reyes | D3: atac-seq | E3: blood | G3: b1 | H3: 0.05 | I3: TRUE | J3: =B3 -> assay-a-atac | K3: =INDEX(Individuals!L2:L999, MATCH(C3,Individuals!A2:A999, 0)) -> /intake/new-patient/reyes-ana | L3: =K3 & "/assays/" & A3 -> /intake/new-patient/reyes-ana/assays/assay-a-atac | M3: =INDEX(OmicsModalities!B2:B999, MATCH(D3,OmicsModalities!A2:A999, 0)) -> ATAC-seq | N3: =IF(E3 = "", "Missing Tissue", INDEX(Tissues!B2:B999, MATCH(E3,Tissues!A2:A999, 0))) -> Blood | O3: =IF(H3 > 0.3, TRUE(), FALSE()) -> FALSE | P3: =IF(AND(NOT(O3), H3 < 0.15), TRUE(), FALSE()) -> TRUE
A4: assay-a-prot | B4: assay-a-prot | C4: ind-a-reyes | D4: proteomics | E4: blood | G4: b1 | H4: 0.05 | I4: TRUE | J4: =B4 -> assay-a-prot | K4: =INDEX(Individuals!L2:L999, MATCH(C4,Individuals!A2:A999, 0)) -> /intake/new-patient/reyes-ana | L4: =K4 & "/assays/" & A4 -> /intake/new-patient/reyes-ana/assays/assay-a-prot | M4: =INDEX(OmicsModalities!B2:B999, MATCH(D4,OmicsModalities!A2:A999, 0)) -> Proteomics | N4: =IF(E4 = "", "Missing Tissue", INDEX(Tissues!B2:B999, MATCH(E4,Tissues!A2:A999, 0))) -> Blood | O4: =IF(H4 > 0.3, TRUE(), FALSE()) -> FALSE | P4: =IF(AND(NOT(O4), H4 < 0.15), TRUE(), FALSE()) -> TRUE
A5: assay-b-rna | B5: assay-b-rna | C5: ind-b-okafor | D5: rna-seq | E5: blood | G5: b1 | H5: 0.05 | I5: TRUE | J5: =B5 -> assay-b-rna | K5: =INDEX(Individuals!L2:L999, MATCH(C5,Individuals!A2:A999, 0)) -> /intake/new-patient/okafor-bili | L5: =K5 & "/assays/" & A5 -> /intake/new-patient/okafor-bili/assays/assay-b-rna | M5: =INDEX(OmicsModalities!B2:B999, MATCH(D5,OmicsModalities!A2:A999, 0)) -> RNA-seq | N5: =IF(E5 = "", "Missing Tissue", INDEX(Tissues!B2:B999, MATCH(E5,Tissues!A2:A999, 0))) -> Blood | O5: =IF(H5 > 0.3, TRUE(), FALSE()) -> FALSE | P5: =IF(AND(NOT(O5), H5 < 0.15), TRUE(), FALSE()) -> TRUE
A6: assay-b-atac | B6: assay-b-atac | C6: ind-b-okafor | D6: atac-seq | E6: blood | G6: b1 | H6: 0.05 | I6: TRUE | J6: =B6 -> assay-b-atac | K6: =INDEX(Individuals!L2:L999, MATCH(C6,Individuals!A2:A999, 0)) -> /intake/new-patient/okafor-bili | L6: =K6 & "/assays/" & A6 -> /intake/new-patient/okafor-bili/assays/assay-b-atac | M6: =INDEX(OmicsModalities!B2:B999, MATCH(D6,OmicsModalities!A2:A999, 0)) -> ATAC-seq | N6: =IF(E6 = "", "Missing Tissue", INDEX(Tissues!B2:B999, MATCH(E6,Tissues!A2:A999, 0))) -> Blood | O6: =IF(H6 > 0.3, TRUE(), FALSE()) -> FALSE | P6: =IF(AND(NOT(O6), H6 < 0.15), TRUE(), FALSE()) -> TRUE
A7: assay-b-prot | B7: assay-b-prot | C7: ind-b-okafor | D7: proteomics | E7: blood | G7: b1 | H7: 0.05 | I7: TRUE | J7: =B7 -> assay-b-prot | K7: =INDEX(Individuals!L2:L999, MATCH(C7,Individuals!A2:A999, 0)) -> /intake/new-patient/okafor-bili | L7: =K7 & "/assays/" & A7 -> /intake/new-patient/okafor-bili/assays/assay-b-prot | M7: =INDEX(OmicsModalities!B2:B999, MATCH(D7,OmicsModalities!A2:A999, 0)) -> Proteomics | N7: =IF(E7 = "", "Missing Tissue", INDEX(Tissues!B2:B999, MATCH(E7,Tissues!A2:A999, 0))) -> Blood | O7: =IF(H7 > 0.3, TRUE(), FALSE()) -> FALSE | P7: =IF(AND(NOT(O7), H7 < 0.15), TRUE(), FALSE()) -> TRUE
A8: assay-c-rna | B8: assay-c-rna | C8: ind-c-chen | D8: rna-seq | E8: blood | G8: b1 | H8: 0.05 | I8: TRUE | J8: =B8 -> assay-c-rna | K8: =INDEX(Individuals!L2:L999, MATCH(C8,Individuals!A2:A999, 0)) -> /intake/new-patient/wei-chen | L8: =K8 & "/assays/" & A8 -> /intake/new-patient/wei-chen/assays/assay-c-rna | M8: =INDEX(OmicsModalities!B2:B999, MATCH(D8,OmicsModalities!A2:A999, 0)) -> RNA-seq | N8: =IF(E8 = "", "Missing Tissue", INDEX(Tissues!B2:B999, MATCH(E8,Tissues!A2:A999, 0))) -> Blood | O8: =IF(H8 > 0.3, TRUE(), FALSE()) -> FALSE | P8: =IF(AND(NOT(O8), H8 < 0.15), TRUE(), FALSE()) -> TRUE
A9: assay-c-atac | B9: assay-c-atac | C9: ind-c-chen | D9: atac-seq | E9: blood | G9: b1 | H9: 0.05 | I9: TRUE | J9: =B9 -> assay-c-atac | K9: =INDEX(Individuals!L2:L999, MATCH(C9,Individuals!A2:A999, 0)) -> /intake/new-patient/wei-chen | L9: =K9 & "/assays/" & A9 -> /intake/new-patient/wei-chen/assays/assay-c-atac | M9: =INDEX(OmicsModalities!B2:B999, MATCH(D9,OmicsModalities!A2:A999, 0)) -> ATAC-seq | N9: =IF(E9 = "", "Missing Tissue", INDEX(Tissues!B2:B999, MATCH(E9,Tissues!A2:A999, 0))) -> Blood | O9: =IF(H9 > 0.3, TRUE(), FALSE()) -> FALSE | P9: =IF(AND(NOT(O9), H9 < 0.15), TRUE(), FALSE()) -> TRUE
A10: assay-c-prot | B10: assay-c-prot | C10: ind-c-chen | D10: proteomics | E10: blood | G10: b1 | H10: 0.05 | I10: TRUE | J10: =B10 -> assay-c-prot | K10: =INDEX(Individuals!L2:L999, MATCH(C10,Individuals!A2:A999, 0)) -> /intake/new-patient/wei-chen | L10: =K10 & "/assays/" & A10 -> /intake/new-patient/wei-chen/assays/assay-c-prot | M10: =INDEX(OmicsModalities!B2:B999, MATCH(D10,OmicsModalities!A2:A999, 0)) -> Proteomics | N10: =IF(E10 = "", "Missing Tissue", INDEX(Tissues!B2:B999, MATCH(E10,Tissues!A2:A999, 0))) -> Blood | O10: =IF(H10 > 0.3, TRUE(), FALSE()) -> FALSE | P10: =IF(AND(NOT(O10), H10 < 0.15), TRUE(), FALSE()) -> TRUE
A11: assay-d-rna | B11: assay-d-rna | C11: ind-d-santos | D11: rna-seq | E11: blood | G11: b1 | H11: 0.05 | I11: TRUE | J11: =B11 -> assay-d-rna | K11: =INDEX(Individuals!L2:L999, MATCH(C11,Individuals!A2:A999, 0)) -> /intake/new-patient/santos-diego | L11: =K11 & "/assays/" & A11 -> /intake/new-patient/santos-diego/assays/assay-d-rna | M11: =INDEX(OmicsModalities!B2:B999, MATCH(D11,OmicsModalities!A2:A999, 0)) -> RNA-seq | N11: =IF(E11 = "", "Missing Tissue", INDEX(Tissues!B2:B999, MATCH(E11,Tissues!A2:A999, 0))) -> Blood | O11: =IF(H11 > 0.3, TRUE(), FALSE()) -> FALSE | P11: =IF(AND(NOT(O11), H11 < 0.15), TRUE(), FALSE()) -> TRUE
A12: assay-d-atac | B12: assay-d-atac | C12: ind-d-santos | D12: atac-seq | E12: blood | G12: b1 | H12: 0.05 | I12: TRUE | J12: =B12 -> assay-d-atac | K12: =INDEX(Individuals!L2:L999, MATCH(C12,Individuals!A2:A999, 0)) -> /intake/new-patient/santos-diego | L12: =K12 & "/assays/" & A12 -> /intake/new-patient/santos-diego/assays/assay-d-atac | M12: =INDEX(OmicsModalities!B2:B999, MATCH(D12,OmicsModalities!A2:A999, 0)) -> ATAC-seq | N12: =IF(E12 = "", "Missing Tissue", INDEX(Tissues!B2:B999, MATCH(E12,Tissues!A2:A999, 0))) -> Blood | O12: =IF(H12 > 0.3, TRUE(), FALSE()) -> FALSE | P12: =IF(AND(NOT(O12), H12 < 0.15), TRUE(), FALSE()) -> TRUE
A13: assay-d-prot | B13: assay-d-prot | C13: ind-d-santos | D13: proteomics | E13: blood | G13: b1 | H13: 0.05 | I13: TRUE | J13: =B13 -> assay-d-prot | K13: =INDEX(Individuals!L2:L999, MATCH(C13,Individuals!A2:A999, 0)) -> /intake/new-patient/santos-diego | L13: =K13 & "/assays/" & A13 -> /intake/new-patient/santos-diego/assays/assay-d-prot | M13: =INDEX(OmicsModalities!B2:B999, MATCH(D13,OmicsModalities!A2:A999, 0)) -> Proteomics | N13: =IF(E13 = "", "Missing Tissue", INDEX(Tissues!B2:B999, MATCH(E13,Tissues!A2:A999, 0))) -> Blood | O13: =IF(H13 > 0.3, TRUE(), FALSE()) -> FALSE | P13: =IF(AND(NOT(O13), H13 < 0.15), TRUE(), FALSE()) -> TRUE
A14: assay-e-rna | B14: assay-e-rna | C14: ind-e-mensah | D14: rna-seq | E14: blood | G14: b1 | H14: 0.05 | I14: TRUE | J14: =B14 -> assay-e-rna | K14: =INDEX(Individuals!L2:L999, MATCH(C14,Individuals!A2:A999, 0)) -> /intake/new-patient/mensah-esi | L14: =K14 & "/assays/" & A14 -> /intake/new-patient/mensah-esi/assays/assay-e-rna | M14: =INDEX(OmicsModalities!B2:B999, MATCH(D14,OmicsModalities!A2:A999, 0)) -> RNA-seq | N14: =IF(E14 = "", "Missing Tissue", INDEX(Tissues!B2:B999, MATCH(E14,Tissues!A2:A999, 0))) -> Blood | O14: =IF(H14 > 0.3, TRUE(), FALSE()) -> FALSE | P14: =IF(AND(NOT(O14), H14 < 0.15), TRUE(), FALSE()) -> TRUE
A15: assay-e-atac | B15: assay-e-atac | C15: ind-e-mensah | D15: atac-seq | E15: blood | G15: b1 | H15: 0.05 | I15: TRUE | J15: =B15 -> assay-e-atac | K15: =INDEX(Individuals!L2:L999, MATCH(C15,Individuals!A2:A999, 0)) -> /intake/new-patient/mensah-esi | L15: =K15 & "/assays/" & A15 -> /intake/new-patient/mensah-esi/assays/assay-e-atac | M15: =INDEX(OmicsModalities!B2:B999, MATCH(D15,OmicsModalities!A2:A999, 0)) -> ATAC-seq | N15: =IF(E15 = "", "Missing Tissue", INDEX(Tissues!B2:B999, MATCH(E15,Tissues!A2:A999, 0))) -> Blood | O15: =IF(H15 > 0.3, TRUE(), FALSE()) -> FALSE | P15: =IF(AND(NOT(O15), H15 < 0.15), TRUE(), FALSE()) -> TRUE
A16: assay-e-prot | B16: assay-e-prot | C16: ind-e-mensah | D16: proteomics | E16: blood | G16: b1 | H16: 0.05 | I16: TRUE | J16: =B16 -> assay-e-prot | K16: =INDEX(Individuals!L2:L999, MATCH(C16,Individuals!A2:A999, 0)) -> /intake/new-patient/mensah-esi | L16: =K16 & "/assays/" & A16 -> /intake/new-patient/mensah-esi/assays/assay-e-prot | M16: =INDEX(OmicsModalities!B2:B999, MATCH(D16,OmicsModalities!A2:A999, 0)) -> Proteomics | N16: =IF(E16 = "", "Missing Tissue", INDEX(Tissues!B2:B999, MATCH(E16,Tissues!A2:A999, 0))) -> Blood | O16: =IF(H16 > 0.3, TRUE(), FALSE()) -> FALSE | P16: =IF(AND(NOT(O16), H16 < 0.15), TRUE(), FALSE()) -> TRUE
A17: assay-f-rna | B17: assay-f-rna | C17: ind-f-haidar | D17: rna-seq | E17: blood | G17: b1 | H17: 0.05 | I17: TRUE | J17: =B17 -> assay-f-rna | K17: =INDEX(Individuals!L2:L999, MATCH(C17,Individuals!A2:A999, 0)) -> /intake/new-patient/haidar-faisal | L17: =K17 & "/assays/" & A17 -> /intake/new-patient/haidar-faisal/assays/assay-f-rna | M17: =INDEX(OmicsModalities!B2:B999, MATCH(D17,OmicsModalities!A2:A999, 0)) -> RNA-seq | N17: =IF(E17 = "", "Missing Tissue", INDEX(Tissues!B2:B999, MATCH(E17,Tissues!A2:A999, 0))) -> Blood | O17: =IF(H17 > 0.3, TRUE(), FALSE()) -> FALSE | P17: =IF(AND(NOT(O17), H17 < 0.15), TRUE(), FALSE()) -> TRUE
A18: assay-f-atac | B18: assay-f-atac | C18: ind-f-haidar | D18: atac-seq | E18: blood | G18: b1 | H18: 0.05 | I18: TRUE | J18: =B18 -> assay-f-atac | K18: =INDEX(Individuals!L2:L999, MATCH(C18,Individuals!A2:A999, 0)) -> /intake/new-patient/haidar-faisal | L18: =K18 & "/assays/" & A18 -> /intake/new-patient/haidar-faisal/assays/assay-f-atac | M18: =INDEX(OmicsModalities!B2:B999, MATCH(D18,OmicsModalities!A2:A999, 0)) -> ATAC-seq | N18: =IF(E18 = "", "Missing Tissue", INDEX(Tissues!B2:B999, MATCH(E18,Tissues!A2:A999, 0))) -> Blood | O18: =IF(H18 > 0.3, TRUE(), FALSE()) -> FALSE | P18: =IF(AND(NOT(O18), H18 < 0.15), TRUE(), FALSE()) -> TRUE
A19: assay-f-prot | B19: assay-f-prot | C19: ind-f-haidar | D19: proteomics | E19: blood | G19: b1 | H19: 0.05 | I19: TRUE | J19: =B19 -> assay-f-prot | K19: =INDEX(Individuals!L2:L999, MATCH(C19,Individuals!A2:A999, 0)) -> /intake/new-patient/haidar-faisal | L19: =K19 & "/assays/" & A19 -> /intake/new-patient/haidar-faisal/assays/assay-f-prot | M19: =INDEX(OmicsModalities!B2:B999, MATCH(D19,OmicsModalities!A2:A999, 0)) -> Proteomics | N19: =IF(E19 = "", "Missing Tissue", INDEX(Tissues!B2:B999, MATCH(E19,Tissues!A2:A999, 0))) -> Blood | O19: =IF(H19 > 0.3, TRUE(), FALSE()) -> FALSE | P19: =IF(AND(NOT(O19), H19 < 0.15), TRUE(), FALSE()) -> TRUE
A20: assay-g-rna | B20: assay-g-rna | C20: ind-g-lin | D20: rna-seq | E20: blood | G20: b1 | H20: 0.05 | I20: TRUE | J20: =B20 -> assay-g-rna | K20: =INDEX(Individuals!L2:L999, MATCH(C20,Individuals!A2:A999, 0)) -> /intake/new-patient/lin-grace | L20: =K20 & "/assays/" & A20 -> /intake/new-patient/lin-grace/assays/assay-g-rna | M20: =INDEX(OmicsModalities!B2:B999, MATCH(D20,OmicsModalities!A2:A999, 0)) -> RNA-seq | N20: =IF(E20 = "", "Missing Tissue", INDEX(Tissues!B2:B999, MATCH(E20,Tissues!A2:A999, 0))) -> Blood | O20: =IF(H20 > 0.3, TRUE(), FALSE()) -> FALSE | P20: =IF(AND(NOT(O20), H20 < 0.15), TRUE(), FALSE()) -> TRUE
A21: assay-g-atac | B21: assay-g-atac | C21: ind-g-lin | D21: atac-seq | E21: blood | G21: b1 | H21: 0.05 | I21: TRUE | J21: =B21 -> assay-g-atac | K21: =INDEX(Individuals!L2:L999, MATCH(C21,Individuals!A2:A999, 0)) -> /intake/new-patient/lin-grace | L21: =K21 & "/assays/" & A21 -> /intake/new-patient/lin-grace/assays/assay-g-atac | M21: =INDEX(OmicsModalities!B2:B999, MATCH(D21,OmicsModalities!A2:A999, 0)) -> ATAC-seq | N21: =IF(E21 = "", "Missing Tissue", INDEX(Tissues!B2:B999, MATCH(E21,Tissues!A2:A999, 0))) -> Blood | O21: =IF(H21 > 0.3, TRUE(), FALSE()) -> FALSE | P21: =IF(AND(NOT(O21), H21 < 0.15), TRUE(), FALSE()) -> TRUE
A22: assay-g-prot | B22: assay-g-prot | C22: ind-g-lin | D22: proteomics | E22: blood | G22: b1 | H22: 0.05 | I22: TRUE | J22: =B22 -> assay-g-prot | K22: =INDEX(Individuals!L2:L999, MATCH(C22,Individuals!A2:A999, 0)) -> /intake/new-patient/lin-grace | L22: =K22 & "/assays/" & A22 -> /intake/new-patient/lin-grace/assays/assay-g-prot | M22: =INDEX(OmicsModalities!B2:B999, MATCH(D22,OmicsModalities!A2:A999, 0)) -> Proteomics | N22: =IF(E22 = "", "Missing Tissue", INDEX(Tissues!B2:B999, MATCH(E22,Tissues!A2:A999, 0))) -> Blood | O22: =IF(H22 > 0.3, TRUE(), FALSE()) -> FALSE | P22: =IF(AND(NOT(O22), H22 < 0.15), TRUE(), FALSE()) -> TRUE
A23: assay-h-rna | B23: assay-h-rna | C23: ind-h-yamamoto | D23: rna-seq | E23: blood | G23: b1 | H23: 0.05 | I23: TRUE | J23: =B23 -> assay-h-rna | K23: =INDEX(Individuals!L2:L999, MATCH(C23,Individuals!A2:A999, 0)) -> /intake/new-patient/yamamoto-hana | L23: =K23 & "/assays/" & A23 -> /intake/new-patient/yamamoto-hana/assays/assay-h-rna | M23: =INDEX(OmicsModalities!B2:B999, MATCH(D23,OmicsModalities!A2:A999, 0)) -> RNA-seq | N23: =IF(E23 = "", "Missing Tissue", INDEX(Tissues!B2:B999, MATCH(E23,Tissues!A2:A999, 0))) -> Blood | O23: =IF(H23 > 0.3, TRUE(), FALSE()) -> FALSE | P23: =IF(AND(NOT(O23), H23 < 0.15), TRUE(), FALSE()) -> TRUE
A24: assay-h-atac | B24: assay-h-atac | C24: ind-h-yamamoto | D24: atac-seq | E24: blood | G24: b1 | H24: 0.05 | I24: TRUE | J24: =B24 -> assay-h-atac | K24: =INDEX(Individuals!L2:L999, MATCH(C24,Individuals!A2:A999, 0)) -> /intake/new-patient/yamamoto-hana | L24: =K24 & "/assays/" & A24 -> /intake/new-patient/yamamoto-hana/assays/assay-h-atac | M24: =INDEX(OmicsModalities!B2:B999, MATCH(D24,OmicsModalities!A2:A999, 0)) -> ATAC-seq | N24: =IF(E24 = "", "Missing Tissue", INDEX(Tissues!B2:B999, MATCH(E24,Tissues!A2:A999, 0))) -> Blood | O24: =IF(H24 > 0.3, TRUE(), FALSE()) -> FALSE | P24: =IF(AND(NOT(O24), H24 < 0.15), TRUE(), FALSE()) -> TRUE
A25: assay-h-prot | B25: assay-h-prot | C25: ind-h-yamamoto | D25: proteomics | E25: blood | G25: b1 | H25: 0.05 | I25: TRUE | J25: =B25 -> assay-h-prot | K25: =INDEX(Individuals!L2:L999, MATCH(C25,Individuals!A2:A999, 0)) -> /intake/new-patient/yamamoto-hana | L25: =K25 & "/assays/" & A25 -> /intake/new-patient/yamamoto-hana/assays/assay-h-prot | M25: =INDEX(OmicsModalities!B2:B999, MATCH(D25,OmicsModalities!A2:A999, 0)) -> Proteomics | N25: =IF(E25 = "", "Missing Tissue", INDEX(Tissues!B2:B999, MATCH(E25,Tissues!A2:A999, 0))) -> Blood | O25: =IF(H25 > 0.3, TRUE(), FALSE()) -> FALSE | P25: =IF(AND(NOT(O25), H25 < 0.15), TRUE(), FALSE()) -> TRUE
A26: assay-i-rna | B26: assay-i-rna | C26: ind-i-conteh | D26: rna-seq | E26: blood | G26: b1 | H26: 0.05 | I26: TRUE | J26: =B26 -> assay-i-rna | K26: =INDEX(Individuals!L2:L999, MATCH(C26,Individuals!A2:A999, 0)) -> /intake/new-patient/conteh-ibrahim | L26: =K26 & "/assays/" & A26 -> /intake/new-patient/conteh-ibrahim/assays/assay-i-rna | M26: =INDEX(OmicsModalities!B2:B999, MATCH(D26,OmicsModalities!A2:A999, 0)) -> RNA-seq | N26: =IF(E26 = "", "Missing Tissue", INDEX(Tissues!B2:B999, MATCH(E26,Tissues!A2:A999, 0))) -> Blood | O26: =IF(H26 > 0.3, TRUE(), FALSE()) -> FALSE | P26: =IF(AND(NOT(O26), H26 < 0.15), TRUE(), FALSE()) -> TRUE
A27: assay-i-atac | B27: assay-i-atac | C27: ind-i-conteh | D27: atac-seq | E27: blood | G27: b1 | H27: 0.05 | I27: TRUE | J27: =B27 -> assay-i-atac | K27: =INDEX(Individuals!L2:L999, MATCH(C27,Individuals!A2:A999, 0)) -> /intake/new-patient/conteh-ibrahim | L27: =K27 & "/assays/" & A27 -> /intake/new-patient/conteh-ibrahim/assays/assay-i-atac | M27: =INDEX(OmicsModalities!B2:B999, MATCH(D27,OmicsModalities!A2:A999, 0)) -> ATAC-seq | N27: =IF(E27 = "", "Missing Tissue", INDEX(Tissues!B2:B999, MATCH(E27,Tissues!A2:A999, 0))) -> Blood | O27: =IF(H27 > 0.3, TRUE(), FALSE()) -> FALSE | P27: =IF(AND(NOT(O27), H27 < 0.15), TRUE(), FALSE()) -> TRUE
A28: assay-i-prot | B28: assay-i-prot | C28: ind-i-conteh | D28: proteomics | E28: blood | G28: b1 | H28: 0.05 | I28: TRUE | J28: =B28 -> assay-i-prot | K28: =INDEX(Individuals!L2:L999, MATCH(C28,Individuals!A2:A999, 0)) -> /intake/new-patient/conteh-ibrahim | L28: =K28 & "/assays/" & A28 -> /intake/new-patient/conteh-ibrahim/assays/assay-i-prot | M28: =INDEX(OmicsModalities!B2:B999, MATCH(D28,OmicsModalities!A2:A999, 0)) -> Proteomics | N28: =IF(E28 = "", "Missing Tissue", INDEX(Tissues!B2:B999, MATCH(E28,Tissues!A2:A999, 0))) -> Blood | O28: =IF(H28 > 0.3, TRUE(), FALSE()) -> FALSE | P28: =IF(AND(NOT(O28), H28 < 0.15), TRUE(), FALSE()) -> TRUE
A29: assay-j-rna | B29: assay-j-rna | C29: ind-j-brooks | D29: rna-seq | E29: blood | G29: b1 | H29: 0.05 | I29: TRUE | J29: =B29 -> assay-j-rna | K29: =INDEX(Individuals!L2:L999, MATCH(C29,Individuals!A2:A999, 0)) -> /intake/new-patient/brooks-jamal | L29: =K29 & "/assays/" & A29 -> /intake/new-patient/brooks-jamal/assays/assay-j-rna | M29: =INDEX(OmicsModalities!B2:B999, MATCH(D29,OmicsModalities!A2:A999, 0)) -> RNA-seq | N29: =IF(E29 = "", "Missing Tissue", INDEX(Tissues!B2:B999, MATCH(E29,Tissues!A2:A999, 0))) -> Blood | O29: =IF(H29 > 0.3, TRUE(), FALSE()) -> FALSE | P29: =IF(AND(NOT(O29), H29 < 0.15), TRUE(), FALSE()) -> TRUE
A30: assay-j-atac | B30: assay-j-atac | C30: ind-j-brooks | D30: atac-seq | E30: blood | G30: b1 | H30: 0.05 | I30: TRUE | J30: =B30 -> assay-j-atac | K30: =INDEX(Individuals!L2:L999, MATCH(C30,Individuals!A2:A999, 0)) -> /intake/new-patient/brooks-jamal | L30: =K30 & "/assays/" & A30 -> /intake/new-patient/brooks-jamal/assays/assay-j-atac | M30: =INDEX(OmicsModalities!B2:B999, MATCH(D30,OmicsModalities!A2:A999, 0)) -> ATAC-seq | N30: =IF(E30 = "", "Missing Tissue", INDEX(Tissues!B2:B999, MATCH(E30,Tissues!A2:A999, 0))) -> Blood | O30: =IF(H30 > 0.3, TRUE(), FALSE()) -> FALSE | P30: =IF(AND(NOT(O30), H30 < 0.15), TRUE(), FALSE()) -> TRUE
A31: assay-j-prot | B31: assay-j-prot | C31: ind-j-brooks | D31: proteomics | E31: blood | G31: b1 | H31: 0.05 | I31: TRUE | J31: =B31 -> assay-j-prot | K31: =INDEX(Individuals!L2:L999, MATCH(C31,Individuals!A2:A999, 0)) -> /intake/new-patient/brooks-jamal | L31: =K31 & "/assays/" & A31 -> /intake/new-patient/brooks-jamal/assays/assay-j-prot | M31: =INDEX(OmicsModalities!B2:B999, MATCH(D31,OmicsModalities!A2:A999, 0)) -> Proteomics | N31: =IF(E31 = "", "Missing Tissue", INDEX(Tissues!B2:B999, MATCH(E31,Tissues!A2:A999, 0))) -> Blood | O31: =IF(H31 > 0.3, TRUE(), FALSE()) -> FALSE | P31: =IF(AND(NOT(O31), H31 < 0.15), TRUE(), FALSE()) -> TRUE
A32: assay-k-rna | B32: assay-k-rna | C32: ind-k-nair | D32: rna-seq | E32: blood | G32: b1 | H32: 0.05 | I32: TRUE | J32: =B32 -> assay-k-rna | K32: =INDEX(Individuals!L2:L999, MATCH(C32,Individuals!A2:A999, 0)) -> /intake/new-patient/nair-kavya | L32: =K32 & "/assays/" & A32 -> /intake/new-patient/nair-kavya/assays/assay-k-rna | M32: =INDEX(OmicsModalities!B2:B999, MATCH(D32,OmicsModalities!A2:A999, 0)) -> RNA-seq | N32: =IF(E32 = "", "Missing Tissue", INDEX(Tissues!B2:B999, MATCH(E32,Tissues!A2:A999, 0))) -> Blood | O32: =IF(H32 > 0.3, TRUE(), FALSE()) -> FALSE | P32: =IF(AND(NOT(O32), H32 < 0.15), TRUE(), FALSE()) -> TRUE
A33: assay-k-atac | B33: assay-k-atac | C33: ind-k-nair | D33: atac-seq | E33: blood | G33: b1 | H33: 0.05 | I33: TRUE | J33: =B33 -> assay-k-atac | K33: =INDEX(Individuals!L2:L999, MATCH(C33,Individuals!A2:A999, 0)) -> /intake/new-patient/nair-kavya | L33: =K33 & "/assays/" & A33 -> /intake/new-patient/nair-kavya/assays/assay-k-atac | M33: =INDEX(OmicsModalities!B2:B999, MATCH(D33,OmicsModalities!A2:A999, 0)) -> ATAC-seq | N33: =IF(E33 = "", "Missing Tissue", INDEX(Tissues!B2:B999, MATCH(E33,Tissues!A2:A999, 0))) -> Blood | O33: =IF(H33 > 0.3, TRUE(), FALSE()) -> FALSE | P33: =IF(AND(NOT(O33), H33 < 0.15), TRUE(), FALSE()) -> TRUE
A34: assay-k-prot | B34: assay-k-prot | C34: ind-k-nair | D34: proteomics | E34: blood | G34: b1 | H34: 0.05 | I34: TRUE | J34: =B34 -> assay-k-prot | K34: =INDEX(Individuals!L2:L999, MATCH(C34,Individuals!A2:A999, 0)) -> /intake/new-patient/nair-kavya | L34: =K34 & "/assays/" & A34 -> /intake/new-patient/nair-kavya/assays/assay-k-prot | M34: =INDEX(OmicsModalities!B2:B999, MATCH(D34,OmicsModalities!A2:A999, 0)) -> Proteomics | N34: =IF(E34 = "", "Missing Tissue", INDEX(Tissues!B2:B999, MATCH(E34,Tissues!A2:A999, 0))) -> Blood | O34: =IF(H34 > 0.3, TRUE(), FALSE()) -> FALSE | P34: =IF(AND(NOT(O34), H34 < 0.15), TRUE(), FALSE()) -> TRUE
A35: assay-l-rna | B35: assay-l-rna | C35: ind-l-brandt | D35: rna-seq | E35: blood | G35: b1 | H35: 0.05 | I35: TRUE | J35: =B35 -> assay-l-rna | K35: =INDEX(Individuals!L2:L999, MATCH(C35,Individuals!A2:A999, 0)) -> /intake/new-patient/brandt-lena | L35: =K35 & "/assays/" & A35 -> /intake/new-patient/brandt-lena/assays/assay-l-rna | M35: =INDEX(OmicsModalities!B2:B999, MATCH(D35,OmicsModalities!A2:A999, 0)) -> RNA-seq | N35: =IF(E35 = "", "Missing Tissue", INDEX(Tissues!B2:B999, MATCH(E35,Tissues!A2:A999, 0))) -> Blood | O35: =IF(H35 > 0.3, TRUE(), FALSE()) -> FALSE | P35: =IF(AND(NOT(O35), H35 < 0.15), TRUE(), FALSE()) -> TRUE
A36: assay-l-atac | B36: assay-l-atac | C36: ind-l-brandt | D36: atac-seq | E36: blood | G36: b1 | H36: 0.05 | I36: TRUE | J36: =B36 -> assay-l-atac | K36: =INDEX(Individuals!L2:L999, MATCH(C36,Individuals!A2:A999, 0)) -> /intake/new-patient/brandt-lena | L36: =K36 & "/assays/" & A36 -> /intake/new-patient/brandt-lena/assays/assay-l-atac | M36: =INDEX(OmicsModalities!B2:B999, MATCH(D36,OmicsModalities!A2:A999, 0)) -> ATAC-seq | N36: =IF(E36 = "", "Missing Tissue", INDEX(Tissues!B2:B999, MATCH(E36,Tissues!A2:A999, 0))) -> Blood | O36: =IF(H36 > 0.3, TRUE(), FALSE()) -> FALSE | P36: =IF(AND(NOT(O36), H36 < 0.15), TRUE(), FALSE()) -> TRUE
A37: assay-l-prot | B37: assay-l-prot | C37: ind-l-brandt | D37: proteomics | E37: blood | G37: b1 | H37: 0.05 | I37: TRUE | J37: =B37 -> assay-l-prot | K37: =INDEX(Individuals!L2:L999, MATCH(C37,Individuals!A2:A999, 0)) -> /intake/new-patient/brandt-lena | L37: =K37 & "/assays/" & A37 -> /intake/new-patient/brandt-lena/assays/assay-l-prot | M37: =INDEX(OmicsModalities!B2:B999, MATCH(D37,OmicsModalities!A2:A999, 0)) -> Proteomics | N37: =IF(E37 = "", "Missing Tissue", INDEX(Tissues!B2:B999, MATCH(E37,Tissues!A2:A999, 0))) -> Blood | O37: =IF(H37 > 0.3, TRUE(), FALSE()) -> FALSE | P37: =IF(AND(NOT(O37), H37 < 0.15), TRUE(), FALSE()) -> TRUE

Sheet EvidenceItems
A1: EvidenceItemId | B1: EvidenceLabel | C1: CausalMechanism | D1: OmicsAssay | E1: EffectSize | F1: StandardError | G1: IsCrossModality | H1: IsNegativeControlArm | I1: IsAdjustedForAncestryPCs | J1: IsAdjustedForBatch | K1: IsSyntheticLeaf | L1: RepresentsAssayModality | M1: IdentificationAssumption | N1: Name | O1: ParentPath | P1: RelativePath | Q1: AssayIsHighQuality | R1: ZStat | S1: IsConfoundControlled | T1: IsQualifiedEvidence | U1: SourceQuote
A2: ev-a-1 | B2: ev-a-1 | C2: cm-a | D2: assay-a-rna | E2: 0.91 | F2: 0.2 | G2: FALSE | H2: FALSE | I2: TRUE | J2: TRUE | K2: TRUE | L2: cis-eQTL, blood RNA-seq | M2: colocalization PP4>0.8; no horizontal pleiotropy on the eQTL instrument | N2: =B2 -> ev-a-1 | O2: =INDEX(CausalMechanisms!L2:L999, MATCH(C2,CausalMechanisms!A2:A999, 0)) -> /intake/new-patient/reyes-ana/mechanisms/cm-a | P2: =O2 & "/evidence/" & A2 -> /intake/new-patient/reyes-ana/mechanisms/cm-a/evidence/ev-a-1 | Q2: =INDEX(OmicsAssays!P2:P999, MATCH(D2,OmicsAssays!A2:A999, 0)) -> TRUE | R2: =IF(F2 > 0, E2 / F2, 0) -> 4.55 | S2: =IF(AND(I2, J2), TRUE(), FALSE()) -> TRUE | T2: =IF(AND(Q2, NOT(H2), R2 >= 2, S2), TRUE(), FALSE()) -> TRUE | U2: cis-eQTL in blood RNA-seq with effect 0.91 (SE 0.20)
A3: ev-a-2 | B3: ev-a-2 | C3: cm-a | D3: assay-a-atac | E3: 0.73 | F3: 0.19 | G3: TRUE | H3: FALSE | I3: TRUE | J3: TRUE | K3: TRUE | L3: caQTL, blood ATAC-seq | M3: open-chromatin peak maps to the credible set; cell-state confounding adjusted | N3: =B3 -> ev-a-2 | O3: =INDEX(CausalMechanisms!L2:L999, MATCH(C3,CausalMechanisms!A2:A999, 0)) -> /intake/new-patient/reyes-ana/mechanisms/cm-a | P3: =O3 & "/evidence/" & A3 -> /intake/new-patient/reyes-ana/mechanisms/cm-a/evidence/ev-a-2 | Q3: =INDEX(OmicsAssays!P2:P999, MATCH(D3,OmicsAssays!A2:A999, 0)) -> TRUE | R3: =IF(F3 > 0, E3 / F3, 0) -> 3.8421053 | S3: =IF(AND(I3, J3), TRUE(), FALSE()) -> TRUE | T3: =IF(AND(Q3, NOT(H3), R3 >= 2, S3), TRUE(), FALSE()) -> TRUE | U3: caQTL in blood ATAC-seq with effect 0.73 (SE 0.19)
A4: ev-a-3 | B4: ev-a-3 | C4: cm-a | D4: assay-a-prot | E4: 0.66 | F4: 0.205 | G4: TRUE | H4: FALSE | I4: TRUE | J4: TRUE | K4: TRUE | L4: pQTL, blood mass-spec proteomics | M4: cis-pQTL within 1Mb; aptamer/epitope-binding artifact excluded | N4: =B4 -> ev-a-3 | O4: =INDEX(CausalMechanisms!L2:L999, MATCH(C4,CausalMechanisms!A2:A999, 0)) -> /intake/new-patient/reyes-ana/mechanisms/cm-a | P4: =O4 & "/evidence/" & A4 -> /intake/new-patient/reyes-ana/mechanisms/cm-a/evidence/ev-a-3 | Q4: =INDEX(OmicsAssays!P2:P999, MATCH(D4,OmicsAssays!A2:A999, 0)) -> TRUE | R4: =IF(F4 > 0, E4 / F4, 0) -> 3.2195122 | S4: =IF(AND(I4, J4), TRUE(), FALSE()) -> TRUE | T4: =IF(AND(Q4, NOT(H4), R4 >= 2, S4), TRUE(), FALSE()) -> TRUE | U4: pQTL in blood proteomics with effect 0.66 (SE 0.20)
A5: ev-b-1 | B5: ev-b-1 | C5: cm-b | D5: assay-b-rna | E5: 0.84 | F5: 0.21 | G5: FALSE | H5: FALSE | I5: TRUE | J5: TRUE | K5: TRUE | L5: cis-eQTL, blood RNA-seq | M5: colocalization PP4>0.8; no horizontal pleiotropy on the eQTL instrument | N5: =B5 -> ev-b-1 | O5: =INDEX(CausalMechanisms!L2:L999, MATCH(C5,CausalMechanisms!A2:A999, 0)) -> /intake/new-patient/okafor-bili/mechanisms/cm-b | P5: =O5 & "/evidence/" & A5 -> /intake/new-patient/okafor-bili/mechanisms/cm-b/evidence/ev-b-1 | Q5: =INDEX(OmicsAssays!P2:P999, MATCH(D5,OmicsAssays!A2:A999, 0)) -> TRUE | R5: =IF(F5 > 0, E5 / F5, 0) -> 4 | S5: =IF(AND(I5, J5), TRUE(), FALSE()) -> TRUE | T5: =IF(AND(Q5, NOT(H5), R5 >= 2, S5), TRUE(), FALSE()) -> TRUE | U5: cis-eQTL in blood RNA-seq with effect 0.84 (SE 0.21)
A6: ev-b-2 | B6: ev-b-2 | C6: cm-b | D6: assay-b-atac | E6: 0.79 | F6: 0.205 | G6: TRUE | H6: FALSE | I6: TRUE | J6: TRUE | K6: TRUE | L6: caQTL, blood ATAC-seq | M6: open-chromatin peak maps to the credible set; cell-state confounding adjusted | N6: =B6 -> ev-b-2 | O6: =INDEX(CausalMechanisms!L2:L999, MATCH(C6,CausalMechanisms!A2:A999, 0)) -> /intake/new-patient/okafor-bili/mechanisms/cm-b | P6: =O6 & "/evidence/" & A6 -> /intake/new-patient/okafor-bili/mechanisms/cm-b/evidence/ev-b-2 | Q6: =INDEX(OmicsAssays!P2:P999, MATCH(D6,OmicsAssays!A2:A999, 0)) -> TRUE | R6: =IF(F6 > 0, E6 / F6, 0) -> 3.8536585 | S6: =IF(AND(I6, J6), TRUE(), FALSE()) -> TRUE | T6: =IF(AND(Q6, NOT(H6), R6 >= 2, S6), TRUE(), FALSE()) -> TRUE | U6: caQTL in blood ATAC-seq with effect 0.79 (SE 0.20)
A7: ev-b-3 | B7: ev-b-3 | C7: cm-b | D7: assay-b-prot | E7: 0.58 | F7: 0.205 | G7: TRUE | H7: FALSE | I7: TRUE | J7: TRUE | K7: TRUE | L7: pQTL, blood mass-spec proteomics | M7: cis-pQTL within 1Mb; aptamer/epitope-binding artifact excluded | N7: =B7 -> ev-b-3 | O7: =INDEX(CausalMechanisms!L2:L999, MATCH(C7,CausalMechanisms!A2:A999, 0)) -> /intake/new-patient/okafor-bili/mechanisms/cm-b | P7: =O7 & "/evidence/" & A7 -> /intake/new-patient/okafor-bili/mechanisms/cm-b/evidence/ev-b-3 | Q7: =INDEX(OmicsAssays!P2:P999, MATCH(D7,OmicsAssays!A2:A999, 0)) -> TRUE | R7: =IF(F7 > 0, E7 / F7, 0) -> 2.8292683 | S7: =IF(AND(I7, J7), TRUE(), FALSE()) -> TRUE | T7: =IF(AND(Q7, NOT(H7), R7 >= 2, S7), TRUE(), FALSE()) -> TRUE | U7: pQTL in blood proteomics with effect 0.58 (SE 0.20)
A8: ev-c-1 | B8: ev-c-1 | C8: cm-c | D8: assay-c-rna | E8: 1.02 | F8: 0.225 | G8: FALSE | H8: FALSE | I8: TRUE | J8: TRUE | K8: TRUE | L8: cis-eQTL, blood RNA-seq | M8: colocalization PP4>0.8; no horizontal pleiotropy on the eQTL instrument | N8: =B8 -> ev-c-1 | O8: =INDEX(CausalMechanisms!L2:L999, MATCH(C8,CausalMechanisms!A2:A999, 0)) -> /intake/new-patient/wei-chen/mechanisms/cm-c | P8: =O8 & "/evidence/" & A8 -> /intake/new-patient/wei-chen/mechanisms/cm-c/evidence/ev-c-1 | Q8: =INDEX(OmicsAssays!P2:P999, MATCH(D8,OmicsAssays!A2:A999, 0)) -> TRUE | R8: =IF(F8 > 0, E8 / F8, 0) -> 4.5333333 | S8: =IF(AND(I8, J8), TRUE(), FALSE()) -> TRUE | T8: =IF(AND(Q8, NOT(H8), R8 >= 2, S8), TRUE(), FALSE()) -> TRUE | U8: cis-eQTL in blood RNA-seq with effect 1.02 (SE 0.23)
A9: ev-c-2 | B9: ev-c-2 | C9: cm-c | D9: assay-c-atac | E9: 0.61 | F9: 0.205 | G9: TRUE | H9: FALSE | I9: TRUE | J9: TRUE | K9: TRUE | L9: caQTL, blood ATAC-seq | M9: open-chromatin peak maps to the credible set; cell-state confounding adjusted | N9: =B9 -> ev-c-2 | O9: =INDEX(CausalMechanisms!L2:L999, MATCH(C9,CausalMechanisms!A2:A999, 0)) -> /intake/new-patient/wei-chen/mechanisms/cm-c | P9: =O9 & "/evidence/" & A9 -> /intake/new-patient/wei-chen/mechanisms/cm-c/evidence/ev-c-2 | Q9: =INDEX(OmicsAssays!P2:P999, MATCH(D9,OmicsAssays!A2:A999, 0)) -> TRUE | R9: =IF(F9 > 0, E9 / F9, 0) -> 2.9756098 | S9: =IF(AND(I9, J9), TRUE(), FALSE()) -> TRUE | T9: =IF(AND(Q9, NOT(H9), R9 >= 2, S9), TRUE(), FALSE()) -> TRUE | U9: caQTL in blood ATAC-seq with effect 0.61 (SE 0.20)
A10: ev-c-3 | B10: ev-c-3 | C10: cm-c | D10: assay-c-prot | E10: 0.55 | F10: 0.215 | G10: TRUE | H10: FALSE | I10: TRUE | J10: TRUE | K10: TRUE | L10: pQTL, blood mass-spec proteomics | M10: cis-pQTL within 1Mb; aptamer/epitope-binding artifact excluded | N10: =B10 -> ev-c-3 | O10: =INDEX(CausalMechanisms!L2:L999, MATCH(C10,CausalMechanisms!A2:A999, 0)) -> /intake/new-patient/wei-chen/mechanisms/cm-c | P10: =O10 & "/evidence/" & A10 -> /intake/new-patient/wei-chen/mechanisms/cm-c/evidence/ev-c-3 | Q10: =INDEX(OmicsAssays!P2:P999, MATCH(D10,OmicsAssays!A2:A999, 0)) -> TRUE | R10: =IF(F10 > 0, E10 / F10, 0) -> 2.5581395 | S10: =IF(AND(I10, J10), TRUE(), FALSE()) -> TRUE | T10: =IF(AND(Q10, NOT(H10), R10 >= 2, S10), TRUE(), FALSE()) -> TRUE | U10: pQTL in blood proteomics with effect 0.55 (SE 0.21)
A11: ev-d-1 | B11: ev-d-1 | C11: cm-d | D11: assay-d-rna | E11: 0.88 | F11: 0.205 | G11: FALSE | H11: FALSE | I11: TRUE | J11: TRUE | K11: TRUE | L11: cis-eQTL, blood RNA-seq | M11: colocalization PP4>0.8; no horizontal pleiotropy on the eQTL instrument | N11: =B11 -> ev-d-1 | O11: =INDEX(CausalMechanisms!L2:L999, MATCH(C11,CausalMechanisms!A2:A999, 0)) -> /intake/new-patient/santos-diego/mechanisms/cm-d | P11: =O11 & "/evidence/" & A11 -> /intake/new-patient/santos-diego/mechanisms/cm-d/evidence/ev-d-1 | Q11: =INDEX(OmicsAssays!P2:P999, MATCH(D11,OmicsAssays!A2:A999, 0)) -> TRUE | R11: =IF(F11 > 0, E11 / F11, 0) -> 4.2926829 | S11: =IF(AND(I11, J11), TRUE(), FALSE()) -> TRUE | T11: =IF(AND(Q11, NOT(H11), R11 >= 2, S11), TRUE(), FALSE()) -> TRUE | U11: cis-eQTL in blood RNA-seq with effect 0.88 (SE 0.20)
A12: ev-d-2 | B12: ev-d-2 | C12: cm-d | D12: assay-d-atac | E12: 0.95 | F12: 0.21 | G12: TRUE | H12: FALSE | I12: TRUE | J12: TRUE | K12: TRUE | L12: caQTL, blood ATAC-seq | M12: open-chromatin peak maps to the credible set; cell-state confounding adjusted | N12: =B12 -> ev-d-2 | O12: =INDEX(CausalMechanisms!L2:L999, MATCH(C12,CausalMechanisms!A2:A999, 0)) -> /intake/new-patient/santos-diego/mechanisms/cm-d | P12: =O12 & "/evidence/" & A12 -> /intake/new-patient/santos-diego/mechanisms/cm-d/evidence/ev-d-2 | Q12: =INDEX(OmicsAssays!P2:P999, MATCH(D12,OmicsAssays!A2:A999, 0)) -> TRUE | R12: =IF(F12 > 0, E12 / F12, 0) -> 4.5238095 | S12: =IF(AND(I12, J12), TRUE(), FALSE()) -> TRUE | T12: =IF(AND(Q12, NOT(H12), R12 >= 2, S12), TRUE(), FALSE()) -> TRUE | U12: caQTL in blood ATAC-seq with effect 0.95 (SE 0.21)
A13: ev-d-3 | B13: ev-d-3 | C13: cm-d | D13: assay-d-prot | E13: 0.62 | F13: 0.205 | G13: TRUE | H13: FALSE | I13: TRUE | J13: TRUE | K13: TRUE | L13: pQTL, blood mass-spec proteomics | M13: cis-pQTL within 1Mb; aptamer/epitope-binding artifact excluded | N13: =B13 -> ev-d-3 | O13: =INDEX(CausalMechanisms!L2:L999, MATCH(C13,CausalMechanisms!A2:A999, 0)) -> /intake/new-patient/santos-diego/mechanisms/cm-d | P13: =O13 & "/evidence/" & A13 -> /intake/new-patient/santos-diego/mechanisms/cm-d/evidence/ev-d-3 | Q13: =INDEX(OmicsAssays!P2:P999, MATCH(D13,OmicsAssays!A2:A999, 0)) -> TRUE | R13: =IF(F13 > 0, E13 / F13, 0) -> 3.0243902 | S13: =IF(AND(I13, J13), TRUE(), FALSE()) -> TRUE | T13: =IF(AND(Q13, NOT(H13), R13 >= 2, S13), TRUE(), FALSE()) -> TRUE | U13: pQTL in blood proteomics with effect 0.62 (SE 0.20)
A14: ev-e-1 | B14: ev-e-1 | C14: cm-e | D14: assay-e-rna | E14: 0.79 | F14: 0.21 | G14: FALSE | H14: FALSE | I14: TRUE | J14: TRUE | K14: TRUE | L14: cis-eQTL, blood RNA-seq | M14: colocalization PP4>0.8; no horizontal pleiotropy on the eQTL instrument | N14: =B14 -> ev-e-1 | O14: =INDEX(CausalMechanisms!L2:L999, MATCH(C14,CausalMechanisms!A2:A999, 0)) -> /intake/new-patient/mensah-esi/mechanisms/cm-e | P14: =O14 & "/evidence/" & A14 -> /intake/new-patient/mensah-esi/mechanisms/cm-e/evidence/ev-e-1 | Q14: =INDEX(OmicsAssays!P2:P999, MATCH(D14,OmicsAssays!A2:A999, 0)) -> TRUE | R14: =IF(F14 > 0, E14 / F14, 0) -> 3.7619048 | S14: =IF(AND(I14, J14), TRUE(), FALSE()) -> TRUE | T14: =IF(AND(Q14, NOT(H14), R14 >= 2, S14), TRUE(), FALSE()) -> TRUE | U14: cis-eQTL in blood RNA-seq with effect 0.79 (SE 0.21)
A15: ev-e-2 | B15: ev-e-2 | C15: cm-e | D15: assay-e-atac | E15: 0.71 | F15: 0.205 | G15: TRUE | H15: FALSE | I15: TRUE | J15: TRUE | K15: TRUE | L15: caQTL, blood ATAC-seq | M15: open-chromatin peak maps to the credible set; cell-state confounding adjusted | N15: =B15 -> ev-e-2 | O15: =INDEX(CausalMechanisms!L2:L999, MATCH(C15,CausalMechanisms!A2:A999, 0)) -> /intake/new-patient/mensah-esi/mechanisms/cm-e | P15: =O15 & "/evidence/" & A15 -> /intake/new-patient/mensah-esi/mechanisms/cm-e/evidence/ev-e-2 | Q15: =INDEX(OmicsAssays!P2:P999, MATCH(D15,OmicsAssays!A2:A999, 0)) -> TRUE | R15: =IF(F15 > 0, E15 / F15, 0) -> 3.4634146 | S15: =IF(AND(I15, J15), TRUE(), FALSE()) -> TRUE | T15: =IF(AND(Q15, NOT(H15), R15 >= 2, S15), TRUE(), FALSE()) -> TRUE | U15: caQTL in blood ATAC-seq with effect 0.71 (SE 0.20)
A16: ev-e-3 | B16: ev-e-3 | C16: cm-e | D16: assay-e-prot | E16: 0.41 | F16: 0.2 | G16: TRUE | H16: FALSE | I16: TRUE | J16: TRUE | K16: TRUE | L16: pQTL, blood mass-spec proteomics | M16: cis-pQTL within 1Mb; aptamer/epitope-binding artifact excluded | N16: =B16 -> ev-e-3 | O16: =INDEX(CausalMechanisms!L2:L999, MATCH(C16,CausalMechanisms!A2:A999, 0)) -> /intake/new-patient/mensah-esi/mechanisms/cm-e | P16: =O16 & "/evidence/" & A16 -> /intake/new-patient/mensah-esi/mechanisms/cm-e/evidence/ev-e-3 | Q16: =INDEX(OmicsAssays!P2:P999, MATCH(D16,OmicsAssays!A2:A999, 0)) -> TRUE | R16: =IF(F16 > 0, E16 / F16, 0) -> 2.05 | S16: =IF(AND(I16, J16), TRUE(), FALSE()) -> TRUE | T16: =IF(AND(Q16, NOT(H16), R16 >= 2, S16), TRUE(), FALSE()) -> TRUE | U16: pQTL in blood proteomics with effect 0.41 (SE 0.20)
A17: ev-f-1 | B17: ev-f-1 | C17: cm-f | D17: assay-f-rna | E17: 1.07 | F17: 0.205 | G17: FALSE | H17: FALSE | I17: TRUE | J17: TRUE | K17: TRUE | L17: cis-eQTL, blood RNA-seq | M17: colocalization PP4>0.8; no horizontal pleiotropy on the eQTL instrument | N17: =B17 -> ev-f-1 | O17: =INDEX(CausalMechanisms!L2:L999, MATCH(C17,CausalMechanisms!A2:A999, 0)) -> /intake/new-patient/haidar-faisal/mechanisms/cm-f | P17: =O17 & "/evidence/" & A17 -> /intake/new-patient/haidar-faisal/mechanisms/cm-f/evidence/ev-f-1 | Q17: =INDEX(OmicsAssays!P2:P999, MATCH(D17,OmicsAssays!A2:A999, 0)) -> TRUE | R17: =IF(F17 > 0, E17 / F17, 0) -> 5.2195122 | S17: =IF(AND(I17, J17), TRUE(), FALSE()) -> TRUE | T17: =IF(AND(Q17, NOT(H17), R17 >= 2, S17), TRUE(), FALSE()) -> TRUE | U17: cis-eQTL in blood RNA-seq with effect 1.07 (SE 0.20)
A18: ev-f-2 | B18: ev-f-2 | C18: cm-f | D18: assay-f-atac | E18: 0.83 | F18: 0.21 | G18: TRUE | H18: FALSE | I18: TRUE | J18: TRUE | K18: TRUE | L18: caQTL, blood ATAC-seq | M18: open-chromatin peak maps to the credible set; cell-state confounding adjusted | N18: =B18 -> ev-f-2 | O18: =INDEX(CausalMechanisms!L2:L999, MATCH(C18,CausalMechanisms!A2:A999, 0)) -> /intake/new-patient/haidar-faisal/mechanisms/cm-f | P18: =O18 & "/evidence/" & A18 -> /intake/new-patient/haidar-faisal/mechanisms/cm-f/evidence/ev-f-2 | Q18: =INDEX(OmicsAssays!P2:P999, MATCH(D18,OmicsAssays!A2:A999, 0)) -> TRUE | R18: =IF(F18 > 0, E18 / F18, 0) -> 3.952381 | S18: =IF(AND(I18, J18), TRUE(), FALSE()) -> TRUE | T18: =IF(AND(Q18, NOT(H18), R18 >= 2, S18), TRUE(), FALSE()) -> TRUE | U18: caQTL in blood ATAC-seq with effect 0.83 (SE 0.21)
A19: ev-f-3 | B19: ev-f-3 | C19: cm-f | D19: assay-f-prot | E19: 0.74 | F19: 0.205 | G19: TRUE | H19: FALSE | I19: TRUE | J19: TRUE | K19: TRUE | L19: pQTL, blood mass-spec proteomics | M19: cis-pQTL within 1Mb; aptamer/epitope-binding artifact excluded | N19: =B19 -> ev-f-3 | O19: =INDEX(CausalMechanisms!L2:L999, MATCH(C19,CausalMechanisms!A2:A999, 0)) -> /intake/new-patient/haidar-faisal/mechanisms/cm-f | P19: =O19 & "/evidence/" & A19 -> /intake/new-patient/haidar-faisal/mechanisms/cm-f/evidence/ev-f-3 | Q19: =INDEX(OmicsAssays!P2:P999, MATCH(D19,OmicsAssays!A2:A999, 0)) -> TRUE | R19: =IF(F19 > 0, E19 / F19, 0) -> 3.6097561 | S19: =IF(AND(I19, J19), TRUE(), FALSE()) -> TRUE | T19: =IF(AND(Q19, NOT(H19), R19 >= 2, S19), TRUE(), FALSE()) -> TRUE | U19: pQTL in blood proteomics with effect 0.74 (SE 0.20)
A20: ev-g-1 | B20: ev-g-1 | C20: cm-g | D20: assay-g-rna | E20: 0.96 | F20: 0.2 | G20: FALSE | H20: FALSE | I20: TRUE | J20: TRUE | K20: TRUE | L20: cis-eQTL, blood RNA-seq | M20: colocalization PP4>0.8; no horizontal pleiotropy on the eQTL instrument | N20: =B20 -> ev-g-1 | O20: =INDEX(CausalMechanisms!L2:L999, MATCH(C20,CausalMechanisms!A2:A999, 0)) -> /intake/new-patient/lin-grace/mechanisms/cm-g | P20: =O20 & "/evidence/" & A20 -> /intake/new-patient/lin-grace/mechanisms/cm-g/evidence/ev-g-1 | Q20: =INDEX(OmicsAssays!P2:P999, MATCH(D20,OmicsAssays!A2:A999, 0)) -> TRUE | R20: =IF(F20 > 0, E20 / F20, 0) -> 4.8 | S20: =IF(AND(I20, J20), TRUE(), FALSE()) -> TRUE | T20: =IF(AND(Q20, NOT(H20), R20 >= 2, S20), TRUE(), FALSE()) -> TRUE | U20: cis-eQTL in blood RNA-seq with effect 0.96 (SE 0.20)
A21: ev-g-2 | B21: ev-g-2 | C21: cm-g | D21: assay-g-atac | E21: 0.88 | F21: 0.21 | G21: TRUE | H21: FALSE | I21: TRUE | J21: TRUE | K21: TRUE | L21: caQTL, blood ATAC-seq | M21: open-chromatin peak maps to the credible set; cell-state confounding adjusted | N21: =B21 -> ev-g-2 | O21: =INDEX(CausalMechanisms!L2:L999, MATCH(C21,CausalMechanisms!A2:A999, 0)) -> /intake/new-patient/lin-grace/mechanisms/cm-g | P21: =O21 & "/evidence/" & A21 -> /intake/new-patient/lin-grace/mechanisms/cm-g/evidence/ev-g-2 | Q21: =INDEX(OmicsAssays!P2:P999, MATCH(D21,OmicsAssays!A2:A999, 0)) -> TRUE | R21: =IF(F21 > 0, E21 / F21, 0) -> 4.1904762 | S21: =IF(AND(I21, J21), TRUE(), FALSE()) -> TRUE | T21: =IF(AND(Q21, NOT(H21), R21 >= 2, S21), TRUE(), FALSE()) -> TRUE | U21: caQTL in blood ATAC-seq with effect 0.88 (SE 0.21)
A22: ev-g-3 | B22: ev-g-3 | C22: cm-g | D22: assay-g-prot | E22: 0.69 | F22: 0.205 | G22: TRUE | H22: FALSE | I22: TRUE | J22: TRUE | K22: TRUE | L22: pQTL, blood mass-spec proteomics | M22: cis-pQTL within 1Mb; aptamer/epitope-binding artifact excluded | N22: =B22 -> ev-g-3 | O22: =INDEX(CausalMechanisms!L2:L999, MATCH(C22,CausalMechanisms!A2:A999, 0)) -> /intake/new-patient/lin-grace/mechanisms/cm-g | P22: =O22 & "/evidence/" & A22 -> /intake/new-patient/lin-grace/mechanisms/cm-g/evidence/ev-g-3 | Q22: =INDEX(OmicsAssays!P2:P999, MATCH(D22,OmicsAssays!A2:A999, 0)) -> TRUE | R22: =IF(F22 > 0, E22 / F22, 0) -> 3.3658537 | S22: =IF(AND(I22, J22), TRUE(), FALSE()) -> TRUE | T22: =IF(AND(Q22, NOT(H22), R22 >= 2, S22), TRUE(), FALSE()) -> TRUE | U22: pQTL in blood proteomics with effect 0.69 (SE 0.20)
A23: ev-h-1 | B23: ev-h-1 | C23: cm-h | D23: assay-h-rna | E23: 0.91 | F23: 0.2 | G23: FALSE | H23: FALSE | I23: TRUE | J23: TRUE | K23: TRUE | L23: cis-eQTL, blood RNA-seq | M23: colocalization PP4>0.8; no horizontal pleiotropy on the eQTL instrument | N23: =B23 -> ev-h-1 | O23: =INDEX(CausalMechanisms!L2:L999, MATCH(C23,CausalMechanisms!A2:A999, 0)) -> /intake/new-patient/yamamoto-hana/mechanisms/cm-h | P23: =O23 & "/evidence/" & A23 -> /intake/new-patient/yamamoto-hana/mechanisms/cm-h/evidence/ev-h-1 | Q23: =INDEX(OmicsAssays!P2:P999, MATCH(D23,OmicsAssays!A2:A999, 0)) -> TRUE | R23: =IF(F23 > 0, E23 / F23, 0) -> 4.55 | S23: =IF(AND(I23, J23), TRUE(), FALSE()) -> TRUE | T23: =IF(AND(Q23, NOT(H23), R23 >= 2, S23), TRUE(), FALSE()) -> TRUE | U23: cis-eQTL in blood RNA-seq with effect 0.91 (SE 0.20)
A24: ev-h-2 | B24: ev-h-2 | C24: cm-h | D24: assay-h-atac | E24: 0.73 | F24: 0.19 | G24: TRUE | H24: FALSE | I24: TRUE | J24: TRUE | K24: TRUE | L24: caQTL, blood ATAC-seq | M24: open-chromatin peak maps to the credible set; cell-state confounding adjusted | N24: =B24 -> ev-h-2 | O24: =INDEX(CausalMechanisms!L2:L999, MATCH(C24,CausalMechanisms!A2:A999, 0)) -> /intake/new-patient/yamamoto-hana/mechanisms/cm-h | P24: =O24 & "/evidence/" & A24 -> /intake/new-patient/yamamoto-hana/mechanisms/cm-h/evidence/ev-h-2 | Q24: =INDEX(OmicsAssays!P2:P999, MATCH(D24,OmicsAssays!A2:A999, 0)) -> TRUE | R24: =IF(F24 > 0, E24 / F24, 0) -> 3.8421053 | S24: =IF(AND(I24, J24), TRUE(), FALSE()) -> TRUE | T24: =IF(AND(Q24, NOT(H24), R24 >= 2, S24), TRUE(), FALSE()) -> TRUE | U24: caQTL in blood ATAC-seq with effect 0.73 (SE 0.19)
A25: ev-h-3 | B25: ev-h-3 | C25: cm-h | D25: assay-h-prot | E25: 0.66 | F25: 0.205 | G25: TRUE | H25: FALSE | I25: TRUE | J25: TRUE | K25: TRUE | L25: pQTL, blood mass-spec proteomics | M25: cis-pQTL within 1Mb; aptamer/epitope-binding artifact excluded | N25: =B25 -> ev-h-3 | O25: =INDEX(CausalMechanisms!L2:L999, MATCH(C25,CausalMechanisms!A2:A999, 0)) -> /intake/new-patient/yamamoto-hana/mechanisms/cm-h | P25: =O25 & "/evidence/" & A25 -> /intake/new-patient/yamamoto-hana/mechanisms/cm-h/evidence/ev-h-3 | Q25: =INDEX(OmicsAssays!P2:P999, MATCH(D25,OmicsAssays!A2:A999, 0)) -> TRUE | R25: =IF(F25 > 0, E25 / F25, 0) -> 3.2195122 | S25: =IF(AND(I25, J25), TRUE(), FALSE()) -> TRUE | T25: =IF(AND(Q25, NOT(H25), R25 >= 2, S25), TRUE(), FALSE()) -> TRUE | U25: pQTL in blood proteomics with effect 0.66 (SE 0.20)
A26: ev-i-1 | B26: ev-i-1 | C26: cm-i | D26: assay-i-rna | E26: 0.88 | F26: 0.205 | G26: FALSE | H26: FALSE | I26: TRUE | J26: TRUE | K26: TRUE | L26: cis-eQTL, blood RNA-seq | M26: colocalization PP4>0.8; no horizontal pleiotropy on the eQTL instrument | N26: =B26 -> ev-i-1 | O26: =INDEX(CausalMechanisms!L2:L999, MATCH(C26,CausalMechanisms!A2:A999, 0)) -> /intake/new-patient/conteh-ibrahim/mechanisms/cm-i | P26: =O26 & "/evidence/" & A26 -> /intake/new-patient/conteh-ibrahim/mechanisms/cm-i/evidence/ev-i-1 | Q26: =INDEX(OmicsAssays!P2:P999, MATCH(D26,OmicsAssays!A2:A999, 0)) -> TRUE | R26: =IF(F26 > 0, E26 / F26, 0) -> 4.2926829 | S26: =IF(AND(I26, J26), TRUE(), FALSE()) -> TRUE | T26: =IF(AND(Q26, NOT(H26), R26 >= 2, S26), TRUE(), FALSE()) -> TRUE | U26: cis-eQTL in blood RNA-seq with effect 0.88 (SE 0.20)
A27: ev-i-2 | B27: ev-i-2 | C27: cm-i | D27: assay-i-atac | E27: 0.95 | F27: 0.21 | G27: TRUE | H27: FALSE | I27: TRUE | J27: TRUE | K27: TRUE | L27: caQTL, blood ATAC-seq | M27: open-chromatin peak maps to the credible set; cell-state confounding adjusted | N27: =B27 -> ev-i-2 | O27: =INDEX(CausalMechanisms!L2:L999, MATCH(C27,CausalMechanisms!A2:A999, 0)) -> /intake/new-patient/conteh-ibrahim/mechanisms/cm-i | P27: =O27 & "/evidence/" & A27 -> /intake/new-patient/conteh-ibrahim/mechanisms/cm-i/evidence/ev-i-2 | Q27: =INDEX(OmicsAssays!P2:P999, MATCH(D27,OmicsAssays!A2:A999, 0)) -> TRUE | R27: =IF(F27 > 0, E27 / F27, 0) -> 4.5238095 | S27: =IF(AND(I27, J27), TRUE(), FALSE()) -> TRUE | T27: =IF(AND(Q27, NOT(H27), R27 >= 2, S27), TRUE(), FALSE()) -> TRUE | U27: caQTL in blood ATAC-seq with effect 0.95 (SE 0.21)
A28: ev-i-3 | B28: ev-i-3 | C28: cm-i | D28: assay-i-prot | E28: 0.62 | F28: 0.205 | G28: TRUE | H28: FALSE | I28: TRUE | J28: TRUE | K28: TRUE | L28: pQTL, blood mass-spec proteomics | M28: cis-pQTL within 1Mb; aptamer/epitope-binding artifact excluded | N28: =B28 -> ev-i-3 | O28: =INDEX(CausalMechanisms!L2:L999, MATCH(C28,CausalMechanisms!A2:A999, 0)) -> /intake/new-patient/conteh-ibrahim/mechanisms/cm-i | P28: =O28 & "/evidence/" & A28 -> /intake/new-patient/conteh-ibrahim/mechanisms/cm-i/evidence/ev-i-3 | Q28: =INDEX(OmicsAssays!P2:P999, MATCH(D28,OmicsAssays!A2:A999, 0)) -> TRUE | R28: =IF(F28 > 0, E28 / F28, 0) -> 3.0243902 | S28: =IF(AND(I28, J28), TRUE(), FALSE()) -> TRUE | T28: =IF(AND(Q28, NOT(H28), R28 >= 2, S28), TRUE(), FALSE()) -> TRUE | U28: pQTL in blood proteomics with effect 0.62 (SE 0.20)
A29: ev-j-1 | B29: ev-j-1 | C29: cm-j | D29: assay-j-rna | E29: 0.84 | F29: 0.21 | G29: FALSE | H29: FALSE | I29: TRUE | J29: TRUE | K29: TRUE | L29: cis-eQTL, blood RNA-seq | M29: colocalization PP4>0.8; no horizontal pleiotropy on the eQTL instrument | N29: =B29 -> ev-j-1 | O29: =INDEX(CausalMechanisms!L2:L999, MATCH(C29,CausalMechanisms!A2:A999, 0)) -> /intake/new-patient/brooks-jamal/mechanisms/cm-j | P29: =O29 & "/evidence/" & A29 -> /intake/new-patient/brooks-jamal/mechanisms/cm-j/evidence/ev-j-1 | Q29: =INDEX(OmicsAssays!P2:P999, MATCH(D29,OmicsAssays!A2:A999, 0)) -> TRUE | R29: =IF(F29 > 0, E29 / F29, 0) -> 4 | S29: =IF(AND(I29, J29), TRUE(), FALSE()) -> TRUE | T29: =IF(AND(Q29, NOT(H29), R29 >= 2, S29), TRUE(), FALSE()) -> TRUE | U29: cis-eQTL in blood RNA-seq with effect 0.84 (SE 0.21)
A30: ev-j-2 | B30: ev-j-2 | C30: cm-j | D30: assay-j-atac | E30: 0.79 | F30: 0.205 | G30: TRUE | H30: FALSE | I30: TRUE | J30: TRUE | K30: TRUE | L30: caQTL, blood ATAC-seq | M30: open-chromatin peak maps to the credible set; cell-state confounding adjusted | N30: =B30 -> ev-j-2 | O30: =INDEX(CausalMechanisms!L2:L999, MATCH(C30,CausalMechanisms!A2:A999, 0)) -> /intake/new-patient/brooks-jamal/mechanisms/cm-j | P30: =O30 & "/evidence/" & A30 -> /intake/new-patient/brooks-jamal/mechanisms/cm-j/evidence/ev-j-2 | Q30: =INDEX(OmicsAssays!P2:P999, MATCH(D30,OmicsAssays!A2:A999, 0)) -> TRUE | R30: =IF(F30 > 0, E30 / F30, 0) -> 3.8536585 | S30: =IF(AND(I30, J30), TRUE(), FALSE()) -> TRUE | T30: =IF(AND(Q30, NOT(H30), R30 >= 2, S30), TRUE(), FALSE()) -> TRUE | U30: caQTL in blood ATAC-seq with effect 0.79 (SE 0.20)
A31: ev-j-3 | B31: ev-j-3 | C31: cm-j | D31: assay-j-prot | E31: 0.58 | F31: 0.205 | G31: TRUE | H31: FALSE | I31: TRUE | J31: TRUE | K31: TRUE | L31: pQTL, blood mass-spec proteomics | M31: cis-pQTL within 1Mb; aptamer/epitope-binding artifact excluded | N31: =B31 -> ev-j-3 | O31: =INDEX(CausalMechanisms!L2:L999, MATCH(C31,CausalMechanisms!A2:A999, 0)) -> /intake/new-patient/brooks-jamal/mechanisms/cm-j | P31: =O31 & "/evidence/" & A31 -> /intake/new-patient/brooks-jamal/mechanisms/cm-j/evidence/ev-j-3 | Q31: =INDEX(OmicsAssays!P2:P999, MATCH(D31,OmicsAssays!A2:A999, 0)) -> TRUE | R31: =IF(F31 > 0, E31 / F31, 0) -> 2.8292683 | S31: =IF(AND(I31, J31), TRUE(), FALSE()) -> TRUE | T31: =IF(AND(Q31, NOT(H31), R31 >= 2, S31), TRUE(), FALSE()) -> TRUE | U31: pQTL in blood proteomics with effect 0.58 (SE 0.20)
A32: ev-k-1 | B32: ev-k-1 | C32: cm-k | D32: assay-k-rna | E32: 1.07 | F32: 0.205 | G32: FALSE | H32: FALSE | I32: TRUE | J32: TRUE | K32: TRUE | L32: cis-eQTL, blood RNA-seq | M32: colocalization PP4>0.8; no horizontal pleiotropy on the eQTL instrument | N32: =B32 -> ev-k-1 | O32: =INDEX(CausalMechanisms!L2:L999, MATCH(C32,CausalMechanisms!A2:A999, 0)) -> /intake/new-patient/nair-kavya/mechanisms/cm-k | P32: =O32 & "/evidence/" & A32 -> /intake/new-patient/nair-kavya/mechanisms/cm-k/evidence/ev-k-1 | Q32: =INDEX(OmicsAssays!P2:P999, MATCH(D32,OmicsAssays!A2:A999, 0)) -> TRUE | R32: =IF(F32 > 0, E32 / F32, 0) -> 5.2195122 | S32: =IF(AND(I32, J32), TRUE(), FALSE()) -> TRUE | T32: =IF(AND(Q32, NOT(H32), R32 >= 2, S32), TRUE(), FALSE()) -> TRUE | U32: cis-eQTL in blood RNA-seq with effect 1.07 (SE 0.20)
A33: ev-k-2 | B33: ev-k-2 | C33: cm-k | D33: assay-k-atac | E33: 0.83 | F33: 0.21 | G33: TRUE | H33: FALSE | I33: TRUE | J33: TRUE | K33: TRUE | L33: caQTL, blood ATAC-seq | M33: open-chromatin peak maps to the credible set; cell-state confounding adjusted | N33: =B33 -> ev-k-2 | O33: =INDEX(CausalMechanisms!L2:L999, MATCH(C33,CausalMechanisms!A2:A999, 0)) -> /intake/new-patient/nair-kavya/mechanisms/cm-k | P33: =O33 & "/evidence/" & A33 -> /intake/new-patient/nair-kavya/mechanisms/cm-k/evidence/ev-k-2 | Q33: =INDEX(OmicsAssays!P2:P999, MATCH(D33,OmicsAssays!A2:A999, 0)) -> TRUE | R33: =IF(F33 > 0, E33 / F33, 0) -> 3.952381 | S33: =IF(AND(I33, J33), TRUE(), FALSE()) -> TRUE | T33: =IF(AND(Q33, NOT(H33), R33 >= 2, S33), TRUE(), FALSE()) -> TRUE | U33: caQTL in blood ATAC-seq with effect 0.83 (SE 0.21)
A34: ev-k-3 | B34: ev-k-3 | C34: cm-k | D34: assay-k-prot | E34: 0.74 | F34: 0.205 | G34: TRUE | H34: FALSE | I34: TRUE | J34: TRUE | K34: TRUE | L34: pQTL, blood mass-spec proteomics | M34: cis-pQTL within 1Mb; aptamer/epitope-binding artifact excluded | N34: =B34 -> ev-k-3 | O34: =INDEX(CausalMechanisms!L2:L999, MATCH(C34,CausalMechanisms!A2:A999, 0)) -> /intake/new-patient/nair-kavya/mechanisms/cm-k | P34: =O34 & "/evidence/" & A34 -> /intake/new-patient/nair-kavya/mechanisms/cm-k/evidence/ev-k-3 | Q34: =INDEX(OmicsAssays!P2:P999, MATCH(D34,OmicsAssays!A2:A999, 0)) -> TRUE | R34: =IF(F34 > 0, E34 / F34, 0) -> 3.6097561 | S34: =IF(AND(I34, J34), TRUE(), FALSE()) -> TRUE | T34: =IF(AND(Q34, NOT(H34), R34 >= 2, S34), TRUE(), FALSE()) -> TRUE | U34: pQTL in blood proteomics with effect 0.74 (SE 0.20)
A35: ev-l-1 | B35: ev-l-1 | C35: cm-l | D35: assay-l-rna | E35: 0.96 | F35: 0.2 | G35: FALSE | H35: FALSE | I35: TRUE | J35: TRUE | K35: TRUE | L35: cis-eQTL, blood RNA-seq | M35: colocalization PP4>0.8; no horizontal pleiotropy on the eQTL instrument | N35: =B35 -> ev-l-1 | O35: =INDEX(CausalMechanisms!L2:L999, MATCH(C35,CausalMechanisms!A2:A999, 0)) -> /intake/new-patient/brandt-lena/mechanisms/cm-l | P35: =O35 & "/evidence/" & A35 -> /intake/new-patient/brandt-lena/mechanisms/cm-l/evidence/ev-l-1 | Q35: =INDEX(OmicsAssays!P2:P999, MATCH(D35,OmicsAssays!A2:A999, 0)) -> TRUE | R35: =IF(F35 > 0, E35 / F35, 0) -> 4.8 | S35: =IF(AND(I35, J35), TRUE(), FALSE()) -> TRUE | T35: =IF(AND(Q35, NOT(H35), R35 >= 2, S35), TRUE(), FALSE()) -> TRUE | U35: cis-eQTL in blood RNA-seq with effect 0.96 (SE 0.20)
A36: ev-l-2 | B36: ev-l-2 | C36: cm-l | D36: assay-l-atac | E36: 0.88 | F36: 0.21 | G36: TRUE | H36: FALSE | I36: TRUE | J36: TRUE | K36: TRUE | L36: caQTL, blood ATAC-seq | M36: open-chromatin peak maps to the credible set; cell-state confounding adjusted | N36: =B36 -> ev-l-2 | O36: =INDEX(CausalMechanisms!L2:L999, MATCH(C36,CausalMechanisms!A2:A999, 0)) -> /intake/new-patient/brandt-lena/mechanisms/cm-l | P36: =O36 & "/evidence/" & A36 -> /intake/new-patient/brandt-lena/mechanisms/cm-l/evidence/ev-l-2 | Q36: =INDEX(OmicsAssays!P2:P999, MATCH(D36,OmicsAssays!A2:A999, 0)) -> TRUE | R36: =IF(F36 > 0, E36 / F36, 0) -> 4.1904762 | S36: =IF(AND(I36, J36), TRUE(), FALSE()) -> TRUE | T36: =IF(AND(Q36, NOT(H36), R36 >= 2, S36), TRUE(), FALSE()) -> TRUE | U36: caQTL in blood ATAC-seq with effect 0.88 (SE 0.21)
A37: ev-l-3 | B37: ev-l-3 | C37: cm-l | D37: assay-l-prot | E37: 0.69 | F37: 0.205 | G37: TRUE | H37: FALSE | I37: TRUE | J37: TRUE | K37: TRUE | L37: pQTL, blood mass-spec proteomics | M37: cis-pQTL within 1Mb; aptamer/epitope-binding artifact excluded | N37: =B37 -> ev-l-3 | O37: =INDEX(CausalMechanisms!L2:L999, MATCH(C37,CausalMechanisms!A2:A999, 0)) -> /intake/new-patient/brandt-lena/mechanisms/cm-l | P37: =O37 & "/evidence/" & A37 -> /intake/new-patient/brandt-lena/mechanisms/cm-l/evidence/ev-l-3 | Q37: =INDEX(OmicsAssays!P2:P999, MATCH(D37,OmicsAssays!A2:A999, 0)) -> TRUE | R37: =IF(F37 > 0, E37 / F37, 0) -> 3.3658537 | S37: =IF(AND(I37, J37), TRUE(), FALSE()) -> TRUE | T37: =IF(AND(Q37, NOT(H37), R37 >= 2, S37), TRUE(), FALSE()) -> TRUE | U37: pQTL in blood proteomics with effect 0.69 (SE 0.20)

Sheet CohortReplications
A1: CohortReplicationId | B1: ReplicationLabel | C1: CausalMechanism | D1: FederatedDataset | E1: ReplicationEffectSign | F1: ReplicationPValue | G1: ReplicationAncestryLabel | H1: Name | I1: ParentPath | J1: RelativePath | K1: ReplicatedAtNominalSig | L1: MechanismPrimaryAncestry | M1: IsDifferentAncestryReplication | N1: IsCrossAncestryConcordant | O1: SourceQuote
A2: rep-a-1 | B2: rep-a-1 | C2: cm-a | D2: fed-east-asia | E2: 1 | F2: 0.004 | G2: East Asian | H2: =B2 -> rep-a-1 | I2: =INDEX(CausalMechanisms!L2:L999, MATCH(C2,CausalMechanisms!A2:A999, 0)) -> /intake/new-patient/reyes-ana/mechanisms/cm-a | J2: =I2 & "/replications/" & A2 -> /intake/new-patient/reyes-ana/mechanisms/cm-a/replications/rep-a-1 | K2: =IF(AND(F2 <= 0.05, E2 = 1), TRUE(), FALSE()) -> TRUE | L2: =INDEX(CausalMechanisms!M2:M999, MATCH(C2,CausalMechanisms!A2:A999, 0)) -> European | M2: =IF(G2 = L2, FALSE(), TRUE()) -> TRUE | N2: =IF(AND(K2, M2), TRUE(), FALSE()) -> TRUE | O2: positive effect sign in an East Asian cohort (p=0.004)
A3: rep-a-2 | B3: rep-a-2 | C3: cm-a | D3: fed-west-africa | E3: 1 | F3: 0.013 | G3: African | H3: =B3 -> rep-a-2 | I3: =INDEX(CausalMechanisms!L2:L999, MATCH(C3,CausalMechanisms!A2:A999, 0)) -> /intake/new-patient/reyes-ana/mechanisms/cm-a | J3: =I3 & "/replications/" & A3 -> /intake/new-patient/reyes-ana/mechanisms/cm-a/replications/rep-a-2 | K3: =IF(AND(F3 <= 0.05, E3 = 1), TRUE(), FALSE()) -> TRUE | L3: =INDEX(CausalMechanisms!M2:M999, MATCH(C3,CausalMechanisms!A2:A999, 0)) -> European | M3: =IF(G3 = L3, FALSE(), TRUE()) -> TRUE | N3: =IF(AND(K3, M3), TRUE(), FALSE()) -> TRUE | O3: in an African cohort (p=0.013)
A4: rep-a-3 | B4: rep-a-3 | C4: cm-a | D4: fed-europe | E4: 1 | F4: 0.18 | G4: European | H4: =B4 -> rep-a-3 | I4: =INDEX(CausalMechanisms!L2:L999, MATCH(C4,CausalMechanisms!A2:A999, 0)) -> /intake/new-patient/reyes-ana/mechanisms/cm-a | J4: =I4 & "/replications/" & A4 -> /intake/new-patient/reyes-ana/mechanisms/cm-a/replications/rep-a-3 | K4: =IF(AND(F4 <= 0.05, E4 = 1), TRUE(), FALSE()) -> FALSE | L4: =INDEX(CausalMechanisms!M2:M999, MATCH(C4,CausalMechanisms!A2:A999, 0)) -> European | M4: =IF(G4 = L4, FALSE(), TRUE()) -> FALSE | N4: =IF(AND(K4, M4), TRUE(), FALSE()) -> FALSE | O4: European replication is directionally consistent but not significant (p=0.18)
A5: rep-b-1 | B5: rep-b-1 | C5: cm-b | D5: fed-east-asia | E5: 1 | F5: 0.006 | G5: East Asian | H5: =B5 -> rep-b-1 | I5: =INDEX(CausalMechanisms!L2:L999, MATCH(C5,CausalMechanisms!A2:A999, 0)) -> /intake/new-patient/okafor-bili/mechanisms/cm-b | J5: =I5 & "/replications/" & A5 -> /intake/new-patient/okafor-bili/mechanisms/cm-b/replications/rep-b-1 | K5: =IF(AND(F5 <= 0.05, E5 = 1), TRUE(), FALSE()) -> TRUE | L5: =INDEX(CausalMechanisms!M2:M999, MATCH(C5,CausalMechanisms!A2:A999, 0)) -> European | M5: =IF(G5 = L5, FALSE(), TRUE()) -> TRUE | N5: =IF(AND(K5, M5), TRUE(), FALSE()) -> TRUE | O5: replicates positive in an East Asian cohort (p=0.006)
A6: rep-b-2 | B6: rep-b-2 | C6: cm-b | D6: fed-west-africa | E6: 1 | F6: 0.017 | G6: African | H6: =B6 -> rep-b-2 | I6: =INDEX(CausalMechanisms!L2:L999, MATCH(C6,CausalMechanisms!A2:A999, 0)) -> /intake/new-patient/okafor-bili/mechanisms/cm-b | J6: =I6 & "/replications/" & A6 -> /intake/new-patient/okafor-bili/mechanisms/cm-b/replications/rep-b-2 | K6: =IF(AND(F6 <= 0.05, E6 = 1), TRUE(), FALSE()) -> TRUE | L6: =INDEX(CausalMechanisms!M2:M999, MATCH(C6,CausalMechanisms!A2:A999, 0)) -> European | M6: =IF(G6 = L6, FALSE(), TRUE()) -> TRUE | N6: =IF(AND(K6, M6), TRUE(), FALSE()) -> TRUE | O6: an African cohort (p=0.017)
A7: rep-b-3 | B7: rep-b-3 | C7: cm-b | D7: fed-europe | E7: 1 | F7: 0.22 | G7: European | H7: =B7 -> rep-b-3 | I7: =INDEX(CausalMechanisms!L2:L999, MATCH(C7,CausalMechanisms!A2:A999, 0)) -> /intake/new-patient/okafor-bili/mechanisms/cm-b | J7: =I7 & "/replications/" & A7 -> /intake/new-patient/okafor-bili/mechanisms/cm-b/replications/rep-b-3 | K7: =IF(AND(F7 <= 0.05, E7 = 1), TRUE(), FALSE()) -> FALSE | L7: =INDEX(CausalMechanisms!M2:M999, MATCH(C7,CausalMechanisms!A2:A999, 0)) -> European | M7: =IF(G7 = L7, FALSE(), TRUE()) -> FALSE | N7: =IF(AND(K7, M7), TRUE(), FALSE()) -> FALSE | O7: non-significant European replication (p=0.22)
A8: rep-c-1 | B8: rep-c-1 | C8: cm-c | D8: fed-east-asia | E8: 1 | F8: 0.009 | G8: East Asian | H8: =B8 -> rep-c-1 | I8: =INDEX(CausalMechanisms!L2:L999, MATCH(C8,CausalMechanisms!A2:A999, 0)) -> /intake/new-patient/wei-chen/mechanisms/cm-c | J8: =I8 & "/replications/" & A8 -> /intake/new-patient/wei-chen/mechanisms/cm-c/replications/rep-c-1 | K8: =IF(AND(F8 <= 0.05, E8 = 1), TRUE(), FALSE()) -> TRUE | L8: =INDEX(CausalMechanisms!M2:M999, MATCH(C8,CausalMechanisms!A2:A999, 0)) -> East Asian | M8: =IF(G8 = L8, FALSE(), TRUE()) -> FALSE | N8: =IF(AND(K8, M8), TRUE(), FALSE()) -> FALSE | O8: positive in an East Asian cohort (p=0.009)
A9: rep-c-2 | B9: rep-c-2 | C9: cm-c | D9: fed-west-africa | E9: -1 | F9: 0.024 | G9: African | H9: =B9 -> rep-c-2 | I9: =INDEX(CausalMechanisms!L2:L999, MATCH(C9,CausalMechanisms!A2:A999, 0)) -> /intake/new-patient/wei-chen/mechanisms/cm-c | J9: =I9 & "/replications/" & A9 -> /intake/new-patient/wei-chen/mechanisms/cm-c/replications/rep-c-2 | K9: =IF(AND(F9 <= 0.05, E9 = 1), TRUE(), FALSE()) -> FALSE | L9: =INDEX(CausalMechanisms!M2:M999, MATCH(C9,CausalMechanisms!A2:A999, 0)) -> East Asian | M9: =IF(G9 = L9, FALSE(), TRUE()) -> TRUE | N9: =IF(AND(K9, M9), TRUE(), FALSE()) -> FALSE | O9: SIGN FLIPS to negative in an African cohort (p=0.024)
A10: rep-c-3 | B10: rep-c-3 | C10: cm-c | D10: fed-europe | E10: 1 | F10: 0.27 | G10: European | H10: =B10 -> rep-c-3 | I10: =INDEX(CausalMechanisms!L2:L999, MATCH(C10,CausalMechanisms!A2:A999, 0)) -> /intake/new-patient/wei-chen/mechanisms/cm-c | J10: =I10 & "/replications/" & A10 -> /intake/new-patient/wei-chen/mechanisms/cm-c/replications/rep-c-3 | K10: =IF(AND(F10 <= 0.05, E10 = 1), TRUE(), FALSE()) -> FALSE | L10: =INDEX(CausalMechanisms!M2:M999, MATCH(C10,CausalMechanisms!A2:A999, 0)) -> East Asian | M10: =IF(G10 = L10, FALSE(), TRUE()) -> TRUE | N10: =IF(AND(K10, M10), TRUE(), FALSE()) -> FALSE | O10: European replication is non-significant (p=0.27)
A11: rep-d-1 | B11: rep-d-1 | C11: cm-d | D11: fed-east-asia | E11: 1 | F11: 0.003 | G11: East Asian | H11: =B11 -> rep-d-1 | I11: =INDEX(CausalMechanisms!L2:L999, MATCH(C11,CausalMechanisms!A2:A999, 0)) -> /intake/new-patient/santos-diego/mechanisms/cm-d | J11: =I11 & "/replications/" & A11 -> /intake/new-patient/santos-diego/mechanisms/cm-d/replications/rep-d-1 | K11: =IF(AND(F11 <= 0.05, E11 = 1), TRUE(), FALSE()) -> TRUE | L11: =INDEX(CausalMechanisms!M2:M999, MATCH(C11,CausalMechanisms!A2:A999, 0)) -> European | M11: =IF(G11 = L11, FALSE(), TRUE()) -> TRUE | N11: =IF(AND(K11, M11), TRUE(), FALSE()) -> TRUE | O11: replicates positive in an East Asian cohort (p=0.003)
A12: rep-d-2 | B12: rep-d-2 | C12: cm-d | D12: fed-west-africa | E12: 1 | F12: 0.019 | G12: African | H12: =B12 -> rep-d-2 | I12: =INDEX(CausalMechanisms!L2:L999, MATCH(C12,CausalMechanisms!A2:A999, 0)) -> /intake/new-patient/santos-diego/mechanisms/cm-d | J12: =I12 & "/replications/" & A12 -> /intake/new-patient/santos-diego/mechanisms/cm-d/replications/rep-d-2 | K12: =IF(AND(F12 <= 0.05, E12 = 1), TRUE(), FALSE()) -> TRUE | L12: =INDEX(CausalMechanisms!M2:M999, MATCH(C12,CausalMechanisms!A2:A999, 0)) -> European | M12: =IF(G12 = L12, FALSE(), TRUE()) -> TRUE | N12: =IF(AND(K12, M12), TRUE(), FALSE()) -> TRUE | O12: an African cohort (p=0.019)
A13: rep-d-3 | B13: rep-d-3 | C13: cm-d | D13: fed-europe | E13: 1 | F13: 0.16 | G13: European | H13: =B13 -> rep-d-3 | I13: =INDEX(CausalMechanisms!L2:L999, MATCH(C13,CausalMechanisms!A2:A999, 0)) -> /intake/new-patient/santos-diego/mechanisms/cm-d | J13: =I13 & "/replications/" & A13 -> /intake/new-patient/santos-diego/mechanisms/cm-d/replications/rep-d-3 | K13: =IF(AND(F13 <= 0.05, E13 = 1), TRUE(), FALSE()) -> FALSE | L13: =INDEX(CausalMechanisms!M2:M999, MATCH(C13,CausalMechanisms!A2:A999, 0)) -> European | M13: =IF(G13 = L13, FALSE(), TRUE()) -> FALSE | N13: =IF(AND(K13, M13), TRUE(), FALSE()) -> FALSE | O13: non-significant European replication (p=0.16)
A14: rep-e-1 | B14: rep-e-1 | C14: cm-e | D14: fed-east-asia | E14: 1 | F14: 0.007 | G14: East Asian | H14: =B14 -> rep-e-1 | I14: =INDEX(CausalMechanisms!L2:L999, MATCH(C14,CausalMechanisms!A2:A999, 0)) -> /intake/new-patient/mensah-esi/mechanisms/cm-e | J14: =I14 & "/replications/" & A14 -> /intake/new-patient/mensah-esi/mechanisms/cm-e/replications/rep-e-1 | K14: =IF(AND(F14 <= 0.05, E14 = 1), TRUE(), FALSE()) -> TRUE | L14: =INDEX(CausalMechanisms!M2:M999, MATCH(C14,CausalMechanisms!A2:A999, 0)) -> African | M14: =IF(G14 = L14, FALSE(), TRUE()) -> TRUE | N14: =IF(AND(K14, M14), TRUE(), FALSE()) -> TRUE | O14: replicates positive in an East Asian cohort (p=0.007)
A15: rep-e-2 | B15: rep-e-2 | C15: cm-e | D15: fed-europe | E15: 1 | F15: 0.021 | G15: European | H15: =B15 -> rep-e-2 | I15: =INDEX(CausalMechanisms!L2:L999, MATCH(C15,CausalMechanisms!A2:A999, 0)) -> /intake/new-patient/mensah-esi/mechanisms/cm-e | J15: =I15 & "/replications/" & A15 -> /intake/new-patient/mensah-esi/mechanisms/cm-e/replications/rep-e-2 | K15: =IF(AND(F15 <= 0.05, E15 = 1), TRUE(), FALSE()) -> TRUE | L15: =INDEX(CausalMechanisms!M2:M999, MATCH(C15,CausalMechanisms!A2:A999, 0)) -> African | M15: =IF(G15 = L15, FALSE(), TRUE()) -> TRUE | N15: =IF(AND(K15, M15), TRUE(), FALSE()) -> TRUE | O15: a European cohort (p=0.021)
A16: rep-e-3 | B16: rep-e-3 | C16: cm-e | D16: fed-west-africa | E16: 1 | F16: 0.19 | G16: African | H16: =B16 -> rep-e-3 | I16: =INDEX(CausalMechanisms!L2:L999, MATCH(C16,CausalMechanisms!A2:A999, 0)) -> /intake/new-patient/mensah-esi/mechanisms/cm-e | J16: =I16 & "/replications/" & A16 -> /intake/new-patient/mensah-esi/mechanisms/cm-e/replications/rep-e-3 | K16: =IF(AND(F16 <= 0.05, E16 = 1), TRUE(), FALSE()) -> FALSE | L16: =INDEX(CausalMechanisms!M2:M999, MATCH(C16,CausalMechanisms!A2:A999, 0)) -> African | M16: =IF(G16 = L16, FALSE(), TRUE()) -> FALSE | N16: =IF(AND(K16, M16), TRUE(), FALSE()) -> FALSE | O16: non-significant African replication (p=0.19)
A17: rep-f-1 | B17: rep-f-1 | C17: cm-f | D17: fed-amazon | E17: 1 | F17: 0.005 | G17: Indigenous American | H17: =B17 -> rep-f-1 | I17: =INDEX(CausalMechanisms!L2:L999, MATCH(C17,CausalMechanisms!A2:A999, 0)) -> /intake/new-patient/haidar-faisal/mechanisms/cm-f | J17: =I17 & "/replications/" & A17 -> /intake/new-patient/haidar-faisal/mechanisms/cm-f/replications/rep-f-1 | K17: =IF(AND(F17 <= 0.05, E17 = 1), TRUE(), FALSE()) -> TRUE | L17: =INDEX(CausalMechanisms!M2:M999, MATCH(C17,CausalMechanisms!A2:A999, 0)) -> Indigenous American | M17: =IF(G17 = L17, FALSE(), TRUE()) -> FALSE | N17: =IF(AND(K17, M17), TRUE(), FALSE()) -> FALSE | O17: run in an Indigenous American cohort: p=0.005
A18: rep-f-2 | B18: rep-f-2 | C18: cm-f | D18: fed-amazon | E18: 1 | F18: 0.015 | G18: Indigenous American | H18: =B18 -> rep-f-2 | I18: =INDEX(CausalMechanisms!L2:L999, MATCH(C18,CausalMechanisms!A2:A999, 0)) -> /intake/new-patient/haidar-faisal/mechanisms/cm-f | J18: =I18 & "/replications/" & A18 -> /intake/new-patient/haidar-faisal/mechanisms/cm-f/replications/rep-f-2 | K18: =IF(AND(F18 <= 0.05, E18 = 1), TRUE(), FALSE()) -> TRUE | L18: =INDEX(CausalMechanisms!M2:M999, MATCH(C18,CausalMechanisms!A2:A999, 0)) -> Indigenous American | M18: =IF(G18 = L18, FALSE(), TRUE()) -> FALSE | N18: =IF(AND(K18, M18), TRUE(), FALSE()) -> FALSE | O18: p=0.015
A19: rep-f-3 | B19: rep-f-3 | C19: cm-f | D19: fed-amazon | E19: 1 | F19: 0.034 | G19: Indigenous American | H19: =B19 -> rep-f-3 | I19: =INDEX(CausalMechanisms!L2:L999, MATCH(C19,CausalMechanisms!A2:A999, 0)) -> /intake/new-patient/haidar-faisal/mechanisms/cm-f | J19: =I19 & "/replications/" & A19 -> /intake/new-patient/haidar-faisal/mechanisms/cm-f/replications/rep-f-3 | K19: =IF(AND(F19 <= 0.05, E19 = 1), TRUE(), FALSE()) -> TRUE | L19: =INDEX(CausalMechanisms!M2:M999, MATCH(C19,CausalMechanisms!A2:A999, 0)) -> Indigenous American | M19: =IF(G19 = L19, FALSE(), TRUE()) -> FALSE | N19: =IF(AND(K19, M19), TRUE(), FALSE()) -> FALSE | O19: p=0.034, all positive, all in the SAME ancestry
A20: rep-g-1 | B20: rep-g-1 | C20: cm-g | D20: fed-europe | E20: 1 | F20: 0.004 | G20: European | H20: =B20 -> rep-g-1 | I20: =INDEX(CausalMechanisms!L2:L999, MATCH(C20,CausalMechanisms!A2:A999, 0)) -> /intake/new-patient/lin-grace/mechanisms/cm-g | J20: =I20 & "/replications/" & A20 -> /intake/new-patient/lin-grace/mechanisms/cm-g/replications/rep-g-1 | K20: =IF(AND(F20 <= 0.05, E20 = 1), TRUE(), FALSE()) -> TRUE | L20: =INDEX(CausalMechanisms!M2:M999, MATCH(C20,CausalMechanisms!A2:A999, 0)) -> Indigenous American | M20: =IF(G20 = L20, FALSE(), TRUE()) -> TRUE | N20: =IF(AND(K20, M20), TRUE(), FALSE()) -> TRUE | O20: positive in a European cohort (p=0.004)
A21: rep-g-2 | B21: rep-g-2 | C21: cm-g | D21: fed-east-asia | E21: 1 | F21: 0.012 | G21: East Asian | H21: =B21 -> rep-g-2 | I21: =INDEX(CausalMechanisms!L2:L999, MATCH(C21,CausalMechanisms!A2:A999, 0)) -> /intake/new-patient/lin-grace/mechanisms/cm-g | J21: =I21 & "/replications/" & A21 -> /intake/new-patient/lin-grace/mechanisms/cm-g/replications/rep-g-2 | K21: =IF(AND(F21 <= 0.05, E21 = 1), TRUE(), FALSE()) -> TRUE | L21: =INDEX(CausalMechanisms!M2:M999, MATCH(C21,CausalMechanisms!A2:A999, 0)) -> Indigenous American | M21: =IF(G21 = L21, FALSE(), TRUE()) -> TRUE | N21: =IF(AND(K21, M21), TRUE(), FALSE()) -> TRUE | O21: positive in an East Asian cohort (p=0.012)
A22: rep-g-3 | B22: rep-g-3 | C22: cm-g | D22: fed-amazon | E22: 1 | F22: 0.029 | G22: Indigenous American | H22: =B22 -> rep-g-3 | I22: =INDEX(CausalMechanisms!L2:L999, MATCH(C22,CausalMechanisms!A2:A999, 0)) -> /intake/new-patient/lin-grace/mechanisms/cm-g | J22: =I22 & "/replications/" & A22 -> /intake/new-patient/lin-grace/mechanisms/cm-g/replications/rep-g-3 | K22: =IF(AND(F22 <= 0.05, E22 = 1), TRUE(), FALSE()) -> TRUE | L22: =INDEX(CausalMechanisms!M2:M999, MATCH(C22,CausalMechanisms!A2:A999, 0)) -> Indigenous American | M22: =IF(G22 = L22, FALSE(), TRUE()) -> FALSE | N22: =IF(AND(K22, M22), TRUE(), FALSE()) -> FALSE | O22: positive in an Indigenous American cohort (p=0.029)
A23: rep-h-1 | B23: rep-h-1 | C23: cm-h | D23: fed-east-asia | E23: 1 | F23: 0.004 | G23: East Asian | H23: =B23 -> rep-h-1 | I23: =INDEX(CausalMechanisms!L2:L999, MATCH(C23,CausalMechanisms!A2:A999, 0)) -> /intake/new-patient/yamamoto-hana/mechanisms/cm-h | J23: =I23 & "/replications/" & A23 -> /intake/new-patient/yamamoto-hana/mechanisms/cm-h/replications/rep-h-1 | K23: =IF(AND(F23 <= 0.05, E23 = 1), TRUE(), FALSE()) -> TRUE | L23: =INDEX(CausalMechanisms!M2:M999, MATCH(C23,CausalMechanisms!A2:A999, 0)) -> East Asian | M23: =IF(G23 = L23, FALSE(), TRUE()) -> FALSE | N23: =IF(AND(K23, M23), TRUE(), FALSE()) -> FALSE | O23: positive effect sign in an East Asian cohort (p=0.004)
A24: rep-h-2 | B24: rep-h-2 | C24: cm-h | D24: fed-west-africa | E24: 1 | F24: 0.013 | G24: African | H24: =B24 -> rep-h-2 | I24: =INDEX(CausalMechanisms!L2:L999, MATCH(C24,CausalMechanisms!A2:A999, 0)) -> /intake/new-patient/yamamoto-hana/mechanisms/cm-h | J24: =I24 & "/replications/" & A24 -> /intake/new-patient/yamamoto-hana/mechanisms/cm-h/replications/rep-h-2 | K24: =IF(AND(F24 <= 0.05, E24 = 1), TRUE(), FALSE()) -> TRUE | L24: =INDEX(CausalMechanisms!M2:M999, MATCH(C24,CausalMechanisms!A2:A999, 0)) -> East Asian | M24: =IF(G24 = L24, FALSE(), TRUE()) -> TRUE | N24: =IF(AND(K24, M24), TRUE(), FALSE()) -> TRUE | O24: in an African cohort (p=0.013)
A25: rep-h-3 | B25: rep-h-3 | C25: cm-h | D25: fed-europe | E25: 1 | F25: 0.18 | G25: European | H25: =B25 -> rep-h-3 | I25: =INDEX(CausalMechanisms!L2:L999, MATCH(C25,CausalMechanisms!A2:A999, 0)) -> /intake/new-patient/yamamoto-hana/mechanisms/cm-h | J25: =I25 & "/replications/" & A25 -> /intake/new-patient/yamamoto-hana/mechanisms/cm-h/replications/rep-h-3 | K25: =IF(AND(F25 <= 0.05, E25 = 1), TRUE(), FALSE()) -> FALSE | L25: =INDEX(CausalMechanisms!M2:M999, MATCH(C25,CausalMechanisms!A2:A999, 0)) -> East Asian | M25: =IF(G25 = L25, FALSE(), TRUE()) -> TRUE | N25: =IF(AND(K25, M25), TRUE(), FALSE()) -> FALSE | O25: European replication is directionally consistent but not significant (p=0.18)
A26: rep-i-1 | B26: rep-i-1 | C26: cm-i | D26: fed-east-asia | E26: 1 | F26: 0.003 | G26: East Asian | H26: =B26 -> rep-i-1 | I26: =INDEX(CausalMechanisms!L2:L999, MATCH(C26,CausalMechanisms!A2:A999, 0)) -> /intake/new-patient/conteh-ibrahim/mechanisms/cm-i | J26: =I26 & "/replications/" & A26 -> /intake/new-patient/conteh-ibrahim/mechanisms/cm-i/replications/rep-i-1 | K26: =IF(AND(F26 <= 0.05, E26 = 1), TRUE(), FALSE()) -> TRUE | L26: =INDEX(CausalMechanisms!M2:M999, MATCH(C26,CausalMechanisms!A2:A999, 0)) -> African | M26: =IF(G26 = L26, FALSE(), TRUE()) -> TRUE | N26: =IF(AND(K26, M26), TRUE(), FALSE()) -> TRUE | O26: replicates positive in an East Asian cohort (p=0.003)
A27: rep-i-2 | B27: rep-i-2 | C27: cm-i | D27: fed-west-africa | E27: 1 | F27: 0.019 | G27: African | H27: =B27 -> rep-i-2 | I27: =INDEX(CausalMechanisms!L2:L999, MATCH(C27,CausalMechanisms!A2:A999, 0)) -> /intake/new-patient/conteh-ibrahim/mechanisms/cm-i | J27: =I27 & "/replications/" & A27 -> /intake/new-patient/conteh-ibrahim/mechanisms/cm-i/replications/rep-i-2 | K27: =IF(AND(F27 <= 0.05, E27 = 1), TRUE(), FALSE()) -> TRUE | L27: =INDEX(CausalMechanisms!M2:M999, MATCH(C27,CausalMechanisms!A2:A999, 0)) -> African | M27: =IF(G27 = L27, FALSE(), TRUE()) -> FALSE | N27: =IF(AND(K27, M27), TRUE(), FALSE()) -> FALSE | O27: an African cohort (p=0.019)
A28: rep-i-3 | B28: rep-i-3 | C28: cm-i | D28: fed-europe | E28: 1 | F28: 0.16 | G28: European | H28: =B28 -> rep-i-3 | I28: =INDEX(CausalMechanisms!L2:L999, MATCH(C28,CausalMechanisms!A2:A999, 0)) -> /intake/new-patient/conteh-ibrahim/mechanisms/cm-i | J28: =I28 & "/replications/" & A28 -> /intake/new-patient/conteh-ibrahim/mechanisms/cm-i/replications/rep-i-3 | K28: =IF(AND(F28 <= 0.05, E28 = 1), TRUE(), FALSE()) -> FALSE | L28: =INDEX(CausalMechanisms!M2:M999, MATCH(C28,CausalMechanisms!A2:A999, 0)) -> African | M28: =IF(G28 = L28, FALSE(), TRUE()) -> TRUE | N28: =IF(AND(K28, M28), TRUE(), FALSE()) -> FALSE | O28: non-significant European replication (p=0.16)
A29: rep-j-1 | B29: rep-j-1 | C29: cm-j | D29: fed-east-asia | E29: 1 | F29: 0.006 | G29: East Asian | H29: =B29 -> rep-j-1 | I29: =INDEX(CausalMechanisms!L2:L999, MATCH(C29,CausalMechanisms!A2:A999, 0)) -> /intake/new-patient/brooks-jamal/mechanisms/cm-j | J29: =I29 & "/replications/" & A29 -> /intake/new-patient/brooks-jamal/mechanisms/cm-j/replications/rep-j-1 | K29: =IF(AND(F29 <= 0.05, E29 = 1), TRUE(), FALSE()) -> TRUE | L29: =INDEX(CausalMechanisms!M2:M999, MATCH(C29,CausalMechanisms!A2:A999, 0)) -> Hispanic/Latino | M29: =IF(G29 = L29, FALSE(), TRUE()) -> TRUE | N29: =IF(AND(K29, M29), TRUE(), FALSE()) -> TRUE | O29: replicates positive in an East Asian cohort (p=0.006)
A30: rep-j-2 | B30: rep-j-2 | C30: cm-j | D30: fed-west-africa | E30: 1 | F30: 0.017 | G30: African | H30: =B30 -> rep-j-2 | I30: =INDEX(CausalMechanisms!L2:L999, MATCH(C30,CausalMechanisms!A2:A999, 0)) -> /intake/new-patient/brooks-jamal/mechanisms/cm-j | J30: =I30 & "/replications/" & A30 -> /intake/new-patient/brooks-jamal/mechanisms/cm-j/replications/rep-j-2 | K30: =IF(AND(F30 <= 0.05, E30 = 1), TRUE(), FALSE()) -> TRUE | L30: =INDEX(CausalMechanisms!M2:M999, MATCH(C30,CausalMechanisms!A2:A999, 0)) -> Hispanic/Latino | M30: =IF(G30 = L30, FALSE(), TRUE()) -> TRUE | N30: =IF(AND(K30, M30), TRUE(), FALSE()) -> TRUE | O30: an African cohort (p=0.017)
A31: rep-j-3 | B31: rep-j-3 | C31: cm-j | D31: fed-europe | E31: 1 | F31: 0.22 | G31: European | H31: =B31 -> rep-j-3 | I31: =INDEX(CausalMechanisms!L2:L999, MATCH(C31,CausalMechanisms!A2:A999, 0)) -> /intake/new-patient/brooks-jamal/mechanisms/cm-j | J31: =I31 & "/replications/" & A31 -> /intake/new-patient/brooks-jamal/mechanisms/cm-j/replications/rep-j-3 | K31: =IF(AND(F31 <= 0.05, E31 = 1), TRUE(), FALSE()) -> FALSE | L31: =INDEX(CausalMechanisms!M2:M999, MATCH(C31,CausalMechanisms!A2:A999, 0)) -> Hispanic/Latino | M31: =IF(G31 = L31, FALSE(), TRUE()) -> TRUE | N31: =IF(AND(K31, M31), TRUE(), FALSE()) -> FALSE | O31: non-significant European replication (p=0.22)
A32: rep-k-1 | B32: rep-k-1 | C32: cm-k | D32: fed-amazon | E32: 1 | F32: 0.005 | G32: South Asian | H32: =B32 -> rep-k-1 | I32: =INDEX(CausalMechanisms!L2:L999, MATCH(C32,CausalMechanisms!A2:A999, 0)) -> /intake/new-patient/nair-kavya/mechanisms/cm-k | J32: =I32 & "/replications/" & A32 -> /intake/new-patient/nair-kavya/mechanisms/cm-k/replications/rep-k-1 | K32: =IF(AND(F32 <= 0.05, E32 = 1), TRUE(), FALSE()) -> TRUE | L32: =INDEX(CausalMechanisms!M2:M999, MATCH(C32,CausalMechanisms!A2:A999, 0)) -> South Asian | M32: =IF(G32 = L32, FALSE(), TRUE()) -> FALSE | N32: =IF(AND(K32, M32), TRUE(), FALSE()) -> FALSE | O32: run in an Indigenous American cohort: p=0.005
A33: rep-k-2 | B33: rep-k-2 | C33: cm-k | D33: fed-amazon | E33: 1 | F33: 0.015 | G33: South Asian | H33: =B33 -> rep-k-2 | I33: =INDEX(CausalMechanisms!L2:L999, MATCH(C33,CausalMechanisms!A2:A999, 0)) -> /intake/new-patient/nair-kavya/mechanisms/cm-k | J33: =I33 & "/replications/" & A33 -> /intake/new-patient/nair-kavya/mechanisms/cm-k/replications/rep-k-2 | K33: =IF(AND(F33 <= 0.05, E33 = 1), TRUE(), FALSE()) -> TRUE | L33: =INDEX(CausalMechanisms!M2:M999, MATCH(C33,CausalMechanisms!A2:A999, 0)) -> South Asian | M33: =IF(G33 = L33, FALSE(), TRUE()) -> FALSE | N33: =IF(AND(K33, M33), TRUE(), FALSE()) -> FALSE | O33: p=0.015
A34: rep-k-3 | B34: rep-k-3 | C34: cm-k | D34: fed-amazon | E34: 1 | F34: 0.034 | G34: South Asian | H34: =B34 -> rep-k-3 | I34: =INDEX(CausalMechanisms!L2:L999, MATCH(C34,CausalMechanisms!A2:A999, 0)) -> /intake/new-patient/nair-kavya/mechanisms/cm-k | J34: =I34 & "/replications/" & A34 -> /intake/new-patient/nair-kavya/mechanisms/cm-k/replications/rep-k-3 | K34: =IF(AND(F34 <= 0.05, E34 = 1), TRUE(), FALSE()) -> TRUE | L34: =INDEX(CausalMechanisms!M2:M999, MATCH(C34,CausalMechanisms!A2:A999, 0)) -> South Asian | M34: =IF(G34 = L34, FALSE(), TRUE()) -> FALSE | N34: =IF(AND(K34, M34), TRUE(), FALSE()) -> FALSE | O34: p=0.034, all positive, all in the SAME ancestry
A35: rep-l-1 | B35: rep-l-1 | C35: cm-l | D35: fed-europe | E35: 1 | F35: 0.004 | G35: European | H35: =B35 -> rep-l-1 | I35: =INDEX(CausalMechanisms!L2:L999, MATCH(C35,CausalMechanisms!A2:A999, 0)) -> /intake/new-patient/brandt-lena/mechanisms/cm-l | J35: =I35 & "/replications/" & A35 -> /intake/new-patient/brandt-lena/mechanisms/cm-l/replications/rep-l-1 | K35: =IF(AND(F35 <= 0.05, E35 = 1), TRUE(), FALSE()) -> TRUE | L35: =INDEX(CausalMechanisms!M2:M999, MATCH(C35,CausalMechanisms!A2:A999, 0)) -> Indigenous American | M35: =IF(G35 = L35, FALSE(), TRUE()) -> TRUE | N35: =IF(AND(K35, M35), TRUE(), FALSE()) -> TRUE | O35: positive in a European cohort (p=0.004)
A36: rep-l-2 | B36: rep-l-2 | C36: cm-l | D36: fed-east-asia | E36: 1 | F36: 0.012 | G36: East Asian | H36: =B36 -> rep-l-2 | I36: =INDEX(CausalMechanisms!L2:L999, MATCH(C36,CausalMechanisms!A2:A999, 0)) -> /intake/new-patient/brandt-lena/mechanisms/cm-l | J36: =I36 & "/replications/" & A36 -> /intake/new-patient/brandt-lena/mechanisms/cm-l/replications/rep-l-2 | K36: =IF(AND(F36 <= 0.05, E36 = 1), TRUE(), FALSE()) -> TRUE | L36: =INDEX(CausalMechanisms!M2:M999, MATCH(C36,CausalMechanisms!A2:A999, 0)) -> Indigenous American | M36: =IF(G36 = L36, FALSE(), TRUE()) -> TRUE | N36: =IF(AND(K36, M36), TRUE(), FALSE()) -> TRUE | O36: positive in an East Asian cohort (p=0.012)
A37: rep-l-3 | B37: rep-l-3 | C37: cm-l | D37: fed-amazon | E37: 1 | F37: 0.029 | G37: Indigenous American | H37: =B37 -> rep-l-3 | I37: =INDEX(CausalMechanisms!L2:L999, MATCH(C37,CausalMechanisms!A2:A999, 0)) -> /intake/new-patient/brandt-lena/mechanisms/cm-l | J37: =I37 & "/replications/" & A37 -> /intake/new-patient/brandt-lena/mechanisms/cm-l/replications/rep-l-3 | K37: =IF(AND(F37 <= 0.05, E37 = 1), TRUE(), FALSE()) -> TRUE | L37: =INDEX(CausalMechanisms!M2:M999, MATCH(C37,CausalMechanisms!A2:A999, 0)) -> Indigenous American | M37: =IF(G37 = L37, FALSE(), TRUE()) -> FALSE | N37: =IF(AND(K37, M37), TRUE(), FALSE()) -> FALSE | O37: positive in an Indigenous American cohort (p=0.029)

Sheet NegativeControlTests
A1: NegativeControlTestId | B1: ControlLabel | C1: CausalMechanism | D1: TestKind | E1: PermutationEffectSize | F1: NullThreshold | G1: Name | H1: ParentPath | I1: RelativePath | J1: IsSurvived | K1: SourceQuote
A2: nct-a-1 | B2: nct-a-1 | C2: cm-a | D2: ancestry-permutation | E2: 0.012 | F2: 0.1 | G2: =B2 -> nct-a-1 | H2: =INDEX(CausalMechanisms!L2:L999, MATCH(C2,CausalMechanisms!A2:A999, 0)) -> /intake/new-patient/reyes-ana/mechanisms/cm-a | I2: =H2 & "/neg-controls/" & A2 -> /intake/new-patient/reyes-ana/mechanisms/cm-a/neg-controls/nct-a-1 | J2: =IF(E2 <= F2, TRUE(), FALSE()) -> TRUE | K2: permutation effect 0.012 and 0.028 inside +/-0.1
A3: nct-a-2 | B3: nct-a-2 | C3: cm-a | D3: ancestry-permutation | E3: 0.028 | F3: 0.1 | G3: =B3 -> nct-a-2 | H3: =INDEX(CausalMechanisms!L2:L999, MATCH(C3,CausalMechanisms!A2:A999, 0)) -> /intake/new-patient/reyes-ana/mechanisms/cm-a | I3: =H3 & "/neg-controls/" & A3 -> /intake/new-patient/reyes-ana/mechanisms/cm-a/neg-controls/nct-a-2 | J3: =IF(E3 <= F3, TRUE(), FALSE()) -> TRUE | K3: permutation effect 0.012 and 0.028 inside +/-0.1
A4: nct-b-1 | B4: nct-b-1 | C4: cm-b | D4: ancestry-permutation | E4: 0.015 | F4: 0.1 | G4: =B4 -> nct-b-1 | H4: =INDEX(CausalMechanisms!L2:L999, MATCH(C4,CausalMechanisms!A2:A999, 0)) -> /intake/new-patient/okafor-bili/mechanisms/cm-b | I4: =H4 & "/neg-controls/" & A4 -> /intake/new-patient/okafor-bili/mechanisms/cm-b/neg-controls/nct-b-1 | J4: =IF(E4 <= F4, TRUE(), FALSE()) -> TRUE | K4: permutation effect 0.015 and 0.024 inside +/-0.1
A5: nct-b-2 | B5: nct-b-2 | C5: cm-b | D5: ancestry-permutation | E5: 0.024 | F5: 0.1 | G5: =B5 -> nct-b-2 | H5: =INDEX(CausalMechanisms!L2:L999, MATCH(C5,CausalMechanisms!A2:A999, 0)) -> /intake/new-patient/okafor-bili/mechanisms/cm-b | I5: =H5 & "/neg-controls/" & A5 -> /intake/new-patient/okafor-bili/mechanisms/cm-b/neg-controls/nct-b-2 | J5: =IF(E5 <= F5, TRUE(), FALSE()) -> TRUE | K5: permutation effect 0.015 and 0.024 inside +/-0.1
A6: nct-d-1 | B6: nct-d-1 | C6: cm-d | D6: ancestry-permutation | E6: 0.009 | F6: 0.1 | G6: =B6 -> nct-d-1 | H6: =INDEX(CausalMechanisms!L2:L999, MATCH(C6,CausalMechanisms!A2:A999, 0)) -> /intake/new-patient/santos-diego/mechanisms/cm-d | I6: =H6 & "/neg-controls/" & A6 -> /intake/new-patient/santos-diego/mechanisms/cm-d/neg-controls/nct-d-1 | J6: =IF(E6 <= F6, TRUE(), FALSE()) -> TRUE | K6: permutation effect 0.009 and 0.031 inside +/-0.1
A7: nct-d-2 | B7: nct-d-2 | C7: cm-d | D7: ancestry-permutation | E7: 0.031 | F7: 0.1 | G7: =B7 -> nct-d-2 | H7: =INDEX(CausalMechanisms!L2:L999, MATCH(C7,CausalMechanisms!A2:A999, 0)) -> /intake/new-patient/santos-diego/mechanisms/cm-d | I7: =H7 & "/neg-controls/" & A7 -> /intake/new-patient/santos-diego/mechanisms/cm-d/neg-controls/nct-d-2 | J7: =IF(E7 <= F7, TRUE(), FALSE()) -> TRUE | K7: permutation effect 0.009 and 0.031 inside +/-0.1
A8: nct-e-1 | B8: nct-e-1 | C8: cm-e | D8: ancestry-permutation | E8: 0.011 | F8: 0.1 | G8: =B8 -> nct-e-1 | H8: =INDEX(CausalMechanisms!L2:L999, MATCH(C8,CausalMechanisms!A2:A999, 0)) -> /intake/new-patient/mensah-esi/mechanisms/cm-e | I8: =H8 & "/neg-controls/" & A8 -> /intake/new-patient/mensah-esi/mechanisms/cm-e/neg-controls/nct-e-1 | J8: =IF(E8 <= F8, TRUE(), FALSE()) -> TRUE | K8: permutation effect 0.011 and 0.026 inside +/-0.1
A9: nct-e-2 | B9: nct-e-2 | C9: cm-e | D9: ancestry-permutation | E9: 0.026 | F9: 0.1 | G9: =B9 -> nct-e-2 | H9: =INDEX(CausalMechanisms!L2:L999, MATCH(C9,CausalMechanisms!A2:A999, 0)) -> /intake/new-patient/mensah-esi/mechanisms/cm-e | I9: =H9 & "/neg-controls/" & A9 -> /intake/new-patient/mensah-esi/mechanisms/cm-e/neg-controls/nct-e-2 | J9: =IF(E9 <= F9, TRUE(), FALSE()) -> TRUE | K9: permutation effect 0.011 and 0.026 inside +/-0.1
A10: nct-f-1 | B10: nct-f-1 | C10: cm-f | D10: ancestry-permutation | E10: 0.008 | F10: 0.1 | G10: =B10 -> nct-f-1 | H10: =INDEX(CausalMechanisms!L2:L999, MATCH(C10,CausalMechanisms!A2:A999, 0)) -> /intake/new-patient/haidar-faisal/mechanisms/cm-f | I10: =H10 & "/neg-controls/" & A10 -> /intake/new-patient/haidar-faisal/mechanisms/cm-f/neg-controls/nct-f-1 | J10: =IF(E10 <= F10, TRUE(), FALSE()) -> TRUE | K10: permutation effect 0.008 and 0.022 inside +/-0.1
A11: nct-f-2 | B11: nct-f-2 | C11: cm-f | D11: ancestry-permutation | E11: 0.022 | F11: 0.1 | G11: =B11 -> nct-f-2 | H11: =INDEX(CausalMechanisms!L2:L999, MATCH(C11,CausalMechanisms!A2:A999, 0)) -> /intake/new-patient/haidar-faisal/mechanisms/cm-f | I11: =H11 & "/neg-controls/" & A11 -> /intake/new-patient/haidar-faisal/mechanisms/cm-f/neg-controls/nct-f-2 | J11: =IF(E11 <= F11, TRUE(), FALSE()) -> TRUE | K11: permutation effect 0.008 and 0.022 inside +/-0.1
A12: nct-g-1 | B12: nct-g-1 | C12: cm-g | D12: ancestry-permutation | E12: 0.007 | F12: 0.1 | G12: =B12 -> nct-g-1 | H12: =INDEX(CausalMechanisms!L2:L999, MATCH(C12,CausalMechanisms!A2:A999, 0)) -> /intake/new-patient/lin-grace/mechanisms/cm-g | I12: =H12 & "/neg-controls/" & A12 -> /intake/new-patient/lin-grace/mechanisms/cm-g/neg-controls/nct-g-1 | J12: =IF(E12 <= F12, TRUE(), FALSE()) -> TRUE | K12: permutation effect 0.007 and 0.019 inside +/-0.1
A13: nct-g-2 | B13: nct-g-2 | C13: cm-g | D13: ancestry-permutation | E13: 0.019 | F13: 0.1 | G13: =B13 -> nct-g-2 | H13: =INDEX(CausalMechanisms!L2:L999, MATCH(C13,CausalMechanisms!A2:A999, 0)) -> /intake/new-patient/lin-grace/mechanisms/cm-g | I13: =H13 & "/neg-controls/" & A13 -> /intake/new-patient/lin-grace/mechanisms/cm-g/neg-controls/nct-g-2 | J13: =IF(E13 <= F13, TRUE(), FALSE()) -> TRUE | K13: permutation effect 0.007 and 0.019 inside +/-0.1
A14: nct-c-1 | B14: nct-c-1 | C14: cm-c | D14: ancestry-permutation | E14: 0.013 | F14: 0.1 | G14: =B14 -> nct-c-1 | H14: =INDEX(CausalMechanisms!L2:L999, MATCH(C14,CausalMechanisms!A2:A999, 0)) -> /intake/new-patient/wei-chen/mechanisms/cm-c | I14: =H14 & "/neg-controls/" & A14 -> /intake/new-patient/wei-chen/mechanisms/cm-c/neg-controls/nct-c-1 | J14: =IF(E14 <= F14, TRUE(), FALSE()) -> TRUE | K14: one ancestry-permutation control collapses (permutation effect 0.013)
A15: nct-c-2 | B15: nct-c-2 | C15: cm-c | D15: ancestry-permutation | E15: 0.46 | F15: 0.1 | G15: =B15 -> nct-c-2 | H15: =INDEX(CausalMechanisms!L2:L999, MATCH(C15,CausalMechanisms!A2:A999, 0)) -> /intake/new-patient/wei-chen/mechanisms/cm-c | I15: =H15 & "/neg-controls/" & A15 -> /intake/new-patient/wei-chen/mechanisms/cm-c/neg-controls/nct-c-2 | J15: =IF(E15 <= F15, TRUE(), FALSE()) -> FALSE | K15: its permutation effect is 0.46, far outside the +/-0.1 null band
A16: nct-h-1 | B16: nct-h-1 | C16: cm-h | D16: ancestry-permutation | E16: 0.012 | F16: 0.1 | G16: =B16 -> nct-h-1 | H16: =INDEX(CausalMechanisms!L2:L999, MATCH(C16,CausalMechanisms!A2:A999, 0)) -> /intake/new-patient/yamamoto-hana/mechanisms/cm-h | I16: =H16 & "/neg-controls/" & A16 -> /intake/new-patient/yamamoto-hana/mechanisms/cm-h/neg-controls/nct-h-1 | J16: =IF(E16 <= F16, TRUE(), FALSE()) -> TRUE | K16: permutation effect 0.012 and 0.028 inside +/-0.1
A17: nct-h-2 | B17: nct-h-2 | C17: cm-h | D17: ancestry-permutation | E17: 0.028 | F17: 0.1 | G17: =B17 -> nct-h-2 | H17: =INDEX(CausalMechanisms!L2:L999, MATCH(C17,CausalMechanisms!A2:A999, 0)) -> /intake/new-patient/yamamoto-hana/mechanisms/cm-h | I17: =H17 & "/neg-controls/" & A17 -> /intake/new-patient/yamamoto-hana/mechanisms/cm-h/neg-controls/nct-h-2 | J17: =IF(E17 <= F17, TRUE(), FALSE()) -> TRUE | K17: permutation effect 0.012 and 0.028 inside +/-0.1
A18: nct-i-1 | B18: nct-i-1 | C18: cm-i | D18: ancestry-permutation | E18: 0.009 | F18: 0.1 | G18: =B18 -> nct-i-1 | H18: =INDEX(CausalMechanisms!L2:L999, MATCH(C18,CausalMechanisms!A2:A999, 0)) -> /intake/new-patient/conteh-ibrahim/mechanisms/cm-i | I18: =H18 & "/neg-controls/" & A18 -> /intake/new-patient/conteh-ibrahim/mechanisms/cm-i/neg-controls/nct-i-1 | J18: =IF(E18 <= F18, TRUE(), FALSE()) -> TRUE | K18: permutation effect 0.009 and 0.031 inside +/-0.1
A19: nct-i-2 | B19: nct-i-2 | C19: cm-i | D19: ancestry-permutation | E19: 0.031 | F19: 0.1 | G19: =B19 -> nct-i-2 | H19: =INDEX(CausalMechanisms!L2:L999, MATCH(C19,CausalMechanisms!A2:A999, 0)) -> /intake/new-patient/conteh-ibrahim/mechanisms/cm-i | I19: =H19 & "/neg-controls/" & A19 -> /intake/new-patient/conteh-ibrahim/mechanisms/cm-i/neg-controls/nct-i-2 | J19: =IF(E19 <= F19, TRUE(), FALSE()) -> TRUE | K19: permutation effect 0.009 and 0.031 inside +/-0.1
A20: nct-j-1 | B20: nct-j-1 | C20: cm-j | D20: ancestry-permutation | E20: 0.015 | F20: 0.1 | G20: =B20 -> nct-j-1 | H20: =INDEX(CausalMechanisms!L2:L999, MATCH(C20,CausalMechanisms!A2:A999, 0)) -> /intake/new-patient/brooks-jamal/mechanisms/cm-j | I20: =H20 & "/neg-controls/" & A20 -> /intake/new-patient/brooks-jamal/mechanisms/cm-j/neg-controls/nct-j-1 | J20: =IF(E20 <= F20, TRUE(), FALSE()) -> TRUE | K20: permutation effect 0.015 and 0.024 inside +/-0.1
A21: nct-j-2 | B21: nct-j-2 | C21: cm-j | D21: ancestry-permutation | E21: 0.024 | F21: 0.1 | G21: =B21 -> nct-j-2 | H21: =INDEX(CausalMechanisms!L2:L999, MATCH(C21,CausalMechanisms!A2:A999, 0)) -> /intake/new-patient/brooks-jamal/mechanisms/cm-j | I21: =H21 & "/neg-controls/" & A21 -> /intake/new-patient/brooks-jamal/mechanisms/cm-j/neg-controls/nct-j-2 | J21: =IF(E21 <= F21, TRUE(), FALSE()) -> TRUE | K21: permutation effect 0.015 and 0.024 inside +/-0.1
A22: nct-k-1 | B22: nct-k-1 | C22: cm-k | D22: ancestry-permutation | E22: 0.008 | F22: 0.1 | G22: =B22 -> nct-k-1 | H22: =INDEX(CausalMechanisms!L2:L999, MATCH(C22,CausalMechanisms!A2:A999, 0)) -> /intake/new-patient/nair-kavya/mechanisms/cm-k | I22: =H22 & "/neg-controls/" & A22 -> /intake/new-patient/nair-kavya/mechanisms/cm-k/neg-controls/nct-k-1 | J22: =IF(E22 <= F22, TRUE(), FALSE()) -> TRUE | K22: permutation effect 0.008 and 0.022 inside +/-0.1
A23: nct-k-2 | B23: nct-k-2 | C23: cm-k | D23: ancestry-permutation | E23: 0.022 | F23: 0.1 | G23: =B23 -> nct-k-2 | H23: =INDEX(CausalMechanisms!L2:L999, MATCH(C23,CausalMechanisms!A2:A999, 0)) -> /intake/new-patient/nair-kavya/mechanisms/cm-k | I23: =H23 & "/neg-controls/" & A23 -> /intake/new-patient/nair-kavya/mechanisms/cm-k/neg-controls/nct-k-2 | J23: =IF(E23 <= F23, TRUE(), FALSE()) -> TRUE | K23: permutation effect 0.008 and 0.022 inside +/-0.1
A24: nct-l-1 | B24: nct-l-1 | C24: cm-l | D24: ancestry-permutation | E24: 0.007 | F24: 0.1 | G24: =B24 -> nct-l-1 | H24: =INDEX(CausalMechanisms!L2:L999, MATCH(C24,CausalMechanisms!A2:A999, 0)) -> /intake/new-patient/brandt-lena/mechanisms/cm-l | I24: =H24 & "/neg-controls/" & A24 -> /intake/new-patient/brandt-lena/mechanisms/cm-l/neg-controls/nct-l-1 | J24: =IF(E24 <= F24, TRUE(), FALSE()) -> TRUE | K24: permutation effect 0.007 and 0.019 inside +/-0.1
A25: nct-l-2 | B25: nct-l-2 | C25: cm-l | D25: ancestry-permutation | E25: 0.019 | F25: 0.1 | G25: =B25 -> nct-l-2 | H25: =INDEX(CausalMechanisms!L2:L999, MATCH(C25,CausalMechanisms!A2:A999, 0)) -> /intake/new-patient/brandt-lena/mechanisms/cm-l | I25: =H25 & "/neg-controls/" & A25 -> /intake/new-patient/brandt-lena/mechanisms/cm-l/neg-controls/nct-l-2 | J25: =IF(E25 <= F25, TRUE(), FALSE()) -> TRUE | K25: permutation effect 0.007 and 0.019 inside +/-0.1

Sheet EnvironmentalExposures
A1: EnvironmentalExposureId | B1: ExposureLabel | C1: Individual | D1: ExposureLevel | E1: ExposureStartDate | F1: IsMaternalEffect | G1: Name | H1: ParentPath | I1: RelativePath | J1: IndividualAncestryLabel | K1: IsHighExposure
A2: exp-context | B2: Smoking pack-years (context only) | C2: ind-a-reyes | D2: 3 | E2: 42005 | F2: FALSE | G2: =B2 -> Smoking pack-years (context only) | H2: =INDEX(Individuals!L2:L999, MATCH(C2,Individuals!A2:A999, 0)) -> /intake/new-patient/reyes-ana | I2: =H2 & "/exposures/" & A2 -> /intake/new-patient/reyes-ana/exposures/exp-context | J2: =INDEX(Individuals!D2:D999, MATCH(C2,Individuals!A2:A999, 0)) -> European | K2: =IF(D2 > 5, TRUE(), FALSE()) -> FALSE

Sheet Treatments
A1: TreatmentId | B1: TreatmentLabel | C1: Individual | D1: AutoimmuneDisease | E1: TargetsMechanism | F1: TreatmentResponse | G1: HasTreatmentInducedChange | H1: HasAdverseEffect | I1: StartDate | J1: Name | K1: ParentPath | L1: RelativePath | M1: AutoimmuneDiseaseLabel | N1: IsEffectiveTreatment | O1: IsMechanismMatched | P1: IsTreatmentResponsePredicted | Q1: TreatmentResponseDecidingFactor
A2: tx-a | B2: Anifrolumab (anti-IFNAR1) | C2: ind-a-reyes | D2: sle | E2: cm-a | F2: Partial | G2: TRUE | H2: FALSE | I2: 45383 | J2: =B2 -> Anifrolumab (anti-IFNAR1) | K2: =INDEX(Individuals!L2:L999, MATCH(C2,Individuals!A2:A999, 0)) -> /intake/new-patient/reyes-ana | L2: =K2 & "/treatments/" & A2 -> /intake/new-patient/reyes-ana/treatments/tx-a | M2: =INDEX(AutoimmuneDiseases!B2:B999, MATCH(D2,AutoimmuneDiseases!A2:A999, 0)) -> Systemic Lupus Erythematosus | N2: =IF(AND(OR(F2 = "Complete", F2 = "Partial"), NOT(H2)), TRUE(), FALSE()) -> TRUE | O2: =IF(E2 = "", FALSE(), INDEX(CausalMechanisms!AC2:AC999, MATCH(E2,CausalMechanisms!A2:A999, 0))) -> TRUE | P2: =IF(AND(N2, O2), TRUE(), FALSE()) -> TRUE | Q2: =IF(P2, "EffectiveOnConfirmedMechanism", IF(NOT(O2), "NoConfirmedMechanism", IF(H2, "AdverseEffect", IF(OR(F2 = "None", F2 = "Adverse"), "NoResponse", "Undetermined")))) -> EffectiveOnConfirmedMechanism
A3: tx-b | B3: Anifrolumab (anti-IFNAR1) | C3: ind-b-okafor | D3: sle | E3: cm-b | F3: Complete | G3: TRUE | H3: FALSE | I3: 45383 | J3: =B3 -> Anifrolumab (anti-IFNAR1) | K3: =INDEX(Individuals!L2:L999, MATCH(C3,Individuals!A2:A999, 0)) -> /intake/new-patient/okafor-bili | L3: =K3 & "/treatments/" & A3 -> /intake/new-patient/okafor-bili/treatments/tx-b | M3: =INDEX(AutoimmuneDiseases!B2:B999, MATCH(D3,AutoimmuneDiseases!A2:A999, 0)) -> Systemic Lupus Erythematosus | N3: =IF(AND(OR(F3 = "Complete", F3 = "Partial"), NOT(H3)), TRUE(), FALSE()) -> TRUE | O3: =IF(E3 = "", FALSE(), INDEX(CausalMechanisms!AC2:AC999, MATCH(E3,CausalMechanisms!A2:A999, 0))) -> TRUE | P3: =IF(AND(N3, O3), TRUE(), FALSE()) -> TRUE | Q3: =IF(P3, "EffectiveOnConfirmedMechanism", IF(NOT(O3), "NoConfirmedMechanism", IF(H3, "AdverseEffect", IF(OR(F3 = "None", F3 = "Adverse"), "NoResponse", "Undetermined")))) -> EffectiveOnConfirmedMechanism
A4: tx-c | B4: STAT4-pathway inhibitor (trial) | C4: ind-c-chen | D4: sle | E4: cm-c | F4: Partial | G4: TRUE | H4: FALSE | I4: 45383 | J4: =B4 -> STAT4-pathway inhibitor (trial) | K4: =INDEX(Individuals!L2:L999, MATCH(C4,Individuals!A2:A999, 0)) -> /intake/new-patient/wei-chen | L4: =K4 & "/treatments/" & A4 -> /intake/new-patient/wei-chen/treatments/tx-c | M4: =INDEX(AutoimmuneDiseases!B2:B999, MATCH(D4,AutoimmuneDiseases!A2:A999, 0)) -> Systemic Lupus Erythematosus | N4: =IF(AND(OR(F4 = "Complete", F4 = "Partial"), NOT(H4)), TRUE(), FALSE()) -> TRUE | O4: =IF(E4 = "", FALSE(), INDEX(CausalMechanisms!AC2:AC999, MATCH(E4,CausalMechanisms!A2:A999, 0))) -> FALSE | P4: =IF(AND(N4, O4), TRUE(), FALSE()) -> FALSE | Q4: =IF(P4, "EffectiveOnConfirmedMechanism", IF(NOT(O4), "NoConfirmedMechanism", IF(H4, "AdverseEffect", IF(OR(F4 = "None", F4 = "Adverse"), "NoResponse", "Undetermined")))) -> NoConfirmedMechanism
A5: tx-d | B5: Anifrolumab (anti-IFNAR1) | C5: ind-d-santos | D5: sle | E5: cm-d | F5: Complete | G5: TRUE | H5: TRUE | I5: 45383 | J5: =B5 -> Anifrolumab (anti-IFNAR1) | K5: =INDEX(Individuals!L2:L999, MATCH(C5,Individuals!A2:A999, 0)) -> /intake/new-patient/santos-diego | L5: =K5 & "/treatments/" & A5 -> /intake/new-patient/santos-diego/treatments/tx-d | M5: =INDEX(AutoimmuneDiseases!B2:B999, MATCH(D5,AutoimmuneDiseases!A2:A999, 0)) -> Systemic Lupus Erythematosus | N5: =IF(AND(OR(F5 = "Complete", F5 = "Partial"), NOT(H5)), TRUE(), FALSE()) -> FALSE | O5: =IF(E5 = "", FALSE(), INDEX(CausalMechanisms!AC2:AC999, MATCH(E5,CausalMechanisms!A2:A999, 0))) -> TRUE | P5: =IF(AND(N5, O5), TRUE(), FALSE()) -> FALSE | Q5: =IF(P5, "EffectiveOnConfirmedMechanism", IF(NOT(O5), "NoConfirmedMechanism", IF(H5, "AdverseEffect", IF(OR(F5 = "None", F5 = "Adverse"), "NoResponse", "Undetermined")))) -> AdverseEffect
A6: tx-e | B6: CTLA4-Ig (abatacept, off-target) | C6: ind-e-mensah | D6: sle | E6: cm-e | F6: None | G6: FALSE | H6: FALSE | I6: 45383 | J6: =B6 -> CTLA4-Ig (abatacept, off-target) | K6: =INDEX(Individuals!L2:L999, MATCH(C6,Individuals!A2:A999, 0)) -> /intake/new-patient/mensah-esi | L6: =K6 & "/treatments/" & A6 -> /intake/new-patient/mensah-esi/treatments/tx-e | M6: =INDEX(AutoimmuneDiseases!B2:B999, MATCH(D6,AutoimmuneDiseases!A2:A999, 0)) -> Systemic Lupus Erythematosus | N6: =IF(AND(OR(F6 = "Complete", F6 = "Partial"), NOT(H6)), TRUE(), FALSE()) -> FALSE | O6: =IF(E6 = "", FALSE(), INDEX(CausalMechanisms!AC2:AC999, MATCH(E6,CausalMechanisms!A2:A999, 0))) -> FALSE | P6: =IF(AND(N6, O6), TRUE(), FALSE()) -> FALSE | Q6: =IF(P6, "EffectiveOnConfirmedMechanism", IF(NOT(O6), "NoConfirmedMechanism", IF(H6, "AdverseEffect", IF(OR(F6 = "None", F6 = "Adverse"), "NoResponse", "Undetermined")))) -> NoConfirmedMechanism
A7: tx-f | B7: Secukinumab (anti-IL-17) | C7: ind-f-haidar | D7: psa | E7: cm-f | F7: None | G7: FALSE | H7: FALSE | I7: 45383 | J7: =B7 -> Secukinumab (anti-IL-17) | K7: =INDEX(Individuals!L2:L999, MATCH(C7,Individuals!A2:A999, 0)) -> /intake/new-patient/haidar-faisal | L7: =K7 & "/treatments/" & A7 -> /intake/new-patient/haidar-faisal/treatments/tx-f | M7: =INDEX(AutoimmuneDiseases!B2:B999, MATCH(D7,AutoimmuneDiseases!A2:A999, 0)) -> Psoriatic Arthritis | N7: =IF(AND(OR(F7 = "Complete", F7 = "Partial"), NOT(H7)), TRUE(), FALSE()) -> FALSE | O7: =IF(E7 = "", FALSE(), INDEX(CausalMechanisms!AC2:AC999, MATCH(E7,CausalMechanisms!A2:A999, 0))) -> TRUE | P7: =IF(AND(N7, O7), TRUE(), FALSE()) -> FALSE | Q7: =IF(P7, "EffectiveOnConfirmedMechanism", IF(NOT(O7), "NoConfirmedMechanism", IF(H7, "AdverseEffect", IF(OR(F7 = "None", F7 = "Adverse"), "NoResponse", "Undetermined")))) -> NoResponse
A8: tx-g | B8: Secukinumab (anti-IL-17) | C8: ind-g-lin | D8: psa | E8: cm-g | F8: Partial | G8: TRUE | H8: FALSE | I8: 45383 | J8: =B8 -> Secukinumab (anti-IL-17) | K8: =INDEX(Individuals!L2:L999, MATCH(C8,Individuals!A2:A999, 0)) -> /intake/new-patient/lin-grace | L8: =K8 & "/treatments/" & A8 -> /intake/new-patient/lin-grace/treatments/tx-g | M8: =INDEX(AutoimmuneDiseases!B2:B999, MATCH(D8,AutoimmuneDiseases!A2:A999, 0)) -> Psoriatic Arthritis | N8: =IF(AND(OR(F8 = "Complete", F8 = "Partial"), NOT(H8)), TRUE(), FALSE()) -> TRUE | O8: =IF(E8 = "", FALSE(), INDEX(CausalMechanisms!AC2:AC999, MATCH(E8,CausalMechanisms!A2:A999, 0))) -> TRUE | P8: =IF(AND(N8, O8), TRUE(), FALSE()) -> TRUE | Q8: =IF(P8, "EffectiveOnConfirmedMechanism", IF(NOT(O8), "NoConfirmedMechanism", IF(H8, "AdverseEffect", IF(OR(F8 = "None", F8 = "Adverse"), "NoResponse", "Undetermined")))) -> EffectiveOnConfirmedMechanism
A9: tx-h | B9: Anifrolumab (anti-IFNAR1) | C9: ind-h-yamamoto | D9: sle | E9: cm-h | F9: Partial | G9: TRUE | H9: FALSE | I9: 45383 | J9: =B9 -> Anifrolumab (anti-IFNAR1) | K9: =INDEX(Individuals!L2:L999, MATCH(C9,Individuals!A2:A999, 0)) -> /intake/new-patient/yamamoto-hana | L9: =K9 & "/treatments/" & A9 -> /intake/new-patient/yamamoto-hana/treatments/tx-h | M9: =INDEX(AutoimmuneDiseases!B2:B999, MATCH(D9,AutoimmuneDiseases!A2:A999, 0)) -> Systemic Lupus Erythematosus | N9: =IF(AND(OR(F9 = "Complete", F9 = "Partial"), NOT(H9)), TRUE(), FALSE()) -> TRUE | O9: =IF(E9 = "", FALSE(), INDEX(CausalMechanisms!AC2:AC999, MATCH(E9,CausalMechanisms!A2:A999, 0))) -> TRUE | P9: =IF(AND(N9, O9), TRUE(), FALSE()) -> TRUE | Q9: =IF(P9, "EffectiveOnConfirmedMechanism", IF(NOT(O9), "NoConfirmedMechanism", IF(H9, "AdverseEffect", IF(OR(F9 = "None", F9 = "Adverse"), "NoResponse", "Undetermined")))) -> EffectiveOnConfirmedMechanism
A10: tx-i | B10: Anifrolumab (anti-IFNAR1) | C10: ind-i-conteh | D10: sle | E10: cm-i | F10: Complete | G10: TRUE | H10: TRUE | I10: 45383 | J10: =B10 -> Anifrolumab (anti-IFNAR1) | K10: =INDEX(Individuals!L2:L999, MATCH(C10,Individuals!A2:A999, 0)) -> /intake/new-patient/conteh-ibrahim | L10: =K10 & "/treatments/" & A10 -> /intake/new-patient/conteh-ibrahim/treatments/tx-i | M10: =INDEX(AutoimmuneDiseases!B2:B999, MATCH(D10,AutoimmuneDiseases!A2:A999, 0)) -> Systemic Lupus Erythematosus | N10: =IF(AND(OR(F10 = "Complete", F10 = "Partial"), NOT(H10)), TRUE(), FALSE()) -> FALSE | O10: =IF(E10 = "", FALSE(), INDEX(CausalMechanisms!AC2:AC999, MATCH(E10,CausalMechanisms!A2:A999, 0))) -> TRUE | P10: =IF(AND(N10, O10), TRUE(), FALSE()) -> FALSE | Q10: =IF(P10, "EffectiveOnConfirmedMechanism", IF(NOT(O10), "NoConfirmedMechanism", IF(H10, "AdverseEffect", IF(OR(F10 = "None", F10 = "Adverse"), "NoResponse", "Undetermined")))) -> AdverseEffect
A11: tx-j | B11: Anifrolumab (anti-IFNAR1) | C11: ind-j-brooks | D11: sle | E11: cm-j | F11: Complete | G11: TRUE | H11: FALSE | I11: 45383 | J11: =B11 -> Anifrolumab (anti-IFNAR1) | K11: =INDEX(Individuals!L2:L999, MATCH(C11,Individuals!A2:A999, 0)) -> /intake/new-patient/brooks-jamal | L11: =K11 & "/treatments/" & A11 -> /intake/new-patient/brooks-jamal/treatments/tx-j | M11: =INDEX(AutoimmuneDiseases!B2:B999, MATCH(D11,AutoimmuneDiseases!A2:A999, 0)) -> Systemic Lupus Erythematosus | N11: =IF(AND(OR(F11 = "Complete", F11 = "Partial"), NOT(H11)), TRUE(), FALSE()) -> TRUE | O11: =IF(E11 = "", FALSE(), INDEX(CausalMechanisms!AC2:AC999, MATCH(E11,CausalMechanisms!A2:A999, 0))) -> TRUE | P11: =IF(AND(N11, O11), TRUE(), FALSE()) -> TRUE | Q11: =IF(P11, "EffectiveOnConfirmedMechanism", IF(NOT(O11), "NoConfirmedMechanism", IF(H11, "AdverseEffect", IF(OR(F11 = "None", F11 = "Adverse"), "NoResponse", "Undetermined")))) -> EffectiveOnConfirmedMechanism
A12: tx-k | B12: Secukinumab (anti-IL-17) | C12: ind-k-nair | D12: psa | E12: cm-k | F12: None | G12: FALSE | H12: FALSE | I12: 45383 | J12: =B12 -> Secukinumab (anti-IL-17) | K12: =INDEX(Individuals!L2:L999, MATCH(C12,Individuals!A2:A999, 0)) -> /intake/new-patient/nair-kavya | L12: =K12 & "/treatments/" & A12 -> /intake/new-patient/nair-kavya/treatments/tx-k | M12: =INDEX(AutoimmuneDiseases!B2:B999, MATCH(D12,AutoimmuneDiseases!A2:A999, 0)) -> Psoriatic Arthritis | N12: =IF(AND(OR(F12 = "Complete", F12 = "Partial"), NOT(H12)), TRUE(), FALSE()) -> FALSE | O12: =IF(E12 = "", FALSE(), INDEX(CausalMechanisms!AC2:AC999, MATCH(E12,CausalMechanisms!A2:A999, 0))) -> TRUE | P12: =IF(AND(N12, O12), TRUE(), FALSE()) -> FALSE | Q12: =IF(P12, "EffectiveOnConfirmedMechanism", IF(NOT(O12), "NoConfirmedMechanism", IF(H12, "AdverseEffect", IF(OR(F12 = "None", F12 = "Adverse"), "NoResponse", "Undetermined")))) -> NoResponse
A13: tx-l | B13: Secukinumab (anti-IL-17) | C13: ind-l-brandt | D13: psa | E13: cm-l | F13: Partial | G13: TRUE | H13: FALSE | I13: 45383 | J13: =B13 -> Secukinumab (anti-IL-17) | K13: =INDEX(Individuals!L2:L999, MATCH(C13,Individuals!A2:A999, 0)) -> /intake/new-patient/brandt-lena | L13: =K13 & "/treatments/" & A13 -> /intake/new-patient/brandt-lena/treatments/tx-l | M13: =INDEX(AutoimmuneDiseases!B2:B999, MATCH(D13,AutoimmuneDiseases!A2:A999, 0)) -> Psoriatic Arthritis | N13: =IF(AND(OR(F13 = "Complete", F13 = "Partial"), NOT(H13)), TRUE(), FALSE()) -> TRUE | O13: =IF(E13 = "", FALSE(), INDEX(CausalMechanisms!AC2:AC999, MATCH(E13,CausalMechanisms!A2:A999, 0))) -> TRUE | P13: =IF(AND(N13, O13), TRUE(), FALSE()) -> TRUE | Q13: =IF(P13, "EffectiveOnConfirmedMechanism", IF(NOT(O13), "NoConfirmedMechanism", IF(H13, "AdverseEffect", IF(OR(F13 = "None", F13 = "Adverse"), "NoResponse", "Undetermined")))) -> EffectiveOnConfirmedMechanism

Sheet ClinicalPhenotypes
A1: ClinicalPhenotypeId | B1: PhenotypeLabel | C1: Individual | D1: AutoimmuneDisease | E1: DiseaseStage | F1: Tissue | G1: SeverityScore | H1: MeasurementDate | I1: HasImmuneDysfunction | J1: Name | K1: ParentPath | L1: RelativePath | M1: DiseaseStageLabel | N1: IsHighSeverity | O1: IsPresymptomaticPhenotype
A2: ph-sev-a | B2: Active SLE — high disease-activity (SLEDAI-equiv) severity | C2: ind-a-reyes | D2: sle | E2: sle-active | F2: blood | G2: 9 | H2: 45352 | I2: TRUE | J2: =B2 -> Active SLE — high disease-activity (SLEDAI-equiv) severity | K2: =INDEX(Individuals!L2:L999, MATCH(C2,Individuals!A2:A999, 0)) -> /intake/new-patient/reyes-ana | L2: =K2 & "/phenotypes/" & A2 -> /intake/new-patient/reyes-ana/phenotypes/ph-sev-a | M2: =IF(E2 = "", "", INDEX(DiseaseStages!B2:B999, MATCH(E2,DiseaseStages!A2:A999, 0))) -> Active | N2: =IF(G2 > 7, TRUE(), FALSE()) -> TRUE | O2: =IF(M2 = "Presymptomatic", TRUE(), FALSE()) -> FALSE
A3: ph-sev-b | B3: Active SLE — serositis + high disease activity | C3: ind-b-okafor | D3: sle | E3: sle-active | F3: blood | G3: 8 | H3: 45352 | I3: TRUE | J3: =B3 -> Active SLE — serositis + high disease activity | K3: =INDEX(Individuals!L2:L999, MATCH(C3,Individuals!A2:A999, 0)) -> /intake/new-patient/okafor-bili | L3: =K3 & "/phenotypes/" & A3 -> /intake/new-patient/okafor-bili/phenotypes/ph-sev-b | M3: =IF(E3 = "", "", INDEX(DiseaseStages!B2:B999, MATCH(E3,DiseaseStages!A2:A999, 0))) -> Active | N3: =IF(G3 > 7, TRUE(), FALSE()) -> TRUE | O3: =IF(M3 = "Presymptomatic", TRUE(), FALSE()) -> FALSE
A4: ph-sev-c | B4: Active SLE — arthritis + anti-dsDNA high activity | C4: ind-c-chen | D4: sle | E4: sle-active | F4: blood | G4: 9 | H4: 45352 | I4: TRUE | J4: =B4 -> Active SLE — arthritis + anti-dsDNA high activity | K4: =INDEX(Individuals!L2:L999, MATCH(C4,Individuals!A2:A999, 0)) -> /intake/new-patient/wei-chen | L4: =K4 & "/phenotypes/" & A4 -> /intake/new-patient/wei-chen/phenotypes/ph-sev-c | M4: =IF(E4 = "", "", INDEX(DiseaseStages!B2:B999, MATCH(E4,DiseaseStages!A2:A999, 0))) -> Active | N4: =IF(G4 > 7, TRUE(), FALSE()) -> TRUE | O4: =IF(M4 = "Presymptomatic", TRUE(), FALSE()) -> FALSE
A5: ph-sev-d | B5: Active SLE — biopsy-confirmed nephritis (high severity) | C5: ind-d-santos | D5: sle | E5: sle-active | F5: kidney | G5: 8 | H5: 45352 | I5: TRUE | J5: =B5 -> Active SLE — biopsy-confirmed nephritis (high severity) | K5: =INDEX(Individuals!L2:L999, MATCH(C5,Individuals!A2:A999, 0)) -> /intake/new-patient/santos-diego | L5: =K5 & "/phenotypes/" & A5 -> /intake/new-patient/santos-diego/phenotypes/ph-sev-d | M5: =IF(E5 = "", "", INDEX(DiseaseStages!B2:B999, MATCH(E5,DiseaseStages!A2:A999, 0))) -> Active | N5: =IF(G5 > 7, TRUE(), FALSE()) -> TRUE | O5: =IF(M5 = "Presymptomatic", TRUE(), FALSE()) -> FALSE
A6: ph-sev-e | B6: SLE — mild cytopenias, low disease activity | C6: ind-e-mensah | D6: sle | E6: sle-active | F6: blood | G6: 3 | H6: 45352 | I6: TRUE | J6: =B6 -> SLE — mild cytopenias, low disease activity | K6: =INDEX(Individuals!L2:L999, MATCH(C6,Individuals!A2:A999, 0)) -> /intake/new-patient/mensah-esi | L6: =K6 & "/phenotypes/" & A6 -> /intake/new-patient/mensah-esi/phenotypes/ph-sev-e | M6: =IF(E6 = "", "", INDEX(DiseaseStages!B2:B999, MATCH(E6,DiseaseStages!A2:A999, 0))) -> Active | N6: =IF(G6 > 7, TRUE(), FALSE()) -> FALSE | O6: =IF(M6 = "Presymptomatic", TRUE(), FALSE()) -> FALSE
A7: ph-sev-f | B7: PsA — minimal joint involvement, mild | C7: ind-f-haidar | D7: psa | E7: psa-active | F7: synovium | G7: 2 | H7: 45352 | I7: TRUE | J7: =B7 -> PsA — minimal joint involvement, mild | K7: =INDEX(Individuals!L2:L999, MATCH(C7,Individuals!A2:A999, 0)) -> /intake/new-patient/haidar-faisal | L7: =K7 & "/phenotypes/" & A7 -> /intake/new-patient/haidar-faisal/phenotypes/ph-sev-f | M7: =IF(E7 = "", "", INDEX(DiseaseStages!B2:B999, MATCH(E7,DiseaseStages!A2:A999, 0))) -> Active | N7: =IF(G7 > 7, TRUE(), FALSE()) -> FALSE | O7: =IF(M7 = "Presymptomatic", TRUE(), FALSE()) -> FALSE
A8: ph-sev-g | B8: PsA — moderate plaque + oligoarthritis | C8: ind-g-lin | D8: psa | E8: psa-active | F8: skin | G8: 6 | H8: 45352 | I8: TRUE | J8: =B8 -> PsA — moderate plaque + oligoarthritis | K8: =INDEX(Individuals!L2:L999, MATCH(C8,Individuals!A2:A999, 0)) -> /intake/new-patient/lin-grace | L8: =K8 & "/phenotypes/" & A8 -> /intake/new-patient/lin-grace/phenotypes/ph-sev-g | M8: =IF(E8 = "", "", INDEX(DiseaseStages!B2:B999, MATCH(E8,DiseaseStages!A2:A999, 0))) -> Active | N8: =IF(G8 > 7, TRUE(), FALSE()) -> FALSE | O8: =IF(M8 = "Presymptomatic", TRUE(), FALSE()) -> FALSE
A9: ph-sev-h | B9: Active SLE — high disease-activity (SLEDAI-equiv) severity | C9: ind-h-yamamoto | D9: sle | E9: sle-active | F9: blood | G9: 9 | H9: 45352 | I9: TRUE | J9: =B9 -> Active SLE — high disease-activity (SLEDAI-equiv) severity | K9: =INDEX(Individuals!L2:L999, MATCH(C9,Individuals!A2:A999, 0)) -> /intake/new-patient/yamamoto-hana | L9: =K9 & "/phenotypes/" & A9 -> /intake/new-patient/yamamoto-hana/phenotypes/ph-sev-h | M9: =IF(E9 = "", "", INDEX(DiseaseStages!B2:B999, MATCH(E9,DiseaseStages!A2:A999, 0))) -> Active | N9: =IF(G9 > 7, TRUE(), FALSE()) -> TRUE | O9: =IF(M9 = "Presymptomatic", TRUE(), FALSE()) -> FALSE
A10: ph-sev-i | B10: Active SLE — biopsy-confirmed nephritis (high severity) | C10: ind-i-conteh | D10: sle | E10: sle-active | F10: kidney | G10: 8 | H10: 45352 | I10: TRUE | J10: =B10 -> Active SLE — biopsy-confirmed nephritis (high severity) | K10: =INDEX(Individuals!L2:L999, MATCH(C10,Individuals!A2:A999, 0)) -> /intake/new-patient/conteh-ibrahim | L10: =K10 & "/phenotypes/" & A10 -> /intake/new-patient/conteh-ibrahim/phenotypes/ph-sev-i | M10: =IF(E10 = "", "", INDEX(DiseaseStages!B2:B999, MATCH(E10,DiseaseStages!A2:A999, 0))) -> Active | N10: =IF(G10 > 7, TRUE(), FALSE()) -> TRUE | O10: =IF(M10 = "Presymptomatic", TRUE(), FALSE()) -> FALSE
A11: ph-sev-j | B11: Active SLE — serositis + high disease activity | C11: ind-j-brooks | D11: sle | E11: sle-active | F11: blood | G11: 8 | H11: 45352 | I11: TRUE | J11: =B11 -> Active SLE — serositis + high disease activity | K11: =INDEX(Individuals!L2:L999, MATCH(C11,Individuals!A2:A999, 0)) -> /intake/new-patient/brooks-jamal | L11: =K11 & "/phenotypes/" & A11 -> /intake/new-patient/brooks-jamal/phenotypes/ph-sev-j | M11: =IF(E11 = "", "", INDEX(DiseaseStages!B2:B999, MATCH(E11,DiseaseStages!A2:A999, 0))) -> Active | N11: =IF(G11 > 7, TRUE(), FALSE()) -> TRUE | O11: =IF(M11 = "Presymptomatic", TRUE(), FALSE()) -> FALSE
A12: ph-sev-k | B12: PsA — minimal joint involvement, mild | C12: ind-k-nair | D12: psa | E12: psa-active | F12: synovium | G12: 2 | H12: 45352 | I12: TRUE | J12: =B12 -> PsA — minimal joint involvement, mild | K12: =INDEX(Individuals!L2:L999, MATCH(C12,Individuals!A2:A999, 0)) -> /intake/new-patient/nair-kavya | L12: =K12 & "/phenotypes/" & A12 -> /intake/new-patient/nair-kavya/phenotypes/ph-sev-k | M12: =IF(E12 = "", "", INDEX(DiseaseStages!B2:B999, MATCH(E12,DiseaseStages!A2:A999, 0))) -> Active | N12: =IF(G12 > 7, TRUE(), FALSE()) -> FALSE | O12: =IF(M12 = "Presymptomatic", TRUE(), FALSE()) -> FALSE
A13: ph-sev-l | B13: PsA — moderate plaque + oligoarthritis | C13: ind-l-brandt | D13: psa | E13: psa-active | F13: skin | G13: 6 | H13: 45352 | I13: TRUE | J13: =B13 -> PsA — moderate plaque + oligoarthritis | K13: =INDEX(Individuals!L2:L999, MATCH(C13,Individuals!A2:A999, 0)) -> /intake/new-patient/brandt-lena | L13: =K13 & "/phenotypes/" & A13 -> /intake/new-patient/brandt-lena/phenotypes/ph-sev-l | M13: =IF(E13 = "", "", INDEX(DiseaseStages!B2:B999, MATCH(E13,DiseaseStages!A2:A999, 0))) -> Active | N13: =IF(G13 > 7, TRUE(), FALSE()) -> FALSE | O13: =IF(M13 = "Presymptomatic", TRUE(), FALSE()) -> FALSE

Sheet CausalMechanisms
A1: CausalMechanismId | B1: MechanismLabel | C1: Individual | D1: GenomicVariant | E1: EnvironmentalExposure | F1: MechanismType | G1: TargetPathway | H1: TargetPathwayCode | I1: HasPleiotropy | J1: Name | K1: ParentPath | L1: RelativePath | M1: IndividualAncestryLabel | N1: CountQualifiedEvidence | O1: CountModalitiesSupporting | P1: CountInterventionTargets | Q1: IsExperimentallyFalsifiable | R1: CountReplications | S1: CountConcordantReplications | T1: CountCrossAncestryConcordant | U1: ReplicationFraction | V1: ReplicatesAcrossCohorts | W1: CountNegControlTests | X1: CountNegControlSurvived | Y1: SurvivesNegativeControls | Z1: IsSpuriousDerived | AA1: CausalConfidence | AB1: VariantIsCausalCandidate | AC1: IsCausalArchitectureNode | AD1: IsAncestryTransportable | AE1: InterventionTargets | AF1: EvidenceItems | AG1: CohortReplications | AH1: NegativeControlTests
A2: cm-a | B2: IRF5 regulatory -> type-I IFN -> SLE risk | C2: ind-a-reyes | D2: var-a-irf5 | F2: regulatory | G2: type-I-IFN | H2: =IF(G2="type-I-IFN",1,IF(G2="B-cell/autoantibody",2,IF(G2="T-cell-costim",3,IF(G2="IL-17/23",4,0)))) -> 1 | I2: FALSE | J2: =B2 -> IRF5 regulatory -> type-I IFN -> SLE risk | K2: =INDEX(Individuals!L2:L999, MATCH(C2,Individuals!A2:A999, 0)) -> /intake/new-patient/reyes-ana | L2: =K2 & "/mechanisms/" & A2 -> /intake/new-patient/reyes-ana/mechanisms/cm-a | M2: =INDEX(Individuals!D2:D999, MATCH(C2,Individuals!A2:A999, 0)) -> European | N2: =COUNTIFS(EvidenceItems!C2:C999, A2,EvidenceItems!T2:T999, TRUE()) -> 3 | O2: =COUNTIFS(EvidenceItems!C2:C999, A2,EvidenceItems!G2:G999, TRUE(),EvidenceItems!T2:T999, TRUE()) -> 2 | P2: =COUNTIFS(InterventionTargets!C2:C999, A2) -> 1 | Q2: =IF(AND(P2 >= 1, N2 >= 1), TRUE(), FALSE()) -> TRUE | R2: =COUNTIFS(CohortReplications!C2:C999, A2) -> 3 | S2: =COUNTIFS(CohortReplications!C2:C999, A2,CohortReplications!K2:K999, TRUE()) -> 2 | T2: =COUNTIFS(CohortReplications!C2:C999, A2,CohortReplications!N2:N999, TRUE()) -> 2 | U2: =IF(R2 > 0, S2 / R2, 0) -> 0.66666667 | V2: =IF(AND(R2 >= 2, S2 >= 2), TRUE(), FALSE()) -> TRUE | W2: =COUNTIFS(NegativeControlTests!C2:C999, A2) -> 2 | X2: =COUNTIFS(NegativeControlTests!C2:C999, A2,NegativeControlTests!J2:J999, TRUE()) -> 2 | Y2: =IF(AND(W2 >= 1, X2 = W2), TRUE(), FALSE()) -> TRUE | Z2: =IF(OR(NOT(V2), NOT(Y2), O2 < 2, I2), TRUE(), FALSE()) -> FALSE | AA2: =IF(((0.30 * IF(N2 >= 4, 1, N2 / 4)) + (0.20 * IF(O2 >= 3, 1, O2 / 3)) + (0.30 * U2) + (0.20 * IF(Y2, 1, 0))) > 1, 1, (0.30 * IF(N2 >= 4, 1, N2 / 4)) + (0.20 * IF(O2 >= 3, 1, O2 / 3)) + (0.30 * U2) + (0.20 * IF(Y2, 1, 0))) -> 0.75833333 | AB2: =IF(D2 = "", FALSE(), INDEX(GenomicVariants!N2:N999, MATCH(D2,GenomicVariants!A2:A999, 0))) -> TRUE | AC2: =IF(AND(AA2 >= 0.7, Q2, NOT(Z2), OR(AB2, E2 <> "")), TRUE(), FALSE()) -> TRUE | AD2: =IF(AND(AC2, T2 >= 1), TRUE(), FALSE()) -> TRUE
A3: cm-b | B3: IRF5 regulatory -> type-I IFN -> SLE risk | C3: ind-b-okafor | D3: var-b-irf5 | F3: regulatory | G3: type-I-IFN | H3: =IF(G3="type-I-IFN",1,IF(G3="B-cell/autoantibody",2,IF(G3="T-cell-costim",3,IF(G3="IL-17/23",4,0)))) -> 1 | I3: FALSE | J3: =B3 -> IRF5 regulatory -> type-I IFN -> SLE risk | K3: =INDEX(Individuals!L2:L999, MATCH(C3,Individuals!A2:A999, 0)) -> /intake/new-patient/okafor-bili | L3: =K3 & "/mechanisms/" & A3 -> /intake/new-patient/okafor-bili/mechanisms/cm-b | M3: =INDEX(Individuals!D2:D999, MATCH(C3,Individuals!A2:A999, 0)) -> European | N3: =COUNTIFS(EvidenceItems!C2:C999, A3,EvidenceItems!T2:T999, TRUE()) -> 3 | O3: =COUNTIFS(EvidenceItems!C2:C999, A3,EvidenceItems!G2:G999, TRUE(),EvidenceItems!T2:T999, TRUE()) -> 2 | P3: =COUNTIFS(InterventionTargets!C2:C999, A3) -> 1 | Q3: =IF(AND(P3 >= 1, N3 >= 1), TRUE(), FALSE()) -> TRUE | R3: =COUNTIFS(CohortReplications!C2:C999, A3) -> 3 | S3: =COUNTIFS(CohortReplications!C2:C999, A3,CohortReplications!K2:K999, TRUE()) -> 2 | T3: =COUNTIFS(CohortReplications!C2:C999, A3,CohortReplications!N2:N999, TRUE()) -> 2 | U3: =IF(R3 > 0, S3 / R3, 0) -> 0.66666667 | V3: =IF(AND(R3 >= 2, S3 >= 2), TRUE(), FALSE()) -> TRUE | W3: =COUNTIFS(NegativeControlTests!C2:C999, A3) -> 2 | X3: =COUNTIFS(NegativeControlTests!C2:C999, A3,NegativeControlTests!J2:J999, TRUE()) -> 2 | Y3: =IF(AND(W3 >= 1, X3 = W3), TRUE(), FALSE()) -> TRUE | Z3: =IF(OR(NOT(V3), NOT(Y3), O3 < 2, I3), TRUE(), FALSE()) -> FALSE | AA3: =IF(((0.30 * IF(N3 >= 4, 1, N3 / 4)) + (0.20 * IF(O3 >= 3, 1, O3 / 3)) + (0.30 * U3) + (0.20 * IF(Y3, 1, 0))) > 1, 1, (0.30 * IF(N3 >= 4, 1, N3 / 4)) + (0.20 * IF(O3 >= 3, 1, O3 / 3)) + (0.30 * U3) + (0.20 * IF(Y3, 1, 0))) -> 0.75833333 | AB3: =IF(D3 = "", FALSE(), INDEX(GenomicVariants!N2:N999, MATCH(D3,GenomicVariants!A2:A999, 0))) -> TRUE | AC3: =IF(AND(AA3 >= 0.7, Q3, NOT(Z3), OR(AB3, E3 <> "")), TRUE(), FALSE()) -> TRUE | AD3: =IF(AND(AC3, T3 >= 1), TRUE(), FALSE()) -> TRUE
A4: cm-c | B4: STAT4 regulatory -> Th1/IFN -> SLE risk | C4: ind-c-chen | D4: var-c-stat4 | F4: regulatory | G4: B-cell/autoantibody | H4: =IF(G4="type-I-IFN",1,IF(G4="B-cell/autoantibody",2,IF(G4="T-cell-costim",3,IF(G4="IL-17/23",4,0)))) -> 2 | I4: FALSE | J4: =B4 -> STAT4 regulatory -> Th1/IFN -> SLE risk | K4: =INDEX(Individuals!L2:L999, MATCH(C4,Individuals!A2:A999, 0)) -> /intake/new-patient/wei-chen | L4: =K4 & "/mechanisms/" & A4 -> /intake/new-patient/wei-chen/mechanisms/cm-c | M4: =INDEX(Individuals!D2:D999, MATCH(C4,Individuals!A2:A999, 0)) -> East Asian | N4: =COUNTIFS(EvidenceItems!C2:C999, A4,EvidenceItems!T2:T999, TRUE()) -> 3 | O4: =COUNTIFS(EvidenceItems!C2:C999, A4,EvidenceItems!G2:G999, TRUE(),EvidenceItems!T2:T999, TRUE()) -> 2 | P4: =COUNTIFS(InterventionTargets!C2:C999, A4) -> 1 | Q4: =IF(AND(P4 >= 1, N4 >= 1), TRUE(), FALSE()) -> TRUE | R4: =COUNTIFS(CohortReplications!C2:C999, A4) -> 3 | S4: =COUNTIFS(CohortReplications!C2:C999, A4,CohortReplications!K2:K999, TRUE()) -> 1 | T4: =COUNTIFS(CohortReplications!C2:C999, A4,CohortReplications!N2:N999, TRUE()) -> 0 | U4: =IF(R4 > 0, S4 / R4, 0) -> 0.33333333 | V4: =IF(AND(R4 >= 2, S4 >= 2), TRUE(), FALSE()) -> FALSE | W4: =COUNTIFS(NegativeControlTests!C2:C999, A4) -> 2 | X4: =COUNTIFS(NegativeControlTests!C2:C999, A4,NegativeControlTests!J2:J999, TRUE()) -> 1 | Y4: =IF(AND(W4 >= 1, X4 = W4), TRUE(), FALSE()) -> FALSE | Z4: =IF(OR(NOT(V4), NOT(Y4), O4 < 2, I4), TRUE(), FALSE()) -> TRUE | AA4: =IF(((0.30 * IF(N4 >= 4, 1, N4 / 4)) + (0.20 * IF(O4 >= 3, 1, O4 / 3)) + (0.30 * U4) + (0.20 * IF(Y4, 1, 0))) > 1, 1, (0.30 * IF(N4 >= 4, 1, N4 / 4)) + (0.20 * IF(O4 >= 3, 1, O4 / 3)) + (0.30 * U4) + (0.20 * IF(Y4, 1, 0))) -> 0.45833333 | AB4: =IF(D4 = "", FALSE(), INDEX(GenomicVariants!N2:N999, MATCH(D4,GenomicVariants!A2:A999, 0))) -> TRUE | AC4: =IF(AND(AA4 >= 0.7, Q4, NOT(Z4), OR(AB4, E4 <> "")), TRUE(), FALSE()) -> FALSE | AD4: =IF(AND(AC4, T4 >= 1), TRUE(), FALSE()) -> FALSE
A5: cm-d | B5: IRF5 regulatory -> type-I IFN -> SLE risk | C5: ind-d-santos | D5: var-d-irf5 | F5: regulatory | G5: B-cell/autoantibody | H5: =IF(G5="type-I-IFN",1,IF(G5="B-cell/autoantibody",2,IF(G5="T-cell-costim",3,IF(G5="IL-17/23",4,0)))) -> 2 | I5: FALSE | J5: =B5 -> IRF5 regulatory -> type-I IFN -> SLE risk | K5: =INDEX(Individuals!L2:L999, MATCH(C5,Individuals!A2:A999, 0)) -> /intake/new-patient/santos-diego | L5: =K5 & "/mechanisms/" & A5 -> /intake/new-patient/santos-diego/mechanisms/cm-d | M5: =INDEX(Individuals!D2:D999, MATCH(C5,Individuals!A2:A999, 0)) -> European | N5: =COUNTIFS(EvidenceItems!C2:C999, A5,EvidenceItems!T2:T999, TRUE()) -> 3 | O5: =COUNTIFS(EvidenceItems!C2:C999, A5,EvidenceItems!G2:G999, TRUE(),EvidenceItems!T2:T999, TRUE()) -> 2 | P5: =COUNTIFS(InterventionTargets!C2:C999, A5) -> 1 | Q5: =IF(AND(P5 >= 1, N5 >= 1), TRUE(), FALSE()) -> TRUE | R5: =COUNTIFS(CohortReplications!C2:C999, A5) -> 3 | S5: =COUNTIFS(CohortReplications!C2:C999, A5,CohortReplications!K2:K999, TRUE()) -> 2 | T5: =COUNTIFS(CohortReplications!C2:C999, A5,CohortReplications!N2:N999, TRUE()) -> 2 | U5: =IF(R5 > 0, S5 / R5, 0) -> 0.66666667 | V5: =IF(AND(R5 >= 2, S5 >= 2), TRUE(), FALSE()) -> TRUE | W5: =COUNTIFS(NegativeControlTests!C2:C999, A5) -> 2 | X5: =COUNTIFS(NegativeControlTests!C2:C999, A5,NegativeControlTests!J2:J999, TRUE()) -> 2 | Y5: =IF(AND(W5 >= 1, X5 = W5), TRUE(), FALSE()) -> TRUE | Z5: =IF(OR(NOT(V5), NOT(Y5), O5 < 2, I5), TRUE(), FALSE()) -> FALSE | AA5: =IF(((0.30 * IF(N5 >= 4, 1, N5 / 4)) + (0.20 * IF(O5 >= 3, 1, O5 / 3)) + (0.30 * U5) + (0.20 * IF(Y5, 1, 0))) > 1, 1, (0.30 * IF(N5 >= 4, 1, N5 / 4)) + (0.20 * IF(O5 >= 3, 1, O5 / 3)) + (0.30 * U5) + (0.20 * IF(Y5, 1, 0))) -> 0.75833333 | AB5: =IF(D5 = "", FALSE(), INDEX(GenomicVariants!N2:N999, MATCH(D5,GenomicVariants!A2:A999, 0))) -> TRUE | AC5: =IF(AND(AA5 >= 0.7, Q5, NOT(Z5), OR(AB5, E5 <> "")), TRUE(), FALSE()) -> TRUE | AD5: =IF(AND(AC5, T5 >= 1), TRUE(), FALSE()) -> TRUE
A6: cm-e | B6: CTLA4 enhancer -> T-cell costimulation -> SLE risk | C6: ind-e-mensah | D6: var-e-ctla4 | F6: regulatory | G6: T-cell-costim | H6: =IF(G6="type-I-IFN",1,IF(G6="B-cell/autoantibody",2,IF(G6="T-cell-costim",3,IF(G6="IL-17/23",4,0)))) -> 3 | I6: FALSE | J6: =B6 -> CTLA4 enhancer -> T-cell costimulation -> SLE risk | K6: =INDEX(Individuals!L2:L999, MATCH(C6,Individuals!A2:A999, 0)) -> /intake/new-patient/mensah-esi | L6: =K6 & "/mechanisms/" & A6 -> /intake/new-patient/mensah-esi/mechanisms/cm-e | M6: =INDEX(Individuals!D2:D999, MATCH(C6,Individuals!A2:A999, 0)) -> African | N6: =COUNTIFS(EvidenceItems!C2:C999, A6,EvidenceItems!T2:T999, TRUE()) -> 3 | O6: =COUNTIFS(EvidenceItems!C2:C999, A6,EvidenceItems!G2:G999, TRUE(),EvidenceItems!T2:T999, TRUE()) -> 2 | P6: =COUNTIFS(InterventionTargets!C2:C999, A6) -> 0 | Q6: =IF(AND(P6 >= 1, N6 >= 1), TRUE(), FALSE()) -> FALSE | R6: =COUNTIFS(CohortReplications!C2:C999, A6) -> 3 | S6: =COUNTIFS(CohortReplications!C2:C999, A6,CohortReplications!K2:K999, TRUE()) -> 2 | T6: =COUNTIFS(CohortReplications!C2:C999, A6,CohortReplications!N2:N999, TRUE()) -> 2 | U6: =IF(R6 > 0, S6 / R6, 0) -> 0.66666667 | V6: =IF(AND(R6 >= 2, S6 >= 2), TRUE(), FALSE()) -> TRUE | W6: =COUNTIFS(NegativeControlTests!C2:C999, A6) -> 2 | X6: =COUNTIFS(NegativeControlTests!C2:C999, A6,NegativeControlTests!J2:J999, TRUE()) -> 2 | Y6: =IF(AND(W6 >= 1, X6 = W6), TRUE(), FALSE()) -> TRUE | Z6: =IF(OR(NOT(V6), NOT(Y6), O6 < 2, I6), TRUE(), FALSE()) -> FALSE | AA6: =IF(((0.30 * IF(N6 >= 4, 1, N6 / 4)) + (0.20 * IF(O6 >= 3, 1, O6 / 3)) + (0.30 * U6) + (0.20 * IF(Y6, 1, 0))) > 1, 1, (0.30 * IF(N6 >= 4, 1, N6 / 4)) + (0.20 * IF(O6 >= 3, 1, O6 / 3)) + (0.30 * U6) + (0.20 * IF(Y6, 1, 0))) -> 0.75833333 | AB6: =IF(D6 = "", FALSE(), INDEX(GenomicVariants!N2:N999, MATCH(D6,GenomicVariants!A2:A999, 0))) -> TRUE | AC6: =IF(AND(AA6 >= 0.7, Q6, NOT(Z6), OR(AB6, E6 <> "")), TRUE(), FALSE()) -> FALSE | AD6: =IF(AND(AC6, T6 >= 1), TRUE(), FALSE()) -> FALSE
A7: cm-f | B7: IL23R regulatory -> IL-17 axis -> PsA risk | C7: ind-f-haidar | D7: var-f-il23r | F7: regulatory | G7: IL-17/23 | H7: =IF(G7="type-I-IFN",1,IF(G7="B-cell/autoantibody",2,IF(G7="T-cell-costim",3,IF(G7="IL-17/23",4,0)))) -> 4 | I7: FALSE | J7: =B7 -> IL23R regulatory -> IL-17 axis -> PsA risk | K7: =INDEX(Individuals!L2:L999, MATCH(C7,Individuals!A2:A999, 0)) -> /intake/new-patient/haidar-faisal | L7: =K7 & "/mechanisms/" & A7 -> /intake/new-patient/haidar-faisal/mechanisms/cm-f | M7: =INDEX(Individuals!D2:D999, MATCH(C7,Individuals!A2:A999, 0)) -> Indigenous American | N7: =COUNTIFS(EvidenceItems!C2:C999, A7,EvidenceItems!T2:T999, TRUE()) -> 3 | O7: =COUNTIFS(EvidenceItems!C2:C999, A7,EvidenceItems!G2:G999, TRUE(),EvidenceItems!T2:T999, TRUE()) -> 2 | P7: =COUNTIFS(InterventionTargets!C2:C999, A7) -> 1 | Q7: =IF(AND(P7 >= 1, N7 >= 1), TRUE(), FALSE()) -> TRUE | R7: =COUNTIFS(CohortReplications!C2:C999, A7) -> 3 | S7: =COUNTIFS(CohortReplications!C2:C999, A7,CohortReplications!K2:K999, TRUE()) -> 3 | T7: =COUNTIFS(CohortReplications!C2:C999, A7,CohortReplications!N2:N999, TRUE()) -> 0 | U7: =IF(R7 > 0, S7 / R7, 0) -> 1 | V7: =IF(AND(R7 >= 2, S7 >= 2), TRUE(), FALSE()) -> TRUE | W7: =COUNTIFS(NegativeControlTests!C2:C999, A7) -> 2 | X7: =COUNTIFS(NegativeControlTests!C2:C999, A7,NegativeControlTests!J2:J999, TRUE()) -> 2 | Y7: =IF(AND(W7 >= 1, X7 = W7), TRUE(), FALSE()) -> TRUE | Z7: =IF(OR(NOT(V7), NOT(Y7), O7 < 2, I7), TRUE(), FALSE()) -> FALSE | AA7: =IF(((0.30 * IF(N7 >= 4, 1, N7 / 4)) + (0.20 * IF(O7 >= 3, 1, O7 / 3)) + (0.30 * U7) + (0.20 * IF(Y7, 1, 0))) > 1, 1, (0.30 * IF(N7 >= 4, 1, N7 / 4)) + (0.20 * IF(O7 >= 3, 1, O7 / 3)) + (0.30 * U7) + (0.20 * IF(Y7, 1, 0))) -> 0.85833333 | AB7: =IF(D7 = "", FALSE(), INDEX(GenomicVariants!N2:N999, MATCH(D7,GenomicVariants!A2:A999, 0))) -> TRUE | AC7: =IF(AND(AA7 >= 0.7, Q7, NOT(Z7), OR(AB7, E7 <> "")), TRUE(), FALSE()) -> TRUE | AD7: =IF(AND(AC7, T7 >= 1), TRUE(), FALSE()) -> FALSE
A8: cm-g | B8: IL23R regulatory -> IL-17 axis -> PsA risk | C8: ind-g-lin | D8: var-g-il23r | F8: regulatory | G8: IL-17/23 | H8: =IF(G8="type-I-IFN",1,IF(G8="B-cell/autoantibody",2,IF(G8="T-cell-costim",3,IF(G8="IL-17/23",4,0)))) -> 4 | I8: FALSE | J8: =B8 -> IL23R regulatory -> IL-17 axis -> PsA risk | K8: =INDEX(Individuals!L2:L999, MATCH(C8,Individuals!A2:A999, 0)) -> /intake/new-patient/lin-grace | L8: =K8 & "/mechanisms/" & A8 -> /intake/new-patient/lin-grace/mechanisms/cm-g | M8: =INDEX(Individuals!D2:D999, MATCH(C8,Individuals!A2:A999, 0)) -> Indigenous American | N8: =COUNTIFS(EvidenceItems!C2:C999, A8,EvidenceItems!T2:T999, TRUE()) -> 3 | O8: =COUNTIFS(EvidenceItems!C2:C999, A8,EvidenceItems!G2:G999, TRUE(),EvidenceItems!T2:T999, TRUE()) -> 2 | P8: =COUNTIFS(InterventionTargets!C2:C999, A8) -> 1 | Q8: =IF(AND(P8 >= 1, N8 >= 1), TRUE(), FALSE()) -> TRUE | R8: =COUNTIFS(CohortReplications!C2:C999, A8) -> 3 | S8: =COUNTIFS(CohortReplications!C2:C999, A8,CohortReplications!K2:K999, TRUE()) -> 3 | T8: =COUNTIFS(CohortReplications!C2:C999, A8,CohortReplications!N2:N999, TRUE()) -> 2 | U8: =IF(R8 > 0, S8 / R8, 0) -> 1 | V8: =IF(AND(R8 >= 2, S8 >= 2), TRUE(), FALSE()) -> TRUE | W8: =COUNTIFS(NegativeControlTests!C2:C999, A8) -> 2 | X8: =COUNTIFS(NegativeControlTests!C2:C999, A8,NegativeControlTests!J2:J999, TRUE()) -> 2 | Y8: =IF(AND(W8 >= 1, X8 = W8), TRUE(), FALSE()) -> TRUE | Z8: =IF(OR(NOT(V8), NOT(Y8), O8 < 2, I8), TRUE(), FALSE()) -> FALSE | AA8: =IF(((0.30 * IF(N8 >= 4, 1, N8 / 4)) + (0.20 * IF(O8 >= 3, 1, O8 / 3)) + (0.30 * U8) + (0.20 * IF(Y8, 1, 0))) > 1, 1, (0.30 * IF(N8 >= 4, 1, N8 / 4)) + (0.20 * IF(O8 >= 3, 1, O8 / 3)) + (0.30 * U8) + (0.20 * IF(Y8, 1, 0))) -> 0.85833333 | AB8: =IF(D8 = "", FALSE(), INDEX(GenomicVariants!N2:N999, MATCH(D8,GenomicVariants!A2:A999, 0))) -> TRUE | AC8: =IF(AND(AA8 >= 0.7, Q8, NOT(Z8), OR(AB8, E8 <> "")), TRUE(), FALSE()) -> TRUE | AD8: =IF(AND(AC8, T8 >= 1), TRUE(), FALSE()) -> TRUE
A9: cm-h | B9: IRF5 regulatory -> type-I IFN -> SLE risk | C9: ind-h-yamamoto | D9: var-h-irf5 | F9: regulatory | G9: type-I-IFN | H9: =IF(G9="type-I-IFN",1,IF(G9="B-cell/autoantibody",2,IF(G9="T-cell-costim",3,IF(G9="IL-17/23",4,0)))) -> 1 | I9: FALSE | J9: =B9 -> IRF5 regulatory -> type-I IFN -> SLE risk | K9: =INDEX(Individuals!L2:L999, MATCH(C9,Individuals!A2:A999, 0)) -> /intake/new-patient/yamamoto-hana | L9: =K9 & "/mechanisms/" & A9 -> /intake/new-patient/yamamoto-hana/mechanisms/cm-h | M9: =INDEX(Individuals!D2:D999, MATCH(C9,Individuals!A2:A999, 0)) -> East Asian | N9: =COUNTIFS(EvidenceItems!C2:C999, A9,EvidenceItems!T2:T999, TRUE()) -> 3 | O9: =COUNTIFS(EvidenceItems!C2:C999, A9,EvidenceItems!G2:G999, TRUE(),EvidenceItems!T2:T999, TRUE()) -> 2 | P9: =COUNTIFS(InterventionTargets!C2:C999, A9) -> 1 | Q9: =IF(AND(P9 >= 1, N9 >= 1), TRUE(), FALSE()) -> TRUE | R9: =COUNTIFS(CohortReplications!C2:C999, A9) -> 3 | S9: =COUNTIFS(CohortReplications!C2:C999, A9,CohortReplications!K2:K999, TRUE()) -> 2 | T9: =COUNTIFS(CohortReplications!C2:C999, A9,CohortReplications!N2:N999, TRUE()) -> 1 | U9: =IF(R9 > 0, S9 / R9, 0) -> 0.66666667 | V9: =IF(AND(R9 >= 2, S9 >= 2), TRUE(), FALSE()) -> TRUE | W9: =COUNTIFS(NegativeControlTests!C2:C999, A9) -> 2 | X9: =COUNTIFS(NegativeControlTests!C2:C999, A9,NegativeControlTests!J2:J999, TRUE()) -> 2 | Y9: =IF(AND(W9 >= 1, X9 = W9), TRUE(), FALSE()) -> TRUE | Z9: =IF(OR(NOT(V9), NOT(Y9), O9 < 2, I9), TRUE(), FALSE()) -> FALSE | AA9: =IF(((0.30 * IF(N9 >= 4, 1, N9 / 4)) + (0.20 * IF(O9 >= 3, 1, O9 / 3)) + (0.30 * U9) + (0.20 * IF(Y9, 1, 0))) > 1, 1, (0.30 * IF(N9 >= 4, 1, N9 / 4)) + (0.20 * IF(O9 >= 3, 1, O9 / 3)) + (0.30 * U9) + (0.20 * IF(Y9, 1, 0))) -> 0.75833333 | AB9: =IF(D9 = "", FALSE(), INDEX(GenomicVariants!N2:N999, MATCH(D9,GenomicVariants!A2:A999, 0))) -> TRUE | AC9: =IF(AND(AA9 >= 0.7, Q9, NOT(Z9), OR(AB9, E9 <> "")), TRUE(), FALSE()) -> TRUE | AD9: =IF(AND(AC9, T9 >= 1), TRUE(), FALSE()) -> TRUE
A10: cm-i | B10: IRF5 regulatory -> type-I IFN -> SLE risk | C10: ind-i-conteh | D10: var-i-irf5 | F10: regulatory | G10: B-cell/autoantibody | H10: =IF(G10="type-I-IFN",1,IF(G10="B-cell/autoantibody",2,IF(G10="T-cell-costim",3,IF(G10="IL-17/23",4,0)))) -> 2 | I10: FALSE | J10: =B10 -> IRF5 regulatory -> type-I IFN -> SLE risk | K10: =INDEX(Individuals!L2:L999, MATCH(C10,Individuals!A2:A999, 0)) -> /intake/new-patient/conteh-ibrahim | L10: =K10 & "/mechanisms/" & A10 -> /intake/new-patient/conteh-ibrahim/mechanisms/cm-i | M10: =INDEX(Individuals!D2:D999, MATCH(C10,Individuals!A2:A999, 0)) -> African | N10: =COUNTIFS(EvidenceItems!C2:C999, A10,EvidenceItems!T2:T999, TRUE()) -> 3 | O10: =COUNTIFS(EvidenceItems!C2:C999, A10,EvidenceItems!G2:G999, TRUE(),EvidenceItems!T2:T999, TRUE()) -> 2 | P10: =COUNTIFS(InterventionTargets!C2:C999, A10) -> 1 | Q10: =IF(AND(P10 >= 1, N10 >= 1), TRUE(), FALSE()) -> TRUE | R10: =COUNTIFS(CohortReplications!C2:C999, A10) -> 3 | S10: =COUNTIFS(CohortReplications!C2:C999, A10,CohortReplications!K2:K999, TRUE()) -> 2 | T10: =COUNTIFS(CohortReplications!C2:C999, A10,CohortReplications!N2:N999, TRUE()) -> 1 | U10: =IF(R10 > 0, S10 / R10, 0) -> 0.66666667 | V10: =IF(AND(R10 >= 2, S10 >= 2), TRUE(), FALSE()) -> TRUE | W10: =COUNTIFS(NegativeControlTests!C2:C999, A10) -> 2 | X10: =COUNTIFS(NegativeControlTests!C2:C999, A10,NegativeControlTests!J2:J999, TRUE()) -> 2 | Y10: =IF(AND(W10 >= 1, X10 = W10), TRUE(), FALSE()) -> TRUE | Z10: =IF(OR(NOT(V10), NOT(Y10), O10 < 2, I10), TRUE(), FALSE()) -> FALSE | AA10: =IF(((0.30 * IF(N10 >= 4, 1, N10 / 4)) + (0.20 * IF(O10 >= 3, 1, O10 / 3)) + (0.30 * U10) + (0.20 * IF(Y10, 1, 0))) > 1, 1, (0.30 * IF(N10 >= 4, 1, N10 / 4)) + (0.20 * IF(O10 >= 3, 1, O10 / 3)) + (0.30 * U10) + (0.20 * IF(Y10, 1, 0))) -> 0.75833333 | AB10: =IF(D10 = "", FALSE(), INDEX(GenomicVariants!N2:N999, MATCH(D10,GenomicVariants!A2:A999, 0))) -> TRUE | AC10: =IF(AND(AA10 >= 0.7, Q10, NOT(Z10), OR(AB10, E10 <> "")), TRUE(), FALSE()) -> TRUE | AD10: =IF(AND(AC10, T10 >= 1), TRUE(), FALSE()) -> TRUE
A11: cm-j | B11: IRF5 regulatory -> type-I IFN -> SLE risk | C11: ind-j-brooks | D11: var-j-irf5 | F11: regulatory | G11: type-I-IFN | H11: =IF(G11="type-I-IFN",1,IF(G11="B-cell/autoantibody",2,IF(G11="T-cell-costim",3,IF(G11="IL-17/23",4,0)))) -> 1 | I11: FALSE | J11: =B11 -> IRF5 regulatory -> type-I IFN -> SLE risk | K11: =INDEX(Individuals!L2:L999, MATCH(C11,Individuals!A2:A999, 0)) -> /intake/new-patient/brooks-jamal | L11: =K11 & "/mechanisms/" & A11 -> /intake/new-patient/brooks-jamal/mechanisms/cm-j | M11: =INDEX(Individuals!D2:D999, MATCH(C11,Individuals!A2:A999, 0)) -> Hispanic/Latino | N11: =COUNTIFS(EvidenceItems!C2:C999, A11,EvidenceItems!T2:T999, TRUE()) -> 3 | O11: =COUNTIFS(EvidenceItems!C2:C999, A11,EvidenceItems!G2:G999, TRUE(),EvidenceItems!T2:T999, TRUE()) -> 2 | P11: =COUNTIFS(InterventionTargets!C2:C999, A11) -> 1 | Q11: =IF(AND(P11 >= 1, N11 >= 1), TRUE(), FALSE()) -> TRUE | R11: =COUNTIFS(CohortReplications!C2:C999, A11) -> 3 | S11: =COUNTIFS(CohortReplications!C2:C999, A11,CohortReplications!K2:K999, TRUE()) -> 2 | T11: =COUNTIFS(CohortReplications!C2:C999, A11,CohortReplications!N2:N999, TRUE()) -> 2 | U11: =IF(R11 > 0, S11 / R11, 0) -> 0.66666667 | V11: =IF(AND(R11 >= 2, S11 >= 2), TRUE(), FALSE()) -> TRUE | W11: =COUNTIFS(NegativeControlTests!C2:C999, A11) -> 2 | X11: =COUNTIFS(NegativeControlTests!C2:C999, A11,NegativeControlTests!J2:J999, TRUE()) -> 2 | Y11: =IF(AND(W11 >= 1, X11 = W11), TRUE(), FALSE()) -> TRUE | Z11: =IF(OR(NOT(V11), NOT(Y11), O11 < 2, I11), TRUE(), FALSE()) -> FALSE | AA11: =IF(((0.30 * IF(N11 >= 4, 1, N11 / 4)) + (0.20 * IF(O11 >= 3, 1, O11 / 3)) + (0.30 * U11) + (0.20 * IF(Y11, 1, 0))) > 1, 1, (0.30 * IF(N11 >= 4, 1, N11 / 4)) + (0.20 * IF(O11 >= 3, 1, O11 / 3)) + (0.30 * U11) + (0.20 * IF(Y11, 1, 0))) -> 0.75833333 | AB11: =IF(D11 = "", FALSE(), INDEX(GenomicVariants!N2:N999, MATCH(D11,GenomicVariants!A2:A999, 0))) -> TRUE | AC11: =IF(AND(AA11 >= 0.7, Q11, NOT(Z11), OR(AB11, E11 <> "")), TRUE(), FALSE()) -> TRUE | AD11: =IF(AND(AC11, T11 >= 1), TRUE(), FALSE()) -> TRUE
A12: cm-k | B12: IL23R regulatory -> IL-17 axis -> PsA risk | C12: ind-k-nair | D12: var-k-il23r | F12: regulatory | G12: IL-17/23 | H12: =IF(G12="type-I-IFN",1,IF(G12="B-cell/autoantibody",2,IF(G12="T-cell-costim",3,IF(G12="IL-17/23",4,0)))) -> 4 | I12: FALSE | J12: =B12 -> IL23R regulatory -> IL-17 axis -> PsA risk | K12: =INDEX(Individuals!L2:L999, MATCH(C12,Individuals!A2:A999, 0)) -> /intake/new-patient/nair-kavya | L12: =K12 & "/mechanisms/" & A12 -> /intake/new-patient/nair-kavya/mechanisms/cm-k | M12: =INDEX(Individuals!D2:D999, MATCH(C12,Individuals!A2:A999, 0)) -> South Asian | N12: =COUNTIFS(EvidenceItems!C2:C999, A12,EvidenceItems!T2:T999, TRUE()) -> 3 | O12: =COUNTIFS(EvidenceItems!C2:C999, A12,EvidenceItems!G2:G999, TRUE(),EvidenceItems!T2:T999, TRUE()) -> 2 | P12: =COUNTIFS(InterventionTargets!C2:C999, A12) -> 1 | Q12: =IF(AND(P12 >= 1, N12 >= 1), TRUE(), FALSE()) -> TRUE | R12: =COUNTIFS(CohortReplications!C2:C999, A12) -> 3 | S12: =COUNTIFS(CohortReplications!C2:C999, A12,CohortReplications!K2:K999, TRUE()) -> 3 | T12: =COUNTIFS(CohortReplications!C2:C999, A12,CohortReplications!N2:N999, TRUE()) -> 0 | U12: =IF(R12 > 0, S12 / R12, 0) -> 1 | V12: =IF(AND(R12 >= 2, S12 >= 2), TRUE(), FALSE()) -> TRUE | W12: =COUNTIFS(NegativeControlTests!C2:C999, A12) -> 2 | X12: =COUNTIFS(NegativeControlTests!C2:C999, A12,NegativeControlTests!J2:J999, TRUE()) -> 2 | Y12: =IF(AND(W12 >= 1, X12 = W12), TRUE(), FALSE()) -> TRUE | Z12: =IF(OR(NOT(V12), NOT(Y12), O12 < 2, I12), TRUE(), FALSE()) -> FALSE | AA12: =IF(((0.30 * IF(N12 >= 4, 1, N12 / 4)) + (0.20 * IF(O12 >= 3, 1, O12 / 3)) + (0.30 * U12) + (0.20 * IF(Y12, 1, 0))) > 1, 1, (0.30 * IF(N12 >= 4, 1, N12 / 4)) + (0.20 * IF(O12 >= 3, 1, O12 / 3)) + (0.30 * U12) + (0.20 * IF(Y12, 1, 0))) -> 0.85833333 | AB12: =IF(D12 = "", FALSE(), INDEX(GenomicVariants!N2:N999, MATCH(D12,GenomicVariants!A2:A999, 0))) -> TRUE | AC12: =IF(AND(AA12 >= 0.7, Q12, NOT(Z12), OR(AB12, E12 <> "")), TRUE(), FALSE()) -> TRUE | AD12: =IF(AND(AC12, T12 >= 1), TRUE(), FALSE()) -> FALSE
A13: cm-l | B13: IL23R regulatory -> IL-17 axis -> PsA risk | C13: ind-l-brandt | D13: var-l-il23r | F13: regulatory | G13: IL-17/23 | H13: =IF(G13="type-I-IFN",1,IF(G13="B-cell/autoantibody",2,IF(G13="T-cell-costim",3,IF(G13="IL-17/23",4,0)))) -> 4 | I13: FALSE | J13: =B13 -> IL23R regulatory -> IL-17 axis -> PsA risk | K13: =INDEX(Individuals!L2:L999, MATCH(C13,Individuals!A2:A999, 0)) -> /intake/new-patient/brandt-lena | L13: =K13 & "/mechanisms/" & A13 -> /intake/new-patient/brandt-lena/mechanisms/cm-l | M13: =INDEX(Individuals!D2:D999, MATCH(C13,Individuals!A2:A999, 0)) -> Indigenous American | N13: =COUNTIFS(EvidenceItems!C2:C999, A13,EvidenceItems!T2:T999, TRUE()) -> 3 | O13: =COUNTIFS(EvidenceItems!C2:C999, A13,EvidenceItems!G2:G999, TRUE(),EvidenceItems!T2:T999, TRUE()) -> 2 | P13: =COUNTIFS(InterventionTargets!C2:C999, A13) -> 1 | Q13: =IF(AND(P13 >= 1, N13 >= 1), TRUE(), FALSE()) -> TRUE | R13: =COUNTIFS(CohortReplications!C2:C999, A13) -> 3 | S13: =COUNTIFS(CohortReplications!C2:C999, A13,CohortReplications!K2:K999, TRUE()) -> 3 | T13: =COUNTIFS(CohortReplications!C2:C999, A13,CohortReplications!N2:N999, TRUE()) -> 2 | U13: =IF(R13 > 0, S13 / R13, 0) -> 1 | V13: =IF(AND(R13 >= 2, S13 >= 2), TRUE(), FALSE()) -> TRUE | W13: =COUNTIFS(NegativeControlTests!C2:C999, A13) -> 2 | X13: =COUNTIFS(NegativeControlTests!C2:C999, A13,NegativeControlTests!J2:J999, TRUE()) -> 2 | Y13: =IF(AND(W13 >= 1, X13 = W13), TRUE(), FALSE()) -> TRUE | Z13: =IF(OR(NOT(V13), NOT(Y13), O13 < 2, I13), TRUE(), FALSE()) -> FALSE | AA13: =IF(((0.30 * IF(N13 >= 4, 1, N13 / 4)) + (0.20 * IF(O13 >= 3, 1, O13 / 3)) + (0.30 * U13) + (0.20 * IF(Y13, 1, 0))) > 1, 1, (0.30 * IF(N13 >= 4, 1, N13 / 4)) + (0.20 * IF(O13 >= 3, 1, O13 / 3)) + (0.30 * U13) + (0.20 * IF(Y13, 1, 0))) -> 0.85833333 | AB13: =IF(D13 = "", FALSE(), INDEX(GenomicVariants!N2:N999, MATCH(D13,GenomicVariants!A2:A999, 0))) -> TRUE | AC13: =IF(AND(AA13 >= 0.7, Q13, NOT(Z13), OR(AB13, E13 <> "")), TRUE(), FALSE()) -> TRUE | AD13: =IF(AND(AC13, T13 >= 1), TRUE(), FALSE()) -> TRUE

Sheet EpistaticInteractions
A1: EpistaticInteractionId | B1: InteractionLabel | C1: Individual | D1: PrimaryVariant | E1: SecondaryVariant | F1: EpistasisScore | G1: HasPleiotropy | H1: Name | I1: ParentPath | J1: RelativePath | K1: IsHighOrderEpistasis
A2: epi-context | B2: IRF5 x STAT4 (context only) | C2: ind-a-reyes | D2: var-a-irf5 | E2: var-c-stat4 | F2: 0.4 | G2: FALSE | H2: =B2 -> IRF5 x STAT4 (context only) | I2: =INDEX(Individuals!L2:L999, MATCH(C2,Individuals!A2:A999, 0)) -> /intake/new-patient/reyes-ana | J2: =I2 & "/epistasis/" & A2 -> /intake/new-patient/reyes-ana/epistasis/epi-context | K2: =IF(F2 > 0.5, TRUE(), FALSE()) -> FALSE

Sheet CounterfactualTrajectories
A1: CounterfactualTrajectoryId | B1: TrajectoryLabel | C1: Individual | D1: AutoimmuneDisease | E1: ProjectedSeverity | F1: HorizonMonths | G1: InterventionApplied | H1: Name | I1: ParentPath | J1: RelativePath | K1: AutoimmuneDiseaseLabel | L1: IsWorseningTrajectory
A2: cf-context | B2: Untreated SLE projection (context only) | C2: ind-a-reyes | D2: sle | E2: 6 | F2: 12 | G2: none | H2: =B2 -> Untreated SLE projection (context only) | I2: =INDEX(Individuals!L2:L999, MATCH(C2,Individuals!A2:A999, 0)) -> /intake/new-patient/reyes-ana | J2: =I2 & "/trajectories/" & A2 -> /intake/new-patient/reyes-ana/trajectories/cf-context | K2: =INDEX(AutoimmuneDiseases!B2:B999, MATCH(D2,AutoimmuneDiseases!A2:A999, 0)) -> Systemic Lupus Erythematosus | L2: =IF(E2 > 7, TRUE(), FALSE()) -> FALSE

Sheet IndividualPredictions
A1: IndividualPredictionId | B1: PredictionLabel | C1: Individual | D1: AutoimmuneDisease | E1: PredictionType | F1: Name | G1: ParentPath | H1: RelativePath | I1: IndividualAncestryLabel | J1: IsAncestryHoldout | K1: IndividualCausalMass | L1: IndividualConfirmedNodeCount | M1: IndividualCrossAncestryNodeCount | N1: IndividualHasCrypticRelatedness | O1: IndividualMaxSeverityScore | P1: IndividualHasHighSeverityPhenotype | Q1: IndividualHasPredictedTreatmentResponse | R1: PredictedValue | S1: CountBins | T1: CountWellCalibratedBins | U1: SumBinAbsError | V1: MeanBinAbsError | W1: WellCalibratedFraction | X1: CalibratedUncertainty | Y1: RestsOnConfirmedMechanism | Z1: HasSpuriousCorrelationFlag | AA1: IsFalsifiabilityBacked | AB1: IsTransportableToAbsentAncestry | AC1: IsAncestryTransportSafe | AD1: TransportGateStatus | AE1: IsHighConfidencePrediction | AF1: PatientStratificationTier | AG1: PredictedSeverityValue | AH1: SeverityTier | AI1: IsSeverityActionable | AJ1: SeverityDecidingFactor | AK1: IsTreatmentResponseActionable | AL1: TreatmentResponseDecidingFactor | AM1: IsClinicallyActionable | AN1: LifecycleStateKey | AO1: DecidingGate | AP1: CalibrationBins | AQ1: IndividualTargetPathway | AR1: IndividualProgressionStateKey | AS1: IndividualIsDiseaseProgressing | AT1: RecommendedTreatmentLine | AU1: TreatmentLineDecidingFactor | AV1: ProgressionVsActionabilityDisagree
